Workbook

Sheet CRM1
A1: Номер п/п | B1: Название статьи затрат | C1: 1 квартал | D1: 2 квартал | E1: 3 квартал | F1: 4 квартал | G1: Год
A2: CAPEX
A4: 2 | B4: Программное обеспечение | C4: 85000 | D4: 100000 | E4: 90000 | F4: 0 | G4: 275000
A5: 3 | B5: ТМЦ | C5: 4000 | D5: 15000 | E5: 35000 | F5: 30000 | G5: 84000
A6: 4 | B6: Услуги сторонних организаций | C6: 0 | D6: 0 | E6: 0 | F6: 0 | G6: 0
A7: 5 | B7: Прочее | C7: 15000 | D7: 35000 | E7: 10000 | F7: 0 | G7: 60000
B8: Итого: | C8: =SUM(C4:C7) -> 104000 | D8: =SUM(D4:D7) -> 150000 | E8: =SUM(E4:E7) -> 135000 | F8: =SUM(F4:F7) -> 30000 | G8: =SUM(G4:G7) -> 419000
A9: OPEX
A10: 1 | B10: Оборудование | C10: 0 | D10: 0 | E10: 0 | F10: 0 | G10: 0
A11: 2 | B11: Программное обеспечение | C11: 0 | D11: 0 | E11: 0 | F11: 0 | G11: 0
A12: 3 | B12: ТМЦ | C12: 0 | D12: 0 | E12: 0 | F12: 0 | G12: 0
A13: 4 | B13: Услуги сторонних организаций | C13: 36000 | D13: 82000 | E13: 123200 | F13: 57600 | G13: 298800
A14: 5 | B14: Прочее | C14: 18000 | D14: 21000 | E14: 36300 | F14: 25500 | G14: 100800
B15: Итого: | C15: =SUM(C10:C14) -> 54000 | D15: =SUM(D10:D14) -> 103000 | E15: =SUM(E10:E14) -> 159500 | F15: =SUM(F10:F14) -> 83100 | G15: =SUM(G10:G14) -> 399600

Sheet СППР
A1: Номер п/п | B1: Название статьи затрат | C1: 1 квартал | D1: 2 квартал | E1: 3 квартал | F1: 4 квартал | G1: Год
A2: CAPEX
A3: 1 | B3: Оборудование | C3: 1500000 | D3: 500000 | E3: 0 | F3: 0 | G3: 2000000
A4: 2 | B4: Программное обеспечение | C4: 500000 | D4: 1000000 | E4: 0 | F4: 0 | G4: 1500000
A5: 3 | B5: ТМЦ | C5: 200000 | D5: 300000 | E5: 0 | F5: 0 | G5: 500000
A6: 4 | B6: Услуги сторонних организаций | C6: 200000 | D6: 300000 | E6: 0 | F6: 0 | G6: 500000
A7: 5 | B7: Прочее | C7: 200000 | D7: 0 | E7: 0 | F7: 0 | G7: 200000
B8: Итого: | C8: =SUM(C3:C7) -> 2600000 | D8: =SUM(D3:D7) -> 2100000 | E8: =SUM(E3:E7) -> 0 | F8: =SUM(F3:F7) -> 0 | G8: =SUM(G3:G7) -> 4700000
A9: OPEX
A10: 1 | B10: Оборудование | C10: 50000 | D10: 50000 | E10: 50000 | F10: 50000 | G10: 200000
A11: 2 | B11: Программное обеспечение | C11: 80000 | D11: 80000 | E11: 80000 | F11: 80000 | G11: 320000
A12: 3 | B12: ТМЦ | C12: 30000 | D12: 30000 | E12: 30000 | F12: 30000 | G12: 120000
A13: 4 | B13: Услуги сторонних организаций | C13: 100000 | D13: 100000 | E13: 100000 | F13: 10000 | G13: 400000
A14: 5 | B14: Прочее | C14: 20000 | D14: 20000 | E14: 20000 | F14: 20000 | G14: 80000
B15: Итого: | C15: =SUM(C10:C14) -> 280000 | D15: =SUM(C10:C14) -> 280000 | E15: =SUM(D10:D14) -> 280000 | F15: 190000 | G15: =SUM(F10:F14) -> 190000

Sheet QMS
A1: Номер п/п | B1: Название статьи затрат | C1: 1 квартал | D1: 2 квартал | E1: 3 квартал | F1: 4 квартал | G1: Год
A2: CAPEX
A3: 1 | B3: Оборудование | C3: 80000 | D3: 70000 | E3: 0 | F3: 0 | G3: 150000
A4: 2 | B4: Программное обеспечение (QMS, интеграции с DevManager и баг-трекером) | C4: 120000 | D4: 120000 | E4: 60 000 ₽ | F4: 0 | G4: 300000
A5: 3 | B5: ТМЦ (доп. накопители, периферия, тестовое оборудование) | C5: 20000 | D5: 15000 | E5: 15 000 ₽ | F5: 0 | G5: 50000
A6: 4 | B6: Услуги сторонних организаций (внедрение, настройка, обучение) | C6: 60000 | D6: 60000 | E6: 30 000 ₽ | F6: 0 | G6: 150000
A7: 5 | B7: Прочее (документация, тестовые среды, пилотные проекты) | C7: 10000 | D7: 10000 | E7: 0 | F7: 0 | G7: 20000
B8: Итого: | C8: =SUM(C3:C7) -> 290000 | D8: =SUM(D3:D7) -> 275000 | E8: =SUM(E3:E7) -> 0 | F8: =SUM(F3:F7) -> 0 | G8: =SUM(G3:G7) -> 670000
A9: OPEX
A10: 1 | B10: Оборудование (аренда/обслуживание серверов под QMS) | C10: 20000 | D10: 20000 | E10: 20000 | F10: 20000 | G10: 80000
A11: 2 | B11: Программное обеспечение (подписки, обновления) | C11: 40000 | D11: 40000 | E11: 40000 | F11: 40000 | G11: 160000
A12: 3 | B12: ТМЦ (расходники, мелкие замены) | C12: 5000 | D12: 5000 | E12: 5000 | F12: 5000 | G12: 20000
A13: 4 | B13: Услуги сторонних организаций (поддержка, SLA) | C13: 20000 | D13: 20000 | E13: 20000 | F13: 20000 | G13: 80000
A14: 5 | B14: Прочее (мелкие доработки, консультации) | C14: 5000 | D14: 5000 | E14: 5000 | F14: 5000 | G14: 20000
B15: Итого: | C15: =SUM(C10:C14) -> 90000 | D15: =SUM(D10:D14) -> 90000 | E15: =SUM(E10:E14) -> 90000 | F15: =SUM(F10:F14) -> 90000 | G15: =SUM(G10:G14) -> 360000

Sheet Мобильное приложение
A1: Номер п/п | B1: Название статьи затрат | C1: 1 квартал | D1: 2 квартал | E1: 3 квартал | F1: 4 квартал | G1: Год
A2: CAPEX
A3: 1 | B3: Оборудование | C3: 1500000 | D3: 500 000 ₽ | E3: 0 | F3: 0 | G3: 2 000 000 ₽
A4: 2 | B4: Программное обеспечение | C4: 500000 | D4: 1 000 000 ₽ | E4: 0 | F4: 0 | G4: 1 500 000 ₽
A5: 3 | B5: ТМЦ | C5: 300 000 ₽ | D5: 200 000 ₽ | E5: 0 | F5: 0 | G5: 500 000 ₽
A6: 4 | B6: Услуги сторонних организаций | C6: 200 000 ₽ | D6: 300 000 ₽ | E6: 0 | F6: 0 | G6: 500 000 ₽
A7: 5 | B7: Прочее | C7: 100 000 ₽ | D7: 0 | E7: 0 | F7: 0 | G7: 100 000 ₽
A8: Итого: | B8: 2 600 000 ₽ | C8: 2 050 000 ₽ | D8: 0 | E8: 0 | F8: =SUM(F3:F7) -> 0 | G8: =SUM(G3:G7) -> 0
A9: OPEX
A10: 1 | B10: Оборудование (аренда/обслуживание) | C10: 50 000 ₽ | D10: 50 000 ₽ | E10: 50 000 ₽ | F10: 50 000 ₽ | G10: 200 000 ₽
A11: 2 | B11: Программное обеспечение (подписки, сторы, сервисы) | C11: 80 000 ₽ | D11: 80 000 ₽ | E11: 80 000 ₽ | F11: 80 000 ₽ | G11: 320 000 ₽
A12: 3 | B12: ТМЦ | C12: 30 000 ₽ | D12: 30 000 ₽ | E12: 30 000 ₽ | F12: 30 000 ₽ | G12: 120 000 ₽
A13: 4 | B13: Услуги сторонних организаций (поддержка, маркетинговые интеграции, аналитика) | C13: 100 000 ₽ | D13: 100 000 ₽ | E13: 100 000 ₽ | F13: 100 000 ₽ | G13: 400 000 ₽
A14: 5 | B14: Прочее | C14: 20 000 ₽ | D14: 20 000 ₽ | E14: 20 000 ₽ | F14: 20 000 ₽ | G14: 80 000 ₽
A15: Итого: | B15: 280 000 ₽ | C15: 280 000 ₽ | D15: 280 000 ₽ | E15: 280 000 ₽ | F15: 1 120 000 ₽ | G15: 399 600 ₽

Sheet PLM
A1: Номер п/п | B1: Название статьи затрат | C1: 1 квартал | D1: 2 квартал | E1: 3 квартал | F1: 4 квартал | G1: Год
A2: CAPEX
A3: 1 | B3: Оборудование (серверы под хранение ассетов, SSD-массива) | C3: 380 000 ₽ | D3: 250 000 ₽ | E3: 0 | F3: 0 | G3: 630 000 ₽
A4: 2 | B4: Программное обеспечение (PLM-платформа, лицензии, интеграции с DevManager/Perforce) | C4: 420 000 ₽ | D4: 300 000 ₽ | E4: 250 000 ₽ | F4: 0 | G4: 970 000 ₽
A5: 3 | B5: ТМЦ (диски, периферия, сеть) | C5: 70 000 ₽ | D5: 30 000 ₽ | E5: 20 000 ₽ | F5: 20 000 ₽ | G5: 140 000 ₽
A6: 4 | B6: Услуги сторонних организаций (внедрение пайплайнов, кастомизация) | C6: 50 000 ₽ | D6: 40 000 ₽ | E6: 0 | F6: 0 | G6: 90 000 ₽
A7: 5 | B7: Прочее (документация, тестирование, обучение) | C7: 0 | D7: 0 | E7: 0 | F7: 0 | G7: 0
A8: Итого: | B8: 920 000 ₽ | C8: 620 000 ₽ | D8: 270 000 ₽ | E8: 20 000 ₽ | F8: 1 830 000 ₽ | G8: 1830000
A9: OPEX
A10: 1 | B10: Оборудование (аренда стоек, обслуживание серверов ассетов) | C10: 150 000 ₽ | D10: 150 000 ₽ | E10: 150 000 ₽ | F10: 150 000 ₽ | G10: 600 000 ₽
A11: 2 | B11: Программное обеспечение (подписки, обновления PLM) | C11: 50 000 ₽ | D11: 50 000 ₽ | E11: 50 000 ₽ | F11: 50 000 ₽ | G11: 200 000 ₽
A12: 3 | B12: ТМЦ (расходные материалы, замена SSD) | C12: 30 000 ₽ | D12: 30 000 ₽ | E12: 30 000 ₽ | F12: 30 000 ₽ | G12: 120 000 ₽
A13: 4 | B13: Услуги сторонних организаций (поддержка интеграций, SLA) | C13: 50 000 ₽ | D13: 50 000 ₽ | E13: 50 000 ₽ | F13: 50 000 ₽ | G13: 200 000 ₽
A14: 5 | B14: Прочее (мелкие доработки и консультации pipeline-команд) | C14: 60 000 ₽ | D14: 60 000 ₽ | E14: 60 000 ₽ | F14: 60 000 ₽ | G14: 240 000 ₽
A15: Итого: | B15: 340 000 ₽ | C15: 340 000 ₽ | D15: 340 000 ₽ | E15: 340 000 ₽ | F15: 1 360 000 ₽ | G15: =SUM(G10:G14) -> 0

Sheet План информатизации ИТ
A1: Номер п/п | B1: Наименование проекта/информационной системы | C1: 1 квартал | D1: 2 квартал | E1: 3 квартал | F1: 4 квартал | G1: Год
A2: CAPEX
A3: 1 | B3: CRM | C3: ='CRM1'!C10 -> 0 | D3: ='CRM1'!D10 -> 0 | E3: ='CRM1'!E10 -> 0 | F3: ='CRM1'!F10 -> 0 | G3: ='CRM1'!G10 -> 0
A4: 2 | B4: СППР | C4: =СППР!C10 -> 50000 | D4: =СППР!D10 -> 50000 | E4: =СППР!E10 -> 50000 | F4: =СППР!F10 -> 50000 | G4: =СППР!G10 -> 200000
A5: 3 | B5: QMS | C5: =QMS!D8 -> 275000 | D5: =QMS!D10 -> 20000 | E5: =QMS!F8 -> 0 | F5: =QMS!G8 -> 670000 | G5: =QMS!G10 -> 80000
A6: 4 | B6: Мобильное приложение | C6: ='Мобильное приложение'!C10 -> 50 000 ₽ | D6: ='Мобильное приложение'!D10 -> 50 000 ₽ | E6: ='Мобильное приложение'!E10 -> 50 000 ₽ | F6: ='Мобильное приложение'!F10 -> 50 000 ₽ | G6: ='Мобильное приложение'!G10 -> 200 000 ₽
A7: 5 | B7: PLM | C7: =PLM!C8 -> 620 000 ₽ | D7: =PLM!D8 -> 270 000 ₽ | E7: =PLM!E8 -> 20 000 ₽ | F7: =PLM!F8 -> 1 830 000 ₽ | G7: =PLM!G10 -> 600 000 ₽
B8: Итого: | C8: =SUM(C3:C7) -> 325000 | D8: =SUM(D3:D7) -> 70000 | E8: =SUM(E3:E7) -> 50000 | F8: =SUM(F3:F7) -> 720000 | G8: =SUM(G3:G7) -> 280000
A9: OPEX
A10: 1 | B10: CRM | C10: ='CRM1'!C10 -> 0 | D10: ='CRM1'!D10 -> 0 | E10: ='CRM1'!E10 -> 0 | F10: ='CRM1'!F10 -> 0 | G10: ='CRM1'!G10 -> 0
A11: 2 | B11: СППР | C11: =СППР!C10 -> 50000 | D11: =СППР!D10 -> 50000 | E11: =СППР!E10 -> 50000 | F11: =СППР!F10 -> 50000 | G11: =СППР!G10 -> 200000
A12: 3 | B12: QMS | C12: =QMS!C10 -> 20000 | D12: =QMS!D10 -> 20000 | E12: =QMS!F10 -> 20000 | F12: =QMS!F10 -> 20000 | G12: =QMS!G10 -> 80000
A13: 4 | B13: Мобильное приложение | C13: ='Мобильное приложение'!C10 -> 50 000 ₽ | D13: ='Мобильное приложение'!D10 -> 50 000 ₽ | E13: ='Мобильное приложение'!E10 -> 50 000 ₽ | F13: ='Мобильное приложение'!F10 -> 50 000 ₽ | G13: ='Мобильное приложение'!G10 -> 200 000 ₽
A14: 5 | B14: PLM | C14: =PLM!C10 -> 150 000 ₽ | D14: =PLM!D10 -> 150 000 ₽ | E14: =PLM!E10 -> 150 000 ₽ | F14: =PLM!F10 -> 150 000 ₽ | G14: =PLM!G10 -> 600 000 ₽
B15: Итого: | C15: =SUM(C10:C14) -> 70000 | D15: =SUM(D10:D14) -> 70000 | E15: =SUM(E10:E14) -> 70000 | F15: =SUM(F10:F14) -> 70000 | G15: =SUM(G10:G14) -> 280000
