Workbook
Name capex: чувствительность!$B$5
Name cur: данные!$A$2
Name discont: СВОД!$B$27
Name fot: СВОД!$B$16
Name fotmes: СВОД!$C$16
Name price: чувствительность!$B$7
Name profittax: СВОД!$B$22
Name proptax: СВОД!$B$24
Name raw: чувствительность!$B$8
Name salarytax: СВОД!$B$25
Name title: данные!$A$1
Name var: СВОД!$C$3
Name vat: СВОД!$B$23
Name volume: чувствительность!$B$6

Sheet СВОД
A1: Исходные данные | F1: Сводные результаты | G1: http://exceltable.com/
A3: Вариант | C3: 1 | D3: 1
D4: 2 | F4: млн. USD
A5: Данные по вариантам | B5: Вар.1 | C5: Вар.2 | F5: =title -> Вариант 1 | G5: Сумма | H5: 2014 | I5: 2015 | J5: 2016 | K5: 2017 | L5: 2018 | M5: 2019 | N5: 2020 | O5: 2021 | P5: 2022 | Q5: 2023 | R5: 2024
A6: Сырьё | F6: Валовый объем продаж (с НДС) | G6: =SUM(H6:R6) -> 6500.9942 | H6: ='Cash Flow'!D55 -> 0 | I6: ='Cash Flow'!E55 -> 228.3525 | J6: ='Cash Flow'!F55 -> 568.86637 | K6: ='Cash Flow'!G55 -> 597.30969 | L6: ='Cash Flow'!H55 -> 627.17518 | M6: ='Cash Flow'!I55 -> 658.53394 | N6: ='Cash Flow'!J55 -> 691.46063 | O6: ='Cash Flow'!K55 -> 726.03367 | ... R6: ='Cash Flow'!N55 -> 840.47472
A7: сырье 1 | B7: 1 | C7: 0.7 | F7: Чистый объем продаж (без НДС) | G7: =SUM(H7:R7) -> 5509.3171 | H7: =PL!D24 -> 0 | I7: =PL!E24 -> 193.51907 | J7: =PL!F24 -> 482.09015 | K7: =PL!G24 -> 506.19466 | L7: =PL!H24 -> 531.50439 | M7: =PL!I24 -> 558.07961 | N7: =PL!J24 -> 585.98359 | O7: =PL!K24 -> 615.28277 | ... R7: =PL!N24 -> 712.26671
A8: сырье 2 | B8: =1-B7 -> 0 | C8: =1-C7 -> 0.3 | F8: Суммарные прямые издержки | G8: =SUM(H8:R8) -> 3767.9449 | H8: =PL!D25 -> 0 | I8: =PL!E25 -> 133.05085 | J8: =PL!F25 -> 331.14407 | K8: =PL!G25 -> 347.29449 | L8: =PL!H25 -> 364.25244 | M8: =PL!I25 -> 382.05828 | N8: =PL!J25 -> 400.75441 | O8: =PL!K25 -> 420.38535 | ... R8: =PL!N25 -> 485.36622
A9: Выход продукции | F9: Суммарные постоянные издержки | G9: =SUM(H9:R9) -> 78.693874 | H9: =PL!D27+PL!D28+PL!D29 -> 0 | I9: =PL!E27+PL!E28 -> 3.6936155 | J9: =PL!F27+PL!F28 -> 8.023858 | K9: =PL!G27+PL!G28 -> 8.101234 | L9: =PL!H27+PL!H28 -> 8.17861 | M9: =PL!I27+PL!I28 -> 8.255986 | N9: =PL!J27+PL!J28 -> 8.333362 | O9: =PL!K27+PL!K28 -> 8.410738 | P9: =PL!L27+PL!L28 -> 8.488114 | ... R9: =PL!N27+PL!N28 -> 8.642866
A10: продукт 1 | B10: 0.7 | C10: 0.5 | F10: Амортизация | G10: =SUM(H10:R10) -> 55.492828 | H10: =PL!D34 -> 0 | I10: =PL!E34 -> 2.5631163 | J10: =PL!F34 -> 5.8810791 | K10: =PL!G34 -> 5.8810791 | L10: =PL!H34 -> 5.8810791 | M10: =PL!I34 -> 5.8810791 | N10: =PL!J34 -> 5.8810791 | O10: =PL!K34 -> 5.8810791 | ... R10: =PL!N34 -> 5.8810791
A11: продукт 2 | B11: 0.23 | C11: 0.4 | F11: Затраты на приобретение активов | G11: =SUM(H11:R11) -> 82.18818 | H11: =-'Cash Flow'!D73 -> 52.36268 | I11: =-'Cash Flow'!E73 -> 29.8255 | J11: =-'Cash Flow'!F73 -> 0 | K11: =-'Cash Flow'!G73 -> 0 | L11: =-'Cash Flow'!H73 -> 0 | M11: =-'Cash Flow'!I73 -> 0 | N11: =-'Cash Flow'!J73 -> 0 | O11: =-'Cash Flow'!K73 -> 0 | ... R11: =-'Cash Flow'!N73 -> 0
A12: продукт 3 | B12: 0 | C12: 0.05 | F12: Займы | G12: =SUM(H12:R12) -> 87.1 | H12: ='Cash Flow'!D78 -> 53.2 | I12: ='Cash Flow'!E78 -> 33.9 | J12: ='Cash Flow'!F78 -> 0 | K12: ='Cash Flow'!G78 -> 0 | L12: ='Cash Flow'!H78 -> 0 | M12: ='Cash Flow'!I78 -> 0 | N12: ='Cash Flow'!J78 -> 0 | O12: ='Cash Flow'!K78 -> 0 | ... R12: ='Cash Flow'!N78 -> 0
F13: Выплаты в погашение займов | G13: =SUM(H13:R13) -> 87.1 | H13: ='Cash Flow'!D80 -> 0 | I13: ='Cash Flow'!E80 -> 24.885714 | J13: ='Cash Flow'!F80 -> 62.214286 | K13: ='Cash Flow'!G80 -> 0 | L13: ='Cash Flow'!H80 -> 0 | M13: ='Cash Flow'!I80 -> 0 | N13: ='Cash Flow'!J80 -> 0 | O13: ='Cash Flow'!K80 -> 0 | ... R13: ='Cash Flow'!N80 -> 0
A14: Рост цены на продукцию, % в год | B14: 0.05 | F14: Выплаты процентов по займам | G14: =SUM(H14:R14) -> 8.7891667 | H14: ='Cash Flow'!D81 -> 0 | I14: ='Cash Flow'!E81 -> 7.2338095 | J14: ='Cash Flow'!F81 -> 1.5553571 | K14: ='Cash Flow'!G81 -> 0 | L14: ='Cash Flow'!H81 -> 0 | M14: ='Cash Flow'!I81 -> 0 | N14: ='Cash Flow'!J81 -> 0 | O14: ='Cash Flow'!K81 -> 0 | ... R14: ='Cash Flow'!N81 -> 0
A15: Рост цены на сырье, % в год | B15: 0.05 | F15: Налоги | G15: =SUM(H15:R15) -> 616.72746 | H15: ='Cash Flow'!D63 -> 0 | I15: ='Cash Flow'!E63 -> 9.5541447 | J15: ='Cash Flow'!F63 -> 50.100204 | K15: ='Cash Flow'!G63 -> 57.784063 | L15: ='Cash Flow'!H63 -> 60.832454 | M15: ='Cash Flow'!I63 -> 64.039213 | N15: ='Cash Flow'!J63 -> 67.412259 | O15: ='Cash Flow'!K63 -> 70.959907 | ... R15: ='Cash Flow'!N63 -> 82.739963
A16: Индексация ФОТ, % в год | B16: 0.02 | C16: =POWER(1+fot,1/12)-1 -> 0.0016515813 | F16: Чистая прибыль | G16: =SUM(H16:R16) -> 1271.8091 | H16: =PL!D39 -> -0.084559322 | I16: =PL!E39 -> 37.423534 | J16: =PL!F39 -> 107.22464 | K16: =PL!G39 -> 114.88441 | L16: =PL!H39 -> 121.60744 | M16: =PL!I39 -> 128.66455 | N16: =PL!J39 -> 136.07243 | O16: =PL!K39 -> 143.84863 | ... R16: =PL!N39 -> 169.57591
F17: Баланс наличности на конец периода | G17: =R17 -> 1236.6902 | H17: ='Cash Flow'!D86 -> 0.83732 | I17: ='Cash Flow'!E86 -> 14.377665 | J17: ='Cash Flow'!F86 -> 69.087557 | K17: ='Cash Flow'!G86 -> 189.1523 | L17: ='Cash Flow'!H86 -> 315.90504 | M17: ='Cash Flow'!I86 -> 449.67811 | N17: ='Cash Flow'!J86 -> 590.82042 | O17: ='Cash Flow'!K86 -> 739.69838 | ... R17: ='Cash Flow'!N86 -> 1236.6902
A18: Срок кредита | B18: Вар.1 | C18: Вар.2
A19: Срок | B19: 18 | C19: 30 | F19: =IF(L30=C30,"","ДЛЯ РАСЧЁТА НАЖАТЬ F9")
F20: Показатели | H20: варианты | J20: ! Для обновления при смене исходных данных нажать F9
A21: Налоги | B21: Ставка | H21: 1 | I21: 2
A22: Налог на прибыль | B22: 0.2 | F22: Чистая текущая стоимость (NPV), млн. USD | G22: =NPV!C11/1000000 -> 415.40684 | H22: 415.40684 | I22: 436.16541
A23: НДС | B23: 0.18 | F23: Внутренняя ставка доходности (IRR), % | G23: =NPV!C12 -> 1.3290017 | H23: 1.3290017 | I23: 1.381781
A24: Налог на имущество | B24: 0.022 | F24: Индекс доходности (PI) | G24: =NPV!C13 -> 3.5754771 | H24: 3.5754771 | I24: 3.7535218
A25: Налог на ФОТ | B25: 0.3 | F25: Срок окупаемости (PBP), мес. | G25: =NPV!C14 -> 18 | H25: 18 | I25: 18
F26: Дисконт. срок окупаемости (DPBP), мес. | G26: =NPV!C15 -> 21 | H26: 21 | I26: 20
A27: Ставка дисконтирования | B27: 0.25
B31: =чувствительность!G7 -> 0.8 | C31: =чувствительность!H7 -> 0.85 | D31: =чувствительность!I7 -> 0.9 | E31: =чувствительность!J7 -> 0.95 | F31: =чувствительность!K7 -> 1 | G31: =чувствительность!L7 -> 1.05 | H31: =чувствительность!M7 -> 1.1 | I31: =чувствительность!N7 -> 1.15 | J31: =чувствительность!O7 -> 1.2
A32: =чувствительность!A5 -> Кап. затраты | B32: =чувствительность!G53 -> 1.360834 | C32: =чувствительность!H53 -> 1.3527878 | D32: =чувствительность!I53 -> 1.344769 | E32: =чувствительность!J53 -> 1.3368447 | F32: =чувствительность!K53 -> 1.3290017 | G32: =чувствительность!L53 -> 1.3210485 | H32: =чувствительность!M53 -> 1.3132094 | I32: =чувствительность!N53 -> 1.3054865 | J32: =чувствительность!O53 -> 1.2977291
A33: =чувствительность!A6 -> Объем переработки | B33: =чувствительность!G59 -> 1.0769928 | C33: =чувствительность!H59 -> 1.1404982 | D33: =чувствительность!I59 -> 1.2035974 | E33: =чувствительность!J59 -> 1.2664137 | F33: =чувствительность!K59 -> 1.3290017 | G33: =чувствительность!L59 -> 1.3911396 | H33: =чувствительность!M59 -> 1.4529995 | I33: =чувствительность!N59 -> 1.514662 | J33: =чувствительность!O59 -> 1.5760659
A34: =чувствительность!A7 -> Цена | B34: =чувствительность!G65 -> 0.46234317 | C34: =чувствительность!H65 -> 0.67446322 | D34: =чувствительность!I65 -> 0.88884841 | E34: =чувствительность!J65 -> 1.1071878 | F34: =чувствительность!K65 -> 1.3290017 | G34: =чувствительность!L65 -> 1.5533933 | H34: =чувствительность!M65 -> 1.7796404 | I34: =чувствительность!N65 -> 2.0076832 | J34: =чувствительность!O65 -> 2.2369593
A35: =чувствительность!A8 -> Стоимость сырья | B35: =чувствительность!G71 -> 1.9738622 | C35: =чувствительность!H71 -> 1.8097327 | D35: =чувствительность!I71 -> 1.6473765 | E35: =чувствительность!J71 -> 1.4870375 | F35: =чувствительность!K71 -> 1.3290017 | G35: =чувствительность!L71 -> 1.1733646 | H35: =чувствительность!M71 -> 1.0205575 | I35: =чувствительность!N71 -> 0.87093314 | J35: =чувствительность!O71 -> 0.72472355
A44: ! Для обновления при смене вариантов нажать F9

Sheet данные
A1: ="Вариант "&var -> Вариант 1 | B1: http://exceltable.com/ | D1: 1 | E1: 2 | F1: 3 | G1: 4 | H1: 5 | I1: 6 | J1: 7 | K1: 8 | L1: 9 | M1: 10 | N1: 11 | O1: 12 | P1: 13 | Q1: 14 | R1: 15 | S1: 16 | T1: 17 | U1: 18 | V1: 19 | W1: 20 | X1: 21 | Y1: 22 | Z1: 23 | AA1: 24 | AB1: 25 | AC1: 26 | AD1: 27 | AE1: 28 | AF1: 29 | AG1: 30 | AH1: 31 | AI1: 32 | AJ1: 33 | AK1: 34 | AL1: 35 | AM1: 36 | AN1: 37 | AO1: 38 | AP1: 39 | AQ1: 40 | AR1: 41 | AS1: 42 | AT1: 43 | AU1: 44 | AV1: 45 | AW1: 46 | AX1: 47 | AY1: 48 | AZ1: 49 | BA1: 50 | BB1: 51 | BC1: 52 | BD1: 53 | BE1: 54 | BF1: 55 | BG1: 56 | BH1: 57 | BI1: 58 | BJ1: 59 | BK1: 60 | BL1: 61 | BM1: 62 | BN1: 63 | BO1: 64 | BP1: 65 | BQ1: 66 | BR1: 67 | BS1: 68 | BT1: 69 | BU1: 70 | BV1: 71 | BW1: 72 | BX1: 73 | BY1: 74 | BZ1: 75 | CA1: 76 | CB1: 77 | CC1: 78 | CD1: 79 | CE1: 80 | CF1: 81 | CG1: 82 | CH1: 83 | CI1: 84 | CJ1: 85 | CK1: 86 | CL1: 87 | CM1: 88 | CN1: 89 | CO1: 90 | CP1: 91 | CQ1: 92 | CR1: 93 | CS1: 94 | CT1: 95 | CU1: 96 | CV1: 97 | CW1: 98 | CX1: 99 | CY1: 100 | CZ1: 101 | DA1: 102 | DB1: 103 | DC1: 104 | DD1: 105 | DE1: 106 | DF1: 107 | DG1: 108 | DH1: 109 | DI1: 110 | DJ1: 111 | DK1: 112 | DL1: 113 | DM1: 114 | DN1: 115 | DO1: 116 | DP1: 117 | DQ1: 118 | DR1: 119 | DS1: 120 | DT1: 121 | DU1: 122
A2: USD | D2: =YEAR(D3) -> 2014 | E2: =YEAR(E3) -> 2014 | F2: =YEAR(F3) -> 2015 | G2: =YEAR(G3) -> 2015 | H2: =YEAR(H3) -> 2015 | I2: =YEAR(I3) -> 2015 | J2: =YEAR(J3) -> 2015 | K2: =YEAR(K3) -> 2015 | ... DU2: =YEAR(DU3) -> 2024
A3: Капитальные затраты | C3: Сумма | D3: 41944 | E3: 41974 | F3: 42005 | G3: 42036 | H3: 42064 | I3: 42095 | J3: 42125 | K3: 42156 | L3: 42186 | M3: 42217 | N3: 42248 | O3: 42278 | P3: 42309 | Q3: 42339 | R3: 42370 | S3: 42401 | T3: 42430 | U3: 42461 | V3: 42491 | W3: 42522 | X3: 42552 | Y3: 42583 | Z3: 42614 | AA3: 42644 | AB3: 42675 | AC3: 42705 | AD3: 42736 | AE3: 42767 | AF3: 42795 | AG3: 42826 | AH3: 42856 | AI3: 42887 | AJ3: 42917 | AK3: 42948 | AL3: 42979 | AM3: 43009 | AN3: 43040 | AO3: 43070 | AP3: 43101 | AQ3: 43132 | AR3: 43160 | AS3: 43191 | AT3: 43221 | AU3: 43252 | AV3: 43282 | AW3: 43313 | AX3: 43344 | AY3: 43374 | AZ3: 43405 | BA3: 43435 | BB3: 43466 | BC3: 43497 | BD3: 43525 | BE3: 43556 | BF3: 43586 | BG3: 43617 | BH3: 43647 | BI3: 43678 | BJ3: 43709 | BK3: 43739 | BL3: 43770 | BM3: 43800 | BN3: 43831 | BO3: 43862 | BP3: 43891 | BQ3: 43922 | BR3: 43952 | BS3: 43983 | BT3: 44013 | BU3: 44044 | BV3: 44075 | BW3: 44105 | BX3: 44136 | BY3: 44166 | BZ3: 44197 | CA3: 44228 | CB3: 44256 | CC3: 44287 | CD3: 44317 | CE3: 44348 | CF3: 44378 | CG3: 44409 | CH3: 44440 | CI3: 44470 | CJ3: 44501 | CK3: 44531 | CL3: 44562 | CM3: 44593 | CN3: 44621 | CO3: 44652 | CP3: 44682 | CQ3: 44713 | CR3: 44743 | CS3: 44774 | CT3: 44805 | CU3: 44835 | CV3: 44866 | CW3: 44896 | CX3: 44927 | CY3: 44958 | CZ3: 44986 | DA3: 45017 | DB3: 45047 | DC3: 45078 | DD3: 45108 | DE3: 45139 | DF3: 45170 | DG3: 45200 | DH3: 45231 | DI3: 45261 | DJ3: 45292 | DK3: 45323 | DL3: 45352 | DM3: 45383 | DN3: 45413 | DO3: 45444 | DP3: 45474 | DQ3: 45505 | DR3: 45536 | DS3: 45566 | DT3: 45597 | DU3: 45627
A4: capex 1 | C4: =SUM(D4:DU4) -> 65000000 | D4: 45000000 | E4: 0 | F4: 0 | G4: 0 | H4: 0 | I4: 0 | J4: 0 | K4: 0 | L4: 0 | M4: 20000000
A5: capex 2 | C5: =SUM(D5:DU5) -> 608400 | D5: 432900 | E5: 0 | F5: 0 | G5: 0 | H5: 175500 | I5: 0 | J5: 0 | K5: 0 | L5: 0 | M5: 0
A6: capex 3 | C6: =SUM(D6:DU6) -> 39780 | D6: 39780 | E6: 0 | F6: 0 | G6: 0 | H6: 0 | I6: 0 | J6: 0 | K6: 0 | L6: 0 | M6: 0
A7: capex 4 | C7: =SUM(D7:DU7) -> 3230000 | D7: 120000 | E7: 120000 | F7: 120000 | G7: 120000 | H7: 550000 | I7: 550000 | J7: 550000 | K7: 550000 | L7: 550000 | M7: 0
A8: capex 5 | C8: =SUM(D8:DU8) -> 60000 | D8: 60000 | E8: 0 | F8: 0 | G8: 0 | H8: 0 | I8: 0 | J8: 0 | K8: 0 | L8: 0 | M8: 0
A9: capex 6 | C9: =SUM(D9:DU9) -> 8100000 | D9: 900000 | E9: 900000 | F9: 900000 | G9: 900000 | H9: 900000 | I9: 900000 | J9: 900000 | K9: 900000 | L9: 900000 | M9: 0
A10: capex 7 | C10: =SUM(D10:DU10) -> 2500000 | D10: 2500000 | E10: 0 | F10: 0 | G10: 0 | H10: 0 | I10: 0 | J10: 0 | K10: 0 | L10: 0 | M10: 0
A11: capex 8 | C11: =SUM(D11:DU11) -> 2200000 | D11: 2200000 | E11: 0 | F11: 0 | G11: 0 | H11: 0 | I11: 0 | J11: 0 | K11: 0 | L11: 0 | M11: 0
A12: capex 9 | C12: =SUM(D12:DU12) -> 450000 | D12: 45000 | E12: 45000 | F12: 45000 | G12: 45000 | H12: 45000 | I12: 45000 | J12: 45000 | K12: 45000 | L12: 45000 | M12: 45000
A13: ИТОГО | C13: =SUM(D13:DU13) -> 82188180 | D13: =SUM(D4:D12)*capex -> 51297680 | E13: =SUM(E4:E12)*capex -> 1065000 | F13: =SUM(F4:F12)*capex -> 1065000 | G13: =SUM(G4:G12)*capex -> 1065000 | H13: =SUM(H4:H12)*capex -> 1670500 | I13: =SUM(I4:I12)*capex -> 1495000 | J13: =SUM(J4:J12)*capex -> 1495000 | K13: =SUM(K4:K12)*capex -> 1495000 | ... DU13: =SUM(DU4:DU12)*capex -> 0
A16: Амортизация | C16: Сумма | D16: =D3 -> 41944 | E16: =E3 -> 41974 | F16: =F3 -> 42005 | G16: =G3 -> 42036 | H16: =H3 -> 42064 | I16: =I3 -> 42095 | J16: =J3 -> 42125 | K16: =K3 -> 42156 | ... DU16: =DU3 -> 45627
A17: Первонач. стоимость | B17: пуск | D17: =SUM(D18:D26) -> 0 | E17: =SUM(E18:E26) -> 0 | F17: =SUM(F18:F26) -> 0 | G17: =SUM(G18:G26) -> 0 | H17: =SUM(H18:H26) -> 0 | I17: =SUM(I18:I26) -> 4498644.1 | J17: =SUM(J18:J26) -> 4498644.1 | K17: =SUM(K18:K26) -> 4498644.1 | ... DU17: =SUM(DU18:DU26) -> 69566441
A18: =A4 -> capex 1 | B18: 10 | D18: =IF($B18<=D$1,$C4/(1+vat),0) -> 0 | E18: =IF($B18<=E$1,$C4/(1+vat),0) -> 0 | F18: =IF($B18<=F$1,$C4/(1+vat),0) -> 0 | G18: =IF($B18<=G$1,$C4/(1+vat),0) -> 0 | H18: =IF($B18<=H$1,$C4/(1+vat),0) -> 0 | I18: =IF($B18<=I$1,$C4/(1+vat),0) -> 0 | J18: =IF($B18<=J$1,$C4/(1+vat),0) -> 0 | K18: =IF($B18<=K$1,$C4/(1+vat),0) -> 0 | ... DU18: =IF($B18<=DU$1,$C4/(1+vat),0) -> 55084746
A19: =A5 -> capex 2 | B19: 6 | D19: =IF($B19<=D$1,$C5/(1+vat),0) -> 0 | E19: =IF($B19<=E$1,$C5/(1+vat),0) -> 0 | F19: =IF($B19<=F$1,$C5/(1+vat),0) -> 0 | G19: =IF($B19<=G$1,$C5/(1+vat),0) -> 0 | H19: =IF($B19<=H$1,$C5/(1+vat),0) -> 0 | I19: =IF($B19<=I$1,$C5/(1+vat),0) -> 515593.22 | J19: =IF($B19<=J$1,$C5/(1+vat),0) -> 515593.22 | K19: =IF($B19<=K$1,$C5/(1+vat),0) -> 515593.22 | ... DU19: =IF($B19<=DU$1,$C5/(1+vat),0) -> 515593.22
A21: =A7 -> capex 4 | B21: 10 | D21: =IF($B21<=D$1,$C7/(1+vat),0) -> 0 | E21: =IF($B21<=E$1,$C7/(1+vat),0) -> 0 | F21: =IF($B21<=F$1,$C7/(1+vat),0) -> 0 | G21: =IF($B21<=G$1,$C7/(1+vat),0) -> 0 | H21: =IF($B21<=H$1,$C7/(1+vat),0) -> 0 | I21: =IF($B21<=I$1,$C7/(1+vat),0) -> 0 | J21: =IF($B21<=J$1,$C7/(1+vat),0) -> 0 | K21: =IF($B21<=K$1,$C7/(1+vat),0) -> 0 | ... DU21: =IF($B21<=DU$1,$C7/(1+vat),0) -> 2737288.1
A23: =A9 -> capex 6 | B23: 10 | D23: =IF($B23<=D$1,$C9/(1+vat),0) -> 0 | E23: =IF($B23<=E$1,$C9/(1+vat),0) -> 0 | F23: =IF($B23<=F$1,$C9/(1+vat),0) -> 0 | G23: =IF($B23<=G$1,$C9/(1+vat),0) -> 0 | H23: =IF($B23<=H$1,$C9/(1+vat),0) -> 0 | I23: =IF($B23<=I$1,$C9/(1+vat),0) -> 0 | J23: =IF($B23<=J$1,$C9/(1+vat),0) -> 0 | K23: =IF($B23<=K$1,$C9/(1+vat),0) -> 0 | ... DU23: =IF($B23<=DU$1,$C9/(1+vat),0) -> 6864406.8
A24: =A10 -> capex 7 | B24: 6 | D24: =IF($B24<=D$1,$C10/(1+vat),0) -> 0 | E24: =IF($B24<=E$1,$C10/(1+vat),0) -> 0 | F24: =IF($B24<=F$1,$C10/(1+vat),0) -> 0 | G24: =IF($B24<=G$1,$C10/(1+vat),0) -> 0 | H24: =IF($B24<=H$1,$C10/(1+vat),0) -> 0 | I24: =IF($B24<=I$1,$C10/(1+vat),0) -> 2118644.1 | J24: =IF($B24<=J$1,$C10/(1+vat),0) -> 2118644.1 | K24: =IF($B24<=K$1,$C10/(1+vat),0) -> 2118644.1 | ... DU24: =IF($B24<=DU$1,$C10/(1+vat),0) -> 2118644.1
A25: =A11 -> capex 8 | B25: 6 | D25: =IF($B25<=D$1,$C11/(1+vat),0) -> 0 | E25: =IF($B25<=E$1,$C11/(1+vat),0) -> 0 | F25: =IF($B25<=F$1,$C11/(1+vat),0) -> 0 | G25: =IF($B25<=G$1,$C11/(1+vat),0) -> 0 | H25: =IF($B25<=H$1,$C11/(1+vat),0) -> 0 | I25: =IF($B25<=I$1,$C11/(1+vat),0) -> 1864406.8 | J25: =IF($B25<=J$1,$C11/(1+vat),0) -> 1864406.8 | K25: =IF($B25<=K$1,$C11/(1+vat),0) -> 1864406.8 | ... DU25: =IF($B25<=DU$1,$C11/(1+vat),0) -> 1864406.8
A26: =A12 -> capex 9 | B26: 10 | D26: =IF($B26<=D$1,$C12/(1+vat),0) -> 0 | E26: =IF($B26<=E$1,$C12/(1+vat),0) -> 0 | F26: =IF($B26<=F$1,$C12/(1+vat),0) -> 0 | G26: =IF($B26<=G$1,$C12/(1+vat),0) -> 0 | H26: =IF($B26<=H$1,$C12/(1+vat),0) -> 0 | I26: =IF($B26<=I$1,$C12/(1+vat),0) -> 0 | J26: =IF($B26<=J$1,$C12/(1+vat),0) -> 0 | K26: =IF($B26<=K$1,$C12/(1+vat),0) -> 0 | ... DU26: =IF($B26<=DU$1,$C12/(1+vat),0) -> 381355.93
A27: Незавершенное стр-во | D27: =SUM(D4:D5,D7,D9:D12)/(1+vat)-D17 -> 43388051 | E27: =MAX(0,SUM($D$4:E5,$D$7:E7,$D$9:E12)/(1+vat)-E17) -> 44290593 | F27: =MAX(0,SUM($D$4:F5,$D$7:F7,$D$9:F12)/(1+vat)-F17) -> 45193136 | G27: =MAX(0,SUM($D$4:G5,$D$7:G7,$D$9:G12)/(1+vat)-G17) -> 46095678 | H27: =MAX(0,SUM($D$4:H5,$D$7:H7,$D$9:H12)/(1+vat)-H17) -> 47511356 | I27: =MAX(0,SUM($D$4:I5,$D$7:I7,$D$9:I12)/(1+vat)-I17) -> 44279661 | J27: =MAX(0,SUM($D$4:J5,$D$7:J7,$D$9:J12)/(1+vat)-J17) -> 45546610 | K27: =MAX(0,SUM($D$4:K5,$D$7:K7,$D$9:K12)/(1+vat)-K17) -> 46813559 | L27: =MAX(0,SUM($D$4:L5,$D$7:L7,$D$9:L12)/(1+vat)-L17) -> 48080508 | ... DU27: =MAX(0,SUM($D$4:DU5,$D$7:DU7,$D$9:DU12)/(1+vat)-DU17) -> 0
A28: Амортизация | B28: ставка | D28: =SUM(D29:D35) -> 0 | E28: =SUM(E29:E35) -> 0 | F28: =SUM(F29:F35) -> 0 | G28: =SUM(G29:G35) -> 0 | H28: =SUM(H29:H35) -> 0 | I28: =SUM(I29:I35) -> 28166.667 | J28: =SUM(J29:J35) -> 28166.667 | K28: =SUM(K29:K35) -> 28166.667 | ... DU28: =SUM(DU29:DU35) -> 490089.92
A29: =A4 -> capex 1 | B29: =1/12 -> 0.083333333 | D29: =D18*$B29/12 -> 0 | E29: =E18*$B29/12 -> 0 | F29: =F18*$B29/12 -> 0 | G29: =G18*$B29/12 -> 0 | H29: =H18*$B29/12 -> 0 | I29: =I18*$B29/12 -> 0 | J29: =J18*$B29/12 -> 0 | K29: =K18*$B29/12 -> 0 | ... DU29: =DU18*$B29/12 -> 382532.96
A30: =A5 -> capex 2 | B30: =1/10 -> 0.1 | D30: =D19*$B30/12 -> 0 | E30: =E19*$B30/12 -> 0 | F30: =F19*$B30/12 -> 0 | G30: =G19*$B30/12 -> 0 | H30: =H19*$B30/12 -> 0 | I30: =I19*$B30/12 -> 4296.6102 | J30: =J19*$B30/12 -> 4296.6102 | K30: =K19*$B30/12 -> 4296.6102 | ... DU30: =DU19*$B30/12 -> 4296.6102
A31: =A7 -> capex 4 | B31: =1/12 -> 0.083333333 | D31: =D21*$B31/12 -> 0 | E31: =E21*$B31/12 -> 0 | F31: =F21*$B31/12 -> 0 | G31: =G21*$B31/12 -> 0 | H31: =H21*$B31/12 -> 0 | I31: =I21*$B31/12 -> 0 | J31: =J21*$B31/12 -> 0 | K31: =K21*$B31/12 -> 0 | ... DU31: =DU21*$B31/12 -> 19008.945
A32: =A9 -> capex 6 | B32: =1/10 -> 0.1 | D32: =D23*$B32/12 -> 0 | E32: =E23*$B32/12 -> 0 | F32: =F23*$B32/12 -> 0 | G32: =G23*$B32/12 -> 0 | H32: =H23*$B32/12 -> 0 | I32: =I23*$B32/12 -> 0 | J32: =J23*$B32/12 -> 0 | K32: =K23*$B32/12 -> 0 | ... DU32: =DU23*$B32/12 -> 57203.39
A33: =A10 -> capex 7 | B33: =1/10 -> 0.1 | D33: =D24*$B33/12 -> 0 | E33: =E24*$B33/12 -> 0 | F33: =F24*$B33/12 -> 0 | G33: =G24*$B33/12 -> 0 | H33: =H24*$B33/12 -> 0 | I33: =I24*$B33/12 -> 17655.367 | J33: =J24*$B33/12 -> 17655.367 | K33: =K24*$B33/12 -> 17655.367 | ... DU33: =DU24*$B33/12 -> 17655.367
A34: =A11 -> capex 8 | B34: =1/25 -> 0.04 | D34: =D25*$B34/12 -> 0 | E34: =E25*$B34/12 -> 0 | F34: =F25*$B34/12 -> 0 | G34: =G25*$B34/12 -> 0 | H34: =H25*$B34/12 -> 0 | I34: =I25*$B34/12 -> 6214.6893 | J34: =J25*$B34/12 -> 6214.6893 | K34: =K25*$B34/12 -> 6214.6893 | ... DU34: =DU25*$B34/12 -> 6214.6893
A35: =A12 -> capex 9 | B35: =1/10 -> 0.1 | D35: =D26*$B35/12 -> 0 | E35: =E26*$B35/12 -> 0 | F35: =F26*$B35/12 -> 0 | G35: =G26*$B35/12 -> 0 | H35: =H26*$B35/12 -> 0 | I35: =I26*$B35/12 -> 0 | J35: =J26*$B35/12 -> 0 | K35: =K26*$B35/12 -> 0 | ... DU35: =DU26*$B35/12 -> 3177.9661
A36: Остаточная стоимость | D36: =D17-D28 -> 0 | E36: =E17-SUM($D$28:E28) -> 0 | F36: =F17-SUM($D$28:F28) -> 0 | G36: =G17-SUM($D$28:G28) -> 0 | H36: =H17-SUM($D$28:H28) -> 0 | I36: =I17-SUM($D$28:I28) -> 4470477.4 | J36: =J17-SUM($D$28:J28) -> 4442310.7 | K36: =K17-SUM($D$28:K28) -> 4414144.1 | L36: =L17-SUM($D$28:L28) -> 4385977.4 | ... DU36: =DU17-SUM($D$28:DU28) -> 14073613
A37: Кредиторская задолженность по кап. затратам | D37: =-MIN(0,SUM($D$4:D5,$D$7:D7,$D$9:D12)/(1+vat)-D17) -> 0 | E37: =-MIN(0,SUM($D$4:E5,$D$7:E7,$D$9:E12)/(1+vat)-E17) -> 0 | F37: =-MIN(0,SUM($D$4:F5,$D$7:F7,$D$9:F12)/(1+vat)-F17) -> 0 | G37: =-MIN(0,SUM($D$4:G5,$D$7:G7,$D$9:G12)/(1+vat)-G17) -> 0 | H37: =-MIN(0,SUM($D$4:H5,$D$7:H7,$D$9:H12)/(1+vat)-H17) -> 0 | I37: =-MIN(0,SUM($D$4:I5,$D$7:I7,$D$9:I12)/(1+vat)-I17) -> 0 | J37: =-MIN(0,SUM($D$4:J5,$D$7:J7,$D$9:J12)/(1+vat)-J17) -> 0 | K37: =-MIN(0,SUM($D$4:K5,$D$7:K7,$D$9:K12)/(1+vat)-K17) -> 0 | ... DU37: =-MIN(0,SUM($D$4:DU5,$D$7:DU7,$D$9:DU12)/(1+vat)-DU17) -> 1.4901161e-08
A39: Выручка | C39: Сумма | D39: =D16 -> 41944 | E39: =E16 -> 41974 | F39: =F16 -> 42005 | G39: =G16 -> 42036 | H39: =H16 -> 42064 | I39: =I16 -> 42095 | J39: =J16 -> 42125 | K39: =K16 -> 42156 | ... DU39: =DU16 -> 45627
A40: Переработка сырья, т | B40: 50000 | C40: =SUM(D40:DU40) -> 5650000 | M40: =$B$40*volume -> 50000 | N40: =$B$40*volume -> 50000 | O40: =$B$40*volume -> 50000 | P40: =$B$40*volume -> 50000 | Q40: =$B$40*volume -> 50000 | R40: =$B$40*volume -> 50000 | S40: =$B$40*volume -> 50000 | T40: =$B$40*volume -> 50000 | ... DU40: =$B$40*volume -> 50000
A41: =СВОД!A7 -> сырье 1 | B41: =IF(var=1,СВОД!B7,СВОД!C7) -> 1 | C41: =SUM(D41:DU41) -> 5650000 | D41: =D$40*$B41 -> 0 | E41: =E$40*$B41 -> 0 | F41: =F$40*$B41 -> 0 | G41: =G$40*$B41 -> 0 | H41: =H$40*$B41 -> 0 | I41: =I$40*$B41 -> 0 | J41: =J$40*$B41 -> 0 | K41: =K$40*$B41 -> 0 | ... DU41: =DU$40*$B41 -> 50000
A42: =СВОД!A8 -> сырье 2 | B42: =1-B41 -> 0 | C42: =SUM(D42:DU42) -> 0 | D42: =D$40*$B42 -> 0 | E42: =E$40*$B42 -> 0 | F42: =F$40*$B42 -> 0 | G42: =G$40*$B42 -> 0 | H42: =H$40*$B42 -> 0 | I42: =I$40*$B42 -> 0 | J42: =J$40*$B42 -> 0 | K42: =K$40*$B42 -> 0 | ... DU42: =DU$40*$B42 -> 0
A43: Производство готовой продукции, т | B43: выход | C43: =SUM(D43:DU43) -> 5254500 | D43: =SUM(D44:D46) -> 0 | E43: =SUM(E44:E46) -> 0 | F43: =SUM(F44:F46) -> 0 | G43: =SUM(G44:G46) -> 0 | H43: =SUM(H44:H46) -> 0 | I43: =SUM(I44:I46) -> 0 | J43: =SUM(J44:J46) -> 0 | K43: =SUM(K44:K46) -> 0 | ... DU43: =SUM(DU44:DU46) -> 46500
A44: =СВОД!A10 -> продукт 1 | B44: =IF(var=1,СВОД!B10,СВОД!C10) -> 0.7 | C44: =SUM(D44:DU44) -> 3955000 | D44: =D$40*$B44 -> 0 | E44: =E$40*$B44 -> 0 | F44: =F$40*$B44 -> 0 | G44: =G$40*$B44 -> 0 | H44: =H$40*$B44 -> 0 | I44: =I$40*$B44 -> 0 | J44: =J$40*$B44 -> 0 | K44: =K$40*$B44 -> 0 | ... DU44: =DU$40*$B44 -> 35000
A45: =СВОД!A11 -> продукт 2 | B45: =IF(var=1,СВОД!B11,СВОД!C11) -> 0.23 | C45: =SUM(D45:DU45) -> 1299500 | D45: =D$40*$B45 -> 0 | E45: =E$40*$B45 -> 0 | F45: =F$40*$B45 -> 0 | G45: =G$40*$B45 -> 0 | H45: =H$40*$B45 -> 0 | I45: =I$40*$B45 -> 0 | J45: =J$40*$B45 -> 0 | K45: =K$40*$B45 -> 0 | ... DU45: =DU$40*$B45 -> 11500
A46: =СВОД!A12 -> продукт 3 | B46: =IF(var=1,СВОД!B12,СВОД!C12) -> 0 | C46: =SUM(D46:DU46) -> 0 | D46: =D$40*$B46 -> 0 | E46: =E$40*$B46 -> 0 | F46: =F$40*$B46 -> 0 | G46: =G$40*$B46 -> 0 | H46: =H$40*$B46 -> 0 | I46: =I$40*$B46 -> 0 | J46: =J$40*$B46 -> 0 | K46: =K$40*$B46 -> 0 | ... DU46: =DU$40*$B46 -> 0
A47: Цена, долл./т (с НДС) | B47: база
A48: =A44 -> продукт 1 | B48: 1000 | D48: =$B48*price -> 1000 | E48: =$B48*price -> 1000 | F48: =$B48*price -> 1000 | G48: =$B48*price -> 1000 | H48: =$B48*price -> 1000 | I48: =$B48*price -> 1000 | J48: =$B48*price -> 1000 | K48: =$B48*price -> 1000 | ... O48: =$B48*price -> 1000 | P48: =$B48*(1+СВОД!$B$14)*price -> 1050 | Q48: =$B48*(1+СВОД!$B$14)*price -> 1050 | R48: =$B48*(1+СВОД!$B$14)*price -> 1050 | S48: =$B48*(1+СВОД!$B$14)*price -> 1050 | T48: =$B48*(1+СВОД!$B$14)*price -> 1050 | U48: =$B48*(1+СВОД!$B$14)*price -> 1050 | V48: =$B48*(1+СВОД!$B$14)*price -> 1050 | W48: =$B48*(1+СВОД!$B$14)*price -> 1050 | ... AA48: =$B48*(1+СВОД!$B$14)*price -> 1050 | AB48: =$AA48*(1+СВОД!$B$14) -> 1102.5 | AC48: =$AA48*(1+СВОД!$B$14) -> 1102.5 | AD48: =$AA48*(1+СВОД!$B$14) -> 1102.5 | AE48: =$AA48*(1+СВОД!$B$14) -> 1102.5 | AF48: =$AA48*(1+СВОД!$B$14) -> 1102.5 | AG48: =$AA48*(1+СВОД!$B$14) -> 1102.5 | AH48: =$AA48*(1+СВОД!$B$14) -> 1102.5 | AI48: =$AA48*(1+СВОД!$B$14) -> 1102.5 | ... AM48: =$AA48*(1+СВОД!$B$14) -> 1102.5 | AN48: =AM48*(1+СВОД!$B$14) -> 1157.625 | AO48: =AN48 -> 1157.625 | AP48: =AO48 -> 1157.625 | AQ48: =AP48 -> 1157.625 | AR48: =AQ48 -> 1157.625 | AS48: =AR48 -> 1157.625 | AT48: =AS48 -> 1157.625 | AU48: =AT48 -> 1157.625 | AV48: =AU48 -> 1157.625 | ... AY48: =AX48 -> 1157.625 | AZ48: =AY48*(1+СВОД!$B$14) -> 1215.5063 | BA48: =AZ48 -> 1215.5063 | BB48: =BA48 -> 1215.5063 | BC48: =BB48 -> 1215.5063 | BD48: =BC48 -> 1215.5063 | BE48: =BD48 -> 1215.5063 | BF48: =BE48 -> 1215.5063 | BG48: =BF48 -> 1215.5063 | BH48: =BG48 -> 1215.5063 | ... BK48: =BJ48 -> 1215.5063 | BL48: =BK48*(1+СВОД!$B$14) -> 1276.2816 | BM48: =BL48 -> 1276.2816 | BN48: =BM48 -> 1276.2816 | BO48: =BN48 -> 1276.2816 | BP48: =BO48 -> 1276.2816 | BQ48: =BP48 -> 1276.2816 | BR48: =BQ48 -> 1276.2816 | BS48: =BR48 -> 1276.2816 | BT48: =BS48 -> 1276.2816 | ... BW48: =BV48 -> 1276.2816 | BX48: =BW48*(1+СВОД!$B$14) -> 1340.0956 | BY48: =BX48 -> 1340.0956 | BZ48: =BY48 -> 1340.0956 | CA48: =BZ48 -> 1340.0956 | CB48: =CA48 -> 1340.0956 | CC48: =CB48 -> 1340.0956 | CD48: =CC48 -> 1340.0956 | CE48: =CD48 -> 1340.0956 | CF48: =CE48 -> 1340.0956 | ... CI48: =CH48 -> 1340.0956 | CJ48: =CI48*(1+СВОД!$B$14) -> 1407.1004 | CK48: =CJ48 -> 1407.1004 | CL48: =CK48 -> 1407.1004 | CM48: =CL48 -> 1407.1004 | CN48: =CM48 -> 1407.1004 | CO48: =CN48 -> 1407.1004 | CP48: =CO48 -> 1407.1004 | CQ48: =CP48 -> 1407.1004 | CR48: =CQ48 -> 1407.1004 | ... CU48: =CT48 -> 1407.1004 | CV48: =CU48*(1+СВОД!$B$14) -> 1477.4554 | CW48: =CV48 -> 1477.4554 | CX48: =CW48 -> 1477.4554 | CY48: =CX48 -> 1477.4554 | CZ48: =CY48 -> 1477.4554 | DA48: =CZ48 -> 1477.4554 | DB48: =DA48 -> 1477.4554 | DC48: =DB48 -> 1477.4554 | DD48: =DC48 -> 1477.4554 | ... DG48: =DF48 -> 1477.4554 | DH48: =DG48*(1+СВОД!$B$14) -> 1551.3282 | DI48: =DH48 -> 1551.3282 | DJ48: =DI48 -> 1551.3282 | DK48: =DJ48 -> 1551.3282 | DL48: =DK48 -> 1551.3282 | DM48: =DL48 -> 1551.3282 | DN48: =DM48 -> 1551.3282 | DO48: =DN48 -> 1551.3282 | DP48: =DO48 -> 1551.3282 | ... DS48: =DR48 -> 1551.3282 | DT48: =DS48*(1+СВОД!$B$14) -> 1628.8946 | DU48: =DT48 -> 1628.8946
A49: =A45 -> продукт 2 | B49: 850 | D49: =$B49*price -> 850 | E49: =$B49*price -> 850 | F49: =$B49*price -> 850 | G49: =$B49*price -> 850 | H49: =$B49*price -> 850 | I49: =$B49*price -> 850 | J49: =$B49*price -> 850 | K49: =$B49*price -> 850 | ... O49: =$B49*price -> 850 | P49: =$B49*(1+СВОД!$B$14)*price -> 892.5 | Q49: =$B49*(1+СВОД!$B$14)*price -> 892.5 | R49: =$B49*(1+СВОД!$B$14)*price -> 892.5 | S49: =$B49*(1+СВОД!$B$14)*price -> 892.5 | T49: =$B49*(1+СВОД!$B$14)*price -> 892.5 | U49: =$B49*(1+СВОД!$B$14)*price -> 892.5 | V49: =$B49*(1+СВОД!$B$14)*price -> 892.5 | W49: =$B49*(1+СВОД!$B$14)*price -> 892.5 | ... AA49: =$B49*(1+СВОД!$B$14)*price -> 892.5 | AB49: =$AA49*(1+СВОД!$B$14) -> 937.125 | AC49: =$AA49*(1+СВОД!$B$14) -> 937.125 | AD49: =$AA49*(1+СВОД!$B$14) -> 937.125 | AE49: =$AA49*(1+СВОД!$B$14) -> 937.125 | AF49: =$AA49*(1+СВОД!$B$14) -> 937.125 | AG49: =$AA49*(1+СВОД!$B$14) -> 937.125 | AH49: =$AA49*(1+СВОД!$B$14) -> 937.125 | AI49: =$AA49*(1+СВОД!$B$14) -> 937.125 | ... AM49: =$AA49*(1+СВОД!$B$14) -> 937.125 | AN49: =AM49*(1+СВОД!$B$14) -> 983.98125 | AO49: =AN49 -> 983.98125 | AP49: =AO49 -> 983.98125 | AQ49: =AP49 -> 983.98125 | AR49: =AQ49 -> 983.98125 | AS49: =AR49 -> 983.98125 | AT49: =AS49 -> 983.98125 | AU49: =AT49 -> 983.98125 | AV49: =AU49 -> 983.98125 | ... AY49: =AX49 -> 983.98125 | AZ49: =AY49*(1+СВОД!$B$14) -> 1033.1803 | BA49: =AZ49 -> 1033.1803 | BB49: =BA49 -> 1033.1803 | BC49: =BB49 -> 1033.1803 | BD49: =BC49 -> 1033.1803 | BE49: =BD49 -> 1033.1803 | BF49: =BE49 -> 1033.1803 | BG49: =BF49 -> 1033.1803 | BH49: =BG49 -> 1033.1803 | ... BK49: =BJ49 -> 1033.1803 | BL49: =BK49*(1+СВОД!$B$14) -> 1084.8393 | BM49: =BL49 -> 1084.8393 | BN49: =BM49 -> 1084.8393 | BO49: =BN49 -> 1084.8393 | BP49: =BO49 -> 1084.8393 | BQ49: =BP49 -> 1084.8393 | BR49: =BQ49 -> 1084.8393 | BS49: =BR49 -> 1084.8393 | BT49: =BS49 -> 1084.8393 | ... BW49: =BV49 -> 1084.8393 | BX49: =BW49*(1+СВОД!$B$14) -> 1139.0813 | BY49: =BX49 -> 1139.0813 | BZ49: =BY49 -> 1139.0813 | CA49: =BZ49 -> 1139.0813 | CB49: =CA49 -> 1139.0813 | CC49: =CB49 -> 1139.0813 | CD49: =CC49 -> 1139.0813 | CE49: =CD49 -> 1139.0813 | CF49: =CE49 -> 1139.0813 | ... CI49: =CH49 -> 1139.0813 | CJ49: =CI49*(1+СВОД!$B$14) -> 1196.0354 | CK49: =CJ49 -> 1196.0354 | CL49: =CK49 -> 1196.0354 | CM49: =CL49 -> 1196.0354 | CN49: =CM49 -> 1196.0354 | CO49: =CN49 -> 1196.0354 | CP49: =CO49 -> 1196.0354 | CQ49: =CP49 -> 1196.0354 | CR49: =CQ49 -> 1196.0354 | ... CU49: =CT49 -> 1196.0354 | CV49: =CU49*(1+СВОД!$B$14) -> 1255.8371 | CW49: =CV49 -> 1255.8371 | CX49: =CW49 -> 1255.8371 | CY49: =CX49 -> 1255.8371 | CZ49: =CY49 -> 1255.8371 | DA49: =CZ49 -> 1255.8371 | DB49: =DA49 -> 1255.8371 | DC49: =DB49 -> 1255.8371 | DD49: =DC49 -> 1255.8371 | ... DG49: =DF49 -> 1255.8371 | DH49: =DG49*(1+СВОД!$B$14) -> 1318.629 | DI49: =DH49 -> 1318.629 | DJ49: =DI49 -> 1318.629 | DK49: =DJ49 -> 1318.629 | DL49: =DK49 -> 1318.629 | DM49: =DL49 -> 1318.629 | DN49: =DM49 -> 1318.629 | DO49: =DN49 -> 1318.629 | DP49: =DO49 -> 1318.629 | ... DS49: =DR49 -> 1318.629 | DT49: =DS49*(1+СВОД!$B$14) -> 1384.5604 | DU49: =DT49 -> 1384.5604
A50: =A46 -> продукт 3 | B50: 750 | D50: =$B50*price -> 750 | E50: =$B50*price -> 750 | F50: =$B50*price -> 750 | G50: =$B50*price -> 750 | H50: =$B50*price -> 750 | I50: =$B50*price -> 750 | J50: =$B50*price -> 750 | K50: =$B50*price -> 750 | ... O50: =$B50*price -> 750 | P50: =$B50*(1+СВОД!$B$14)*price -> 787.5 | Q50: =$B50*(1+СВОД!$B$14)*price -> 787.5 | R50: =$B50*(1+СВОД!$B$14)*price -> 787.5 | S50: =$B50*(1+СВОД!$B$14)*price -> 787.5 | T50: =$B50*(1+СВОД!$B$14)*price -> 787.5 | U50: =$B50*(1+СВОД!$B$14)*price -> 787.5 | V50: =$B50*(1+СВОД!$B$14)*price -> 787.5 | W50: =$B50*(1+СВОД!$B$14)*price -> 787.5 | ... AA50: =$B50*(1+СВОД!$B$14)*price -> 787.5 | AB50: =$AA50*(1+СВОД!$B$14) -> 826.875 | AC50: =$AA50*(1+СВОД!$B$14) -> 826.875 | AD50: =$AA50*(1+СВОД!$B$14) -> 826.875 | AE50: =$AA50*(1+СВОД!$B$14) -> 826.875 | AF50: =$AA50*(1+СВОД!$B$14) -> 826.875 | AG50: =$AA50*(1+СВОД!$B$14) -> 826.875 | AH50: =$AA50*(1+СВОД!$B$14) -> 826.875 | AI50: =$AA50*(1+СВОД!$B$14) -> 826.875 | ... AM50: =$AA50*(1+СВОД!$B$14) -> 826.875 | AN50: =AM50*(1+СВОД!$B$14) -> 868.21875 | AO50: =AN50 -> 868.21875 | AP50: =AO50 -> 868.21875 | AQ50: =AP50 -> 868.21875 | AR50: =AQ50 -> 868.21875 | AS50: =AR50 -> 868.21875 | AT50: =AS50 -> 868.21875 | AU50: =AT50 -> 868.21875 | AV50: =AU50 -> 868.21875 | ... AY50: =AX50 -> 868.21875 | AZ50: =AY50*(1+СВОД!$B$14) -> 911.62969 | BA50: =AZ50 -> 911.62969 | BB50: =BA50 -> 911.62969 | BC50: =BB50 -> 911.62969 | BD50: =BC50 -> 911.62969 | BE50: =BD50 -> 911.62969 | BF50: =BE50 -> 911.62969 | BG50: =BF50 -> 911.62969 | BH50: =BG50 -> 911.62969 | ... BK50: =BJ50 -> 911.62969 | BL50: =BK50*(1+СВОД!$B$14) -> 957.21117 | BM50: =BL50 -> 957.21117 | BN50: =BM50 -> 957.21117 | BO50: =BN50 -> 957.21117 | BP50: =BO50 -> 957.21117 | BQ50: =BP50 -> 957.21117 | BR50: =BQ50 -> 957.21117 | BS50: =BR50 -> 957.21117 | BT50: =BS50 -> 957.21117 | ... BW50: =BV50 -> 957.21117 | BX50: =BW50*(1+СВОД!$B$14) -> 1005.0717 | BY50: =BX50 -> 1005.0717 | BZ50: =BY50 -> 1005.0717 | CA50: =BZ50 -> 1005.0717 | CB50: =CA50 -> 1005.0717 | CC50: =CB50 -> 1005.0717 | CD50: =CC50 -> 1005.0717 | CE50: =CD50 -> 1005.0717 | CF50: =CE50 -> 1005.0717 | ... CI50: =CH50 -> 1005.0717 | CJ50: =CI50*(1+СВОД!$B$14) -> 1055.3253 | CK50: =CJ50 -> 1055.3253 | CL50: =CK50 -> 1055.3253 | CM50: =CL50 -> 1055.3253 | CN50: =CM50 -> 1055.3253 | CO50: =CN50 -> 1055.3253 | CP50: =CO50 -> 1055.3253 | CQ50: =CP50 -> 1055.3253 | CR50: =CQ50 -> 1055.3253 | ... CU50: =CT50 -> 1055.3253 | CV50: =CU50*(1+СВОД!$B$14) -> 1108.0916 | CW50: =CV50 -> 1108.0916 | CX50: =CW50 -> 1108.0916 | CY50: =CX50 -> 1108.0916 | CZ50: =CY50 -> 1108.0916 | DA50: =CZ50 -> 1108.0916 | DB50: =DA50 -> 1108.0916 | DC50: =DB50 -> 1108.0916 | DD50: =DC50 -> 1108.0916 | ... DG50: =DF50 -> 1108.0916 | DH50: =DG50*(1+СВОД!$B$14) -> 1163.4962 | DI50: =DH50 -> 1163.4962 | DJ50: =DI50 -> 1163.4962 | DK50: =DJ50 -> 1163.4962 | DL50: =DK50 -> 1163.4962 | DM50: =DL50 -> 1163.4962 | DN50: =DM50 -> 1163.4962 | DO50: =DN50 -> 1163.4962 | DP50: =DO50 -> 1163.4962 | ... DS50: =DR50 -> 1163.4962 | DT50: =DS50*(1+СВОД!$B$14) -> 1221.671 | DU50: =DT50 -> 1221.671
A51: Выручка, долл. | C51: =SUM(D51:DU51) -> 6.5009942e+09 | D51: =SUM(D52:D54) -> 0 | E51: =SUM(E52:E54) -> 0 | F51: =SUM(F52:F54) -> 0 | G51: =SUM(G52:G54) -> 0 | H51: =SUM(H52:H54) -> 0 | I51: =SUM(I52:I54) -> 0 | J51: =SUM(J52:J54) -> 0 | K51: =SUM(K52:K54) -> 0 | ... DU51: =SUM(DU52:DU54) -> 72933757
A52: =A48 -> продукт 1 | C52: =SUM(D52:DU52) -> 5.0817375e+09 | D52: =D44*D48 -> 0 | E52: =E44*E48 -> 0 | F52: =F44*F48 -> 0 | G52: =G44*G48 -> 0 | H52: =H44*H48 -> 0 | I52: =I44*I48 -> 0 | J52: =J44*J48 -> 0 | K52: =K44*K48 -> 0 | ... DU52: =DU44*DU48 -> 57011312
A53: =A49 -> продукт 2 | C53: =SUM(D53:DU53) -> 1.4192567e+09 | D53: =D45*D49 -> 0 | E53: =E45*E49 -> 0 | F53: =F45*F49 -> 0 | G53: =G45*G49 -> 0 | H53: =H45*H49 -> 0 | I53: =I45*I49 -> 0 | J53: =J45*J49 -> 0 | K53: =K45*K49 -> 0 | ... DU53: =DU45*DU49 -> 15922445
A54: =A50 -> продукт 3 | C54: =SUM(D54:DU54) -> 0 | D54: =D46*D50 -> 0 | E54: =E46*E50 -> 0 | F54: =F46*F50 -> 0 | G54: =G46*G50 -> 0 | H54: =H46*H50 -> 0 | I54: =I46*I50 -> 0 | J54: =J46*J50 -> 0 | K54: =K46*K50 -> 0 | ... DU54: =DU46*DU50 -> 0
A55: НДС | C55: =SUM(D55:DU55) -> 9.9167708e+08 | D55: =D51/(1+vat)*vat -> 0 | E55: =E51/(1+vat)*vat -> 0 | F55: =F51/(1+vat)*vat -> 0 | G55: =G51/(1+vat)*vat -> 0 | H55: =H51/(1+vat)*vat -> 0 | I55: =I51/(1+vat)*vat -> 0 | J55: =J51/(1+vat)*vat -> 0 | K55: =K51/(1+vat)*vat -> 0 | ... DU55: =DU51/(1+vat)*vat -> 11125488
A56: Выручка без НДС | C56: =SUM(D56:DU56) -> 5.5093171e+09 | D56: =D51/(1+vat) -> 0 | E56: =E51/(1+vat) -> 0 | F56: =F51/(1+vat) -> 0 | G56: =G51/(1+vat) -> 0 | H56: =H51/(1+vat) -> 0 | I56: =I51/(1+vat) -> 0 | J56: =J51/(1+vat) -> 0 | K56: =K51/(1+vat) -> 0 | ... DU56: =DU51/(1+vat) -> 61808269
A59: Сырье | C59: Сумма | D59: =D3 -> 41944 | E59: =E3 -> 41974 | F59: =F3 -> 42005 | G59: =G3 -> 42036 | H59: =H3 -> 42064 | I59: =I3 -> 42095 | J59: =J3 -> 42125 | K59: =K3 -> 42156 | ... DU59: =DU3 -> 45627
A60: Цена, долл./т | B60: база
A61: =A41 -> сырье 1 | B61: 600 | D61: =$B61*raw -> 600 | E61: =$B61*raw -> 600 | F61: =$B61*raw -> 600 | G61: =$B61*raw -> 600 | H61: =$B61*raw -> 600 | I61: =$B61*raw -> 600 | J61: =$B61*raw -> 600 | K61: =$B61*raw -> 600 | ... O61: =$B61*raw -> 600 | P61: =O61*(1+СВОД!$B$15) -> 630 | Q61: =P61 -> 630 | R61: =Q61 -> 630 | S61: =R61 -> 630 | T61: =S61 -> 630 | U61: =T61 -> 630 | V61: =U61 -> 630 | W61: =V61 -> 630 | X61: =W61 -> 630 | ... AA61: =Z61 -> 630 | AB61: =AA61*(1+СВОД!$B$15) -> 661.5 | AC61: =AB61 -> 661.5 | AD61: =AC61 -> 661.5 | AE61: =AD61 -> 661.5 | AF61: =AE61 -> 661.5 | AG61: =AF61 -> 661.5 | AH61: =AG61 -> 661.5 | AI61: =AH61 -> 661.5 | AJ61: =AI61 -> 661.5 | ... AM61: =AL61 -> 661.5 | AN61: =AM61*(1+СВОД!$B$15) -> 694.575 | AO61: =AN61 -> 694.575 | AP61: =AO61 -> 694.575 | AQ61: =AP61 -> 694.575 | AR61: =AQ61 -> 694.575 | AS61: =AR61 -> 694.575 | AT61: =AS61 -> 694.575 | AU61: =AT61 -> 694.575 | AV61: =AU61 -> 694.575 | ... AY61: =AX61 -> 694.575 | AZ61: =AY61*(1+СВОД!$B$15) -> 729.30375 | BA61: =AZ61 -> 729.30375 | BB61: =BA61 -> 729.30375 | BC61: =BB61 -> 729.30375 | BD61: =BC61 -> 729.30375 | BE61: =BD61 -> 729.30375 | BF61: =BE61 -> 729.30375 | BG61: =BF61 -> 729.30375 | BH61: =BG61 -> 729.30375 | ... BK61: =BJ61 -> 729.30375 | BL61: =BK61*(1+СВОД!$B$15) -> 765.76894 | BM61: =BL61 -> 765.76894 | BN61: =BM61 -> 765.76894 | BO61: =BN61 -> 765.76894 | BP61: =BO61 -> 765.76894 | BQ61: =BP61 -> 765.76894 | BR61: =BQ61 -> 765.76894 | BS61: =BR61 -> 765.76894 | BT61: =BS61 -> 765.76894 | ... BW61: =BV61 -> 765.76894 | BX61: =BW61*(1+СВОД!$B$15) -> 804.05738 | BY61: =BX61 -> 804.05738 | BZ61: =BY61 -> 804.05738 | CA61: =BZ61 -> 804.05738 | CB61: =CA61 -> 804.05738 | CC61: =CB61 -> 804.05738 | CD61: =CC61 -> 804.05738 | CE61: =CD61 -> 804.05738 | CF61: =CE61 -> 804.05738 | ... CI61: =CH61 -> 804.05738 | CJ61: =CI61*(1+СВОД!$B$15) -> 844.26025 | CK61: =CJ61 -> 844.26025 | CL61: =CK61 -> 844.26025 | CM61: =CL61 -> 844.26025 | CN61: =CM61 -> 844.26025 | CO61: =CN61 -> 844.26025 | CP61: =CO61 -> 844.26025 | CQ61: =CP61 -> 844.26025 | CR61: =CQ61 -> 844.26025 | ... CU61: =CT61 -> 844.26025 | CV61: =CU61*(1+СВОД!$B$15) -> 886.47327 | CW61: =CV61 -> 886.47327 | CX61: =CW61 -> 886.47327 | CY61: =CX61 -> 886.47327 | CZ61: =CY61 -> 886.47327 | DA61: =CZ61 -> 886.47327 | DB61: =DA61 -> 886.47327 | DC61: =DB61 -> 886.47327 | DD61: =DC61 -> 886.47327 | ... DG61: =DF61 -> 886.47327 | DH61: =DG61*(1+СВОД!$B$15) -> 930.79693 | DI61: =DH61 -> 930.79693 | DJ61: =DI61 -> 930.79693 | DK61: =DJ61 -> 930.79693 | DL61: =DK61 -> 930.79693 | DM61: =DL61 -> 930.79693 | DN61: =DM61 -> 930.79693 | DO61: =DN61 -> 930.79693 | DP61: =DO61 -> 930.79693 | ... DS61: =DR61 -> 930.79693 | DT61: =DS61*(1+СВОД!$B$15) -> 977.33678 | DU61: =DT61 -> 977.33678
A62: =A42 -> сырье 2 | B62: 500 | D62: =$B62*raw -> 500 | E62: =$B62*raw -> 500 | F62: =$B62*raw -> 500 | G62: =$B62*raw -> 500 | H62: =$B62*raw -> 500 | I62: =$B62*raw -> 500 | J62: =$B62*raw -> 500 | K62: =$B62*raw -> 500 | ... O62: =$B62*raw -> 500 | P62: =O62*(1+СВОД!$B$15) -> 525 | Q62: =P62 -> 525 | R62: =Q62 -> 525 | S62: =R62 -> 525 | T62: =S62 -> 525 | U62: =T62 -> 525 | V62: =U62 -> 525 | W62: =V62 -> 525 | X62: =W62 -> 525 | ... AA62: =Z62 -> 525 | AB62: =AA62*(1+СВОД!$B$15) -> 551.25 | AC62: =AB62 -> 551.25 | AD62: =AC62 -> 551.25 | AE62: =AD62 -> 551.25 | AF62: =AE62 -> 551.25 | AG62: =AF62 -> 551.25 | AH62: =AG62 -> 551.25 | AI62: =AH62 -> 551.25 | AJ62: =AI62 -> 551.25 | ... AM62: =AL62 -> 551.25 | AN62: =AM62*(1+СВОД!$B$15) -> 578.8125 | AO62: =AN62 -> 578.8125 | AP62: =AO62 -> 578.8125 | AQ62: =AP62 -> 578.8125 | AR62: =AQ62 -> 578.8125 | AS62: =AR62 -> 578.8125 | AT62: =AS62 -> 578.8125 | AU62: =AT62 -> 578.8125 | AV62: =AU62 -> 578.8125 | ... AY62: =AX62 -> 578.8125 | AZ62: =AY62*(1+СВОД!$B$15) -> 607.75313 | BA62: =AZ62 -> 607.75313 | BB62: =BA62 -> 607.75313 | BC62: =BB62 -> 607.75313 | BD62: =BC62 -> 607.75313 | BE62: =BD62 -> 607.75313 | BF62: =BE62 -> 607.75313 | BG62: =BF62 -> 607.75313 | BH62: =BG62 -> 607.75313 | ... BK62: =BJ62 -> 607.75313 | BL62: =BK62*(1+СВОД!$B$15) -> 638.14078 | BM62: =BL62 -> 638.14078 | BN62: =BM62 -> 638.14078 | BO62: =BN62 -> 638.14078 | BP62: =BO62 -> 638.14078 | BQ62: =BP62 -> 638.14078 | BR62: =BQ62 -> 638.14078 | BS62: =BR62 -> 638.14078 | BT62: =BS62 -> 638.14078 | ... BW62: =BV62 -> 638.14078 | BX62: =BW62*(1+СВОД!$B$15) -> 670.04782 | BY62: =BX62 -> 670.04782 | BZ62: =BY62 -> 670.04782 | CA62: =BZ62 -> 670.04782 | CB62: =CA62 -> 670.04782 | CC62: =CB62 -> 670.04782 | CD62: =CC62 -> 670.04782 | CE62: =CD62 -> 670.04782 | CF62: =CE62 -> 670.04782 | ... CI62: =CH62 -> 670.04782 | CJ62: =CI62*(1+СВОД!$B$15) -> 703.55021 | CK62: =CJ62 -> 703.55021 | CL62: =CK62 -> 703.55021 | CM62: =CL62 -> 703.55021 | CN62: =CM62 -> 703.55021 | CO62: =CN62 -> 703.55021 | CP62: =CO62 -> 703.55021 | CQ62: =CP62 -> 703.55021 | CR62: =CQ62 -> 703.55021 | ... CU62: =CT62 -> 703.55021 | CV62: =CU62*(1+СВОД!$B$15) -> 738.72772 | CW62: =CV62 -> 738.72772 | CX62: =CW62 -> 738.72772 | CY62: =CX62 -> 738.72772 | CZ62: =CY62 -> 738.72772 | DA62: =CZ62 -> 738.72772 | DB62: =DA62 -> 738.72772 | DC62: =DB62 -> 738.72772 | DD62: =DC62 -> 738.72772 | ... DG62: =DF62 -> 738.72772 | DH62: =DG62*(1+СВОД!$B$15) -> 775.66411 | DI62: =DH62 -> 775.66411 | DJ62: =DI62 -> 775.66411 | DK62: =DJ62 -> 775.66411 | DL62: =DK62 -> 775.66411 | DM62: =DL62 -> 775.66411 | DN62: =DM62 -> 775.66411 | DO62: =DN62 -> 775.66411 | DP62: =DO62 -> 775.66411 | ... DS62: =DR62 -> 775.66411 | DT62: =DS62*(1+СВОД!$B$15) -> 814.44731 | DU62: =DT62 -> 814.44731
A63: Стоимость сырья, долл. | C63: =SUM(D63:DU63) -> 4.355775e+09 | D63: =SUM(D64:D65) -> 0 | E63: =SUM(E64:E65) -> 0 | F63: =SUM(F64:F65) -> 0 | G63: =SUM(G64:G65) -> 0 | H63: =SUM(H64:H65) -> 0 | I63: =SUM(I64:I65) -> 0 | J63: =SUM(J64:J65) -> 0 | K63: =SUM(K64:K65) -> 0 | ... DU63: =SUM(DU64:DU65) -> 48866839
A64: =A61 -> сырье 1 | C64: =SUM(D64:DU64) -> 4.355775e+09 | D64: =D41*D61 -> 0 | E64: =E41*E61 -> 0 | F64: =F41*F61 -> 0 | G64: =G41*G61 -> 0 | H64: =H41*H61 -> 0 | I64: =I41*I61 -> 0 | J64: =J41*J61 -> 0 | K64: =K41*K61 -> 0 | ... DU64: =DU41*DU61 -> 48866839
A65: =A62 -> сырье 2 | C65: =SUM(D65:DU65) -> 0 | D65: =D42*D62 -> 0 | E65: =E42*E62 -> 0 | F65: =F42*F62 -> 0 | G65: =G42*G62 -> 0 | H65: =H42*H62 -> 0 | I65: =I42*I62 -> 0 | J65: =J42*J62 -> 0 | K65: =K42*K62 -> 0 | ... DU65: =DU42*DU62 -> 0
A66: Предоплата | B66: 0.5
A67: Оплата сырья, долл. | C67: =SUM(D67:DU67) -> 4.3802084e+09 | D67: =$B$66*E63 -> 0 | E67: =(1-$B$66)*E63+$B$66*F63 -> 0 | F67: =(1-$B$66)*F63+$B$66*G63 -> 0 | G67: =(1-$B$66)*G63+$B$66*H63 -> 0 | H67: =(1-$B$66)*H63+$B$66*I63 -> 0 | I67: =(1-$B$66)*I63+$B$66*J63 -> 0 | J67: =(1-$B$66)*J63+$B$66*K63 -> 0 | K67: =(1-$B$66)*K63+$B$66*L63 -> 0 | L67: =(1-$B$66)*L63+$B$66*M63 -> 15000000 | ... DT67: =(1-$B$66)*DT63+$B$66*DU63 -> 48866839 | DU67: =DT67 -> 48866839
A68: НДС | C68: =SUM(D68:DU68) -> 6.6816738e+08 | D68: =D67/(1+vat)*vat -> 0 | E68: =E67/(1+vat)*vat -> 0 | F68: =F67/(1+vat)*vat -> 0 | G68: =G67/(1+vat)*vat -> 0 | H68: =H67/(1+vat)*vat -> 0 | I68: =I67/(1+vat)*vat -> 0 | J68: =J67/(1+vat)*vat -> 0 | K68: =K67/(1+vat)*vat -> 0 | ... DU68: =DU67/(1+vat)*vat -> 7454263.5
A69: Оплата сырья без НДС, долл. | C69: =SUM(D69:DU69) -> 3.712041e+09 | D69: =D67/(1+vat) -> 0 | E69: =E67/(1+vat) -> 0 | F69: =F67/(1+vat) -> 0 | G69: =G67/(1+vat) -> 0 | H69: =H67/(1+vat) -> 0 | I69: =I67/(1+vat) -> 0 | J69: =J67/(1+vat) -> 0 | K69: =K67/(1+vat) -> 0 | ... DU69: =DU67/(1+vat) -> 41412575
A72: Энергетика | B72: долл./мес. | C72: Сумма | D72: =D3 -> 41944 | E72: =E3 -> 41974 | F72: =F3 -> 42005 | G72: =G3 -> 42036 | H72: =H3 -> 42064 | I72: =I3 -> 42095 | J72: =J3 -> 42125 | K72: =K3 -> 42156 | ... DU72: =DU3 -> 45627
A73: Электроэнергия | B73: 800000 | C73: =SUM(D73:DU73) -> 90400000 | D73: =IF(D$40=0,0,$B73)*volume -> 0 | E73: =IF(E40=0,0,$B$73)*volume -> 0 | F73: =IF(F40=0,0,$B$73)*volume -> 0 | G73: =IF(G40=0,0,$B$73)*volume -> 0 | H73: =IF(H40=0,0,$B$73)*volume -> 0 | I73: =IF(I40=0,0,$B$73)*volume -> 0 | J73: =IF(J40=0,0,$B$73)*volume -> 0 | K73: =IF(K40=0,0,$B$73)*volume -> 0 | L73: =IF(L40=0,0,$B$73)*volume -> 0 | ... DU73: =IF(DU40=0,0,$B$73)*volume -> 800000
A74: НДС | C74: =SUM(D74:DU74) -> 13789831 | D74: =D73/(1+vat)*vat -> 0 | E74: =E73/(1+vat)*vat -> 0 | F74: =F73/(1+vat)*vat -> 0 | G74: =G73/(1+vat)*vat -> 0 | H74: =H73/(1+vat)*vat -> 0 | I74: =I73/(1+vat)*vat -> 0 | J74: =J73/(1+vat)*vat -> 0 | K74: =K73/(1+vat)*vat -> 0 | ... DU74: =DU73/(1+vat)*vat -> 122033.9
A75: Электроэнергия без НДС, долл. | C75: =SUM(D75:DU75) -> 76610169 | D75: =D73/(1+vat) -> 0 | E75: =E73/(1+vat) -> 0 | F75: =F73/(1+vat) -> 0 | G75: =G73/(1+vat) -> 0 | H75: =H73/(1+vat) -> 0 | I75: =I73/(1+vat) -> 0 | J75: =J73/(1+vat) -> 0 | K75: =K73/(1+vat) -> 0 | ... DU75: =DU73/(1+vat) -> 677966.1
A76: Предоплата | B76: 0.5
A77: Оплата э/э, долл. | C77: =SUM(D77:DU77) -> 90800000 | D77: =$B$76*E73 -> 0 | E77: =$B$76*F73 -> 0 | F77: =$B$76*G73 -> 0 | G77: =$B$76*H73 -> 0 | H77: =$B$76*I73 -> 0 | I77: =$B$76*J73 -> 0 | J77: =$B$76*K73 -> 0 | K77: =$B$76*L73 -> 0 | L77: =$B$76*M73 -> 400000 | M77: =(1-$B$76)*M73+$B$76*N73 -> 800000 | N77: =(1-$B$76)*N73+$B$76*O73 -> 800000 | O77: =(1-$B$76)*O73+$B$76*P73 -> 800000 | P77: =(1-$B$76)*P73+$B$76*Q73 -> 800000 | Q77: =(1-$B$76)*Q73+$B$76*R73 -> 800000 | R77: =(1-$B$76)*R73+$B$76*S73 -> 800000 | S77: =(1-$B$76)*S73+$B$76*T73 -> 800000 | T77: =(1-$B$76)*T73+$B$76*U73 -> 800000 | ... DT77: =(1-$B$76)*DT73+$B$76*DU73 -> 800000 | DU77: =DT77 -> 800000
A78: НДС | C78: =SUM(D78:DU78) -> 13850847 | D78: =D77/(1+vat)*vat -> 0 | E78: =E77/(1+vat)*vat -> 0 | F78: =F77/(1+vat)*vat -> 0 | G78: =G77/(1+vat)*vat -> 0 | H78: =H77/(1+vat)*vat -> 0 | I78: =I77/(1+vat)*vat -> 0 | J78: =J77/(1+vat)*vat -> 0 | K78: =K77/(1+vat)*vat -> 0 | ... DU78: =DU77/(1+vat)*vat -> 122033.9
A79: Оплата э/э без НДС, долл. | C79: =SUM(D79:DU79) -> 76949153 | D79: =D77/(1+vat) -> 0 | E79: =E77/(1+vat) -> 0 | F79: =F77/(1+vat) -> 0 | G79: =G77/(1+vat) -> 0 | H79: =H77/(1+vat) -> 0 | I79: =I77/(1+vat) -> 0 | J79: =J77/(1+vat) -> 0 | K79: =K77/(1+vat) -> 0 | ... DU79: =DU77/(1+vat) -> 677966.1
A81: Текущие расходы | B81: долл./мес. | C81: Сумма | D81: =D72 -> 41944 | E81: =E72 -> 41974 | F81: =F72 -> 42005 | G81: =G72 -> 42036 | H81: =H72 -> 42064 | I81: =I72 -> 42095 | J81: =J72 -> 42125 | K81: =K72 -> 42156 | ... DU81: =DU72 -> 45627
A82: Ремонт | B82: 0.02 | C82: =SUM(D82:DU82) -> 13126833 | D82: =IF(D$40=0,0,$B82*SUM($C$4,$C$10,$C$11)/12) -> 0 | E82: =IF(E$40=0,0,$B82*SUM($C$4,$C$10,$C$11)/12) -> 0 | F82: =IF(F$40=0,0,$B82*SUM($C$4,$C$10,$C$11)/12) -> 0 | G82: =IF(G$40=0,0,$B82*SUM($C$4,$C$10,$C$11)/12) -> 0 | H82: =IF(H$40=0,0,$B82*SUM($C$4,$C$10,$C$11)/12) -> 0 | I82: =IF(I$40=0,0,$B82*SUM($C$4,$C$10,$C$11)/12) -> 0 | J82: =IF(J$40=0,0,$B82*SUM($C$4,$C$10,$C$11)/12) -> 0 | K82: =IF(K$40=0,0,$B82*SUM($C$4,$C$10,$C$11)/12) -> 0 | ... DU82: =IF(DU$40=0,0,$B82*SUM($C$4,$C$10,$C$11)/12) -> 116166.67
A83: Спецодежда, инвентарь (год) | B83: =800*12 -> 9600 | C83: =SUM(D83:DU83) -> 96000 | D83: =IF(D$40=0,0,$B83) -> 0 | E83: =IF(E$40=0,0,$B83) -> 0 | F83: =IF(F$40=0,0,$B83) -> 0 | G83: =IF(G$40=0,0,$B83) -> 0 | H83: =IF(H$40=0,0,$B83) -> 0 | I83: =IF(I$40=0,0,$B83) -> 0 | J83: =IF(J$40=0,0,$B83) -> 0 | K83: =IF(K$40=0,0,$B83) -> 0 | ... M83: =IF(M$40=0,0,$B83) -> 9600 | N83: 0 | O83: 0 | P83: 0 | Q83: 0 | R83: 0 | S83: 0 | T83: 0 | U83: 0 | V83: 0 | W83: 0 | X83: 0 | Y83: =IF(Y$40=0,0,$B83) -> 9600 | Z83: 0 | AA83: 0 | AB83: 0 | AC83: 0 | AD83: 0 | AE83: 0 | AF83: 0 | AG83: 0 | AH83: 0 | AI83: 0 | AJ83: 0 | AK83: =IF(AK$40=0,0,$B83) -> 9600 | AL83: 0 | AM83: 0 | AN83: 0 | AO83: 0 | AP83: 0 | AQ83: 0 | AR83: 0 | AS83: 0 | AT83: 0 | AU83: 0 | AV83: 0 | AW83: =IF(AW$40=0,0,$B83) -> 9600 | AX83: 0 | AY83: 0 | AZ83: 0 | BA83: 0 | BB83: 0 | BC83: 0 | BD83: 0 | BE83: 0 | BF83: 0 | BG83: 0 | BH83: 0 | BI83: =IF(BI$40=0,0,$B83) -> 9600 | BJ83: 0 | BK83: 0 | BL83: 0 | BM83: 0 | BN83: 0 | BO83: 0 | BP83: 0 | BQ83: 0 | BR83: 0 | BS83: 0 | BT83: 0 | BU83: =IF(BU$40=0,0,$B83) -> 9600 | BV83: 0 | BW83: 0 | BX83: 0 | BY83: 0 | BZ83: 0 | CA83: 0 | CB83: 0 | CC83: 0 | CD83: 0 | CE83: 0 | CF83: 0 | CG83: =IF(CG$40=0,0,$B83) -> 9600 | CH83: 0 | CI83: 0 | CJ83: 0 | CK83: 0 | CL83: 0 | CM83: 0 | CN83: 0 | CO83: 0 | CP83: 0 | CQ83: 0 | CR83: 0 | CS83: =IF(CS$40=0,0,$B83) -> 9600 | CT83: 0 | CU83: 0 | CV83: 0 | CW83: 0 | CX83: 0 | CY83: 0 | CZ83: 0 | DA83: 0 | DB83: 0 | DC83: 0 | DD83: 0 | DE83: =IF(DE$40=0,0,$B83) -> 9600 | DF83: 0 | DG83: 0 | DH83: 0 | DI83: 0 | DJ83: 0 | DK83: 0 | DL83: 0 | DM83: 0 | DN83: 0 | DO83: 0 | DP83: 0 | DQ83: =IF(DQ$40=0,0,$B83) -> 9600 | DR83: 0 | DS83: 0 | DT83: 0 | DU83: 0
A84: Связь и интернет | B84: 4000 | C84: =SUM(D84:DU84) -> 452000 | D84: =IF(D$40=0,0,$B84) -> 0 | E84: =IF(E$40=0,0,$B84) -> 0 | F84: =IF(F$40=0,0,$B84) -> 0 | G84: =IF(G$40=0,0,$B84) -> 0 | H84: =IF(H$40=0,0,$B84) -> 0 | I84: =IF(I$40=0,0,$B84) -> 0 | J84: =IF(J$40=0,0,$B84) -> 0 | K84: =IF(K$40=0,0,$B84) -> 0 | ... DU84: =IF(DU$40=0,0,$B84) -> 4000
A85: Командировочные расходы | B85: 10000 | C85: =SUM(D85:DU85) -> 1130000 | D85: =IF(D$40=0,0,$B85) -> 0 | E85: =IF(E$40=0,0,$B85) -> 0 | F85: =IF(F$40=0,0,$B85) -> 0 | G85: =IF(G$40=0,0,$B85) -> 0 | H85: =IF(H$40=0,0,$B85) -> 0 | I85: =IF(I$40=0,0,$B85) -> 0 | J85: =IF(J$40=0,0,$B85) -> 0 | K85: =IF(K$40=0,0,$B85) -> 0 | ... DU85: =IF(DU$40=0,0,$B85) -> 10000
A86: Страхование имущества | B86: 0.01 | C86: =SUM(D86:DU86) -> 6970000 | D86: 0 | E86: 0 | F86: 0 | G86: 0 | H86: 0 | I86: 0 | J86: 0 | K86: 0 | L86: 0 | M86: =IF(M$40=0,0,$B86*SUM($C$4,$C$10,$C$11)) -> 697000 | N86: 0 | O86: 0 | P86: 0 | Q86: 0 | R86: 0 | S86: 0 | T86: 0 | U86: 0 | V86: 0 | W86: 0 | X86: 0 | Y86: =IF(Y$40=0,0,$B86*SUM($C$4,$C$10,$C$11)) -> 697000 | Z86: 0 | AA86: 0 | AB86: 0 | AC86: 0 | AD86: 0 | AE86: 0 | AF86: 0 | AG86: 0 | AH86: 0 | AI86: 0 | AJ86: 0 | AK86: =IF(AK$40=0,0,$B86*SUM($C$4,$C$10,$C$11)) -> 697000 | AL86: 0 | AM86: 0 | AN86: 0 | AO86: 0 | AP86: 0 | AQ86: 0 | AR86: 0 | AS86: 0 | AT86: 0 | AU86: 0 | AV86: 0 | AW86: =IF(AW$40=0,0,$B86*SUM($C$4,$C$10,$C$11)) -> 697000 | AX86: 0 | AY86: 0 | AZ86: 0 | BA86: 0 | BB86: 0 | BC86: 0 | BD86: 0 | BE86: 0 | BF86: 0 | BG86: 0 | BH86: 0 | BI86: =IF(BI$40=0,0,$B86*SUM($C$4,$C$10,$C$11)) -> 697000 | BJ86: 0 | BK86: 0 | BL86: 0 | BM86: 0 | BN86: 0 | BO86: 0 | BP86: 0 | BQ86: 0 | BR86: 0 | BS86: 0 | BT86: 0 | BU86: =IF(BU$40=0,0,$B86*SUM($C$4,$C$10,$C$11)) -> 697000 | BV86: 0 | BW86: 0 | BX86: 0 | BY86: 0 | BZ86: 0 | CA86: 0 | CB86: 0 | CC86: 0 | CD86: 0 | CE86: 0 | CF86: 0 | CG86: =IF(CG$40=0,0,$B86*SUM($C$4,$C$10,$C$11)) -> 697000 | CH86: 0 | CI86: 0 | CJ86: 0 | CK86: 0 | CL86: 0 | CM86: 0 | CN86: 0 | CO86: 0 | CP86: 0 | CQ86: 0 | CR86: 0 | CS86: =IF(CS$40=0,0,$B86*SUM($C$4,$C$10,$C$11)) -> 697000 | CT86: 0 | CU86: 0 | CV86: 0 | CW86: 0 | CX86: 0 | CY86: 0 | CZ86: 0 | DA86: 0 | DB86: 0 | DC86: 0 | DD86: 0 | DE86: =IF(DE$40=0,0,$B86*SUM($C$4,$C$10,$C$11)) -> 697000 | DF86: 0 | DG86: 0 | DH86: 0 | DI86: 0 | DJ86: 0 | DK86: 0 | DL86: 0 | DM86: 0 | DN86: 0 | DO86: 0 | DP86: 0 | DQ86: =IF(DQ$40=0,0,$B86*SUM($C$4,$C$10,$C$11)) -> 697000 | DR86: 0 | DS86: 0 | DT86: 0 | DU86: 0
A87: Аттестация кадров (год) | B87: 25000 | C87: =SUM(D87:DU87) -> 250000 | D87: =IF(D$40=0,0,$B87) -> 0 | E87: =IF(E$40=0,0,$B87) -> 0 | F87: =IF(F$40=0,0,$B87) -> 0 | G87: =IF(G$40=0,0,$B87) -> 0 | H87: =IF(H$40=0,0,$B87) -> 0 | I87: =IF(I$40=0,0,$B87) -> 0 | J87: =IF(J$40=0,0,$B87) -> 0 | K87: =IF(K$40=0,0,$B87) -> 0 | ... M87: =IF(M$40=0,0,$B87) -> 25000 | N87: 0 | O87: 0 | P87: 0 | Q87: 0 | R87: 0 | S87: 0 | T87: 0 | U87: 0 | V87: 0 | W87: 0 | X87: 0 | Y87: =IF(Y$40=0,0,$B87) -> 25000 | Z87: 0 | AA87: 0 | AB87: 0 | AC87: 0 | AD87: 0 | AE87: 0 | AF87: 0 | AG87: 0 | AH87: 0 | AI87: 0 | AJ87: 0 | AK87: =IF(AK$40=0,0,$B87) -> 25000 | AL87: 0 | AM87: 0 | AN87: 0 | AO87: 0 | AP87: 0 | AQ87: 0 | AR87: 0 | AS87: 0 | AT87: 0 | AU87: 0 | AV87: 0 | AW87: =IF(AW$40=0,0,$B87) -> 25000 | AX87: 0 | AY87: 0 | AZ87: 0 | BA87: 0 | BB87: 0 | BC87: 0 | BD87: 0 | BE87: 0 | BF87: 0 | BG87: 0 | BH87: 0 | BI87: =IF(BI$40=0,0,$B87) -> 25000 | BJ87: 0 | BK87: 0 | BL87: 0 | BM87: 0 | BN87: 0 | BO87: 0 | BP87: 0 | BQ87: 0 | BR87: 0 | BS87: 0 | BT87: 0 | BU87: =IF(BU$40=0,0,$B87) -> 25000 | BV87: 0 | BW87: 0 | BX87: 0 | BY87: 0 | BZ87: 0 | CA87: 0 | CB87: 0 | CC87: 0 | CD87: 0 | CE87: 0 | CF87: 0 | CG87: =IF(CG$40=0,0,$B87) -> 25000 | CH87: 0 | CI87: 0 | CJ87: 0 | CK87: 0 | CL87: 0 | CM87: 0 | CN87: 0 | CO87: 0 | CP87: 0 | CQ87: 0 | CR87: 0 | CS87: =IF(CS$40=0,0,$B87) -> 25000 | CT87: 0 | CU87: 0 | CV87: 0 | CW87: 0 | CX87: 0 | CY87: 0 | CZ87: 0 | DA87: 0 | DB87: 0 | DC87: 0 | DD87: 0 | DE87: =IF(DE$40=0,0,$B87) -> 25000 | DF87: 0 | DG87: 0 | DH87: 0 | DI87: 0 | DJ87: 0 | DK87: 0 | DL87: 0 | DM87: 0 | DN87: 0 | DO87: 0 | DP87: 0 | DQ87: =IF(DQ$40=0,0,$B87) -> 25000 | DR87: 0 | DS87: 0 | DT87: 0 | DU87: 0
A88: Обучение кадров (год) | B88: =750*12 -> 9000 | C88: =SUM(D88:DU88) -> 90000 | D88: =IF(D$40=0,0,$B88) -> 0 | E88: =IF(E$40=0,0,$B88) -> 0 | F88: =IF(F$40=0,0,$B88) -> 0 | G88: =IF(G$40=0,0,$B88) -> 0 | H88: =IF(H$40=0,0,$B88) -> 0 | I88: =IF(I$40=0,0,$B88) -> 0 | J88: =IF(J$40=0,0,$B88) -> 0 | K88: =IF(K$40=0,0,$B88) -> 0 | ... M88: =IF(M$40=0,0,$B88) -> 9000 | N88: 0 | O88: 0 | P88: 0 | Q88: 0 | R88: 0 | S88: 0 | T88: 0 | U88: 0 | V88: 0 | W88: 0 | X88: 0 | Y88: =IF(Y$40=0,0,$B88) -> 9000 | Z88: 0 | AA88: 0 | AB88: 0 | AC88: 0 | AD88: 0 | AE88: 0 | AF88: 0 | AG88: 0 | AH88: 0 | AI88: 0 | AJ88: 0 | AK88: =IF(AK$40=0,0,$B88) -> 9000 | AL88: 0 | AM88: 0 | AN88: 0 | AO88: 0 | AP88: 0 | AQ88: 0 | AR88: 0 | AS88: 0 | AT88: 0 | AU88: 0 | AV88: 0 | AW88: =IF(AW$40=0,0,$B88) -> 9000 | AX88: 0 | AY88: 0 | AZ88: 0 | BA88: 0 | BB88: 0 | BC88: 0 | BD88: 0 | BE88: 0 | BF88: 0 | BG88: 0 | BH88: 0 | BI88: =IF(BI$40=0,0,$B88) -> 9000 | BJ88: 0 | BK88: 0 | BL88: 0 | BM88: 0 | BN88: 0 | BO88: 0 | BP88: 0 | BQ88: 0 | BR88: 0 | BS88: 0 | BT88: 0 | BU88: =IF(BU$40=0,0,$B88) -> 9000 | BV88: 0 | BW88: 0 | BX88: 0 | BY88: 0 | BZ88: 0 | CA88: 0 | CB88: 0 | CC88: 0 | CD88: 0 | CE88: 0 | CF88: 0 | CG88: =IF(CG$40=0,0,$B88) -> 9000 | CH88: 0 | CI88: 0 | CJ88: 0 | CK88: 0 | CL88: 0 | CM88: 0 | CN88: 0 | CO88: 0 | CP88: 0 | CQ88: 0 | CR88: 0 | CS88: =IF(CS$40=0,0,$B88) -> 9000 | CT88: 0 | CU88: 0 | CV88: 0 | CW88: 0 | CX88: 0 | CY88: 0 | CZ88: 0 | DA88: 0 | DB88: 0 | DC88: 0 | DD88: 0 | DE88: =IF(DE$40=0,0,$B88) -> 9000 | DF88: 0 | DG88: 0 | DH88: 0 | DI88: 0 | DJ88: 0 | DK88: 0 | DL88: 0 | DM88: 0 | DN88: 0 | DO88: 0 | DP88: 0 | DQ88: =IF(DQ$40=0,0,$B88) -> 9000 | DR88: 0 | DS88: 0 | DT88: 0 | DU88: 0
A89: Прочее | B89: 150000 | C89: =SUM(D89:DU89) -> 16950000 | D89: =IF(D$40=0,0,$B89) -> 0 | E89: =IF(E$40=0,0,$B89) -> 0 | F89: =IF(F$40=0,0,$B89) -> 0 | G89: =IF(G$40=0,0,$B89) -> 0 | H89: =IF(H$40=0,0,$B89) -> 0 | I89: =IF(I$40=0,0,$B89) -> 0 | J89: =IF(J$40=0,0,$B89) -> 0 | K89: =IF(K$40=0,0,$B89) -> 0 | L89: =IF(L$40=0,0,$B89) -> 0 | M89: =IF(M$40=0,15000,$B89) -> 150000 | N89: =IF(N$40=0,15000,$B89) -> 150000 | O89: =IF(O$40=0,15000,$B89) -> 150000 | P89: =IF(P$40=0,15000,$B89) -> 150000 | Q89: =IF(Q$40=0,15000,$B89) -> 150000 | R89: =IF(R$40=0,0,$B89) -> 150000 | S89: =IF(S$40=0,0,$B89) -> 150000 | T89: =IF(T$40=0,0,$B89) -> 150000 | U89: =IF(U$40=0,0,$B89) -> 150000 | V89: =IF(V$40=0,0,$B89) -> 150000 | W89: =IF(W$40=0,0,$B89) -> 150000 | X89: =IF(X$40=0,0,$B89) -> 150000 | Y89: =IF(Y$40=0,0,$B89) -> 150000 | ... DU89: =IF(DU$40=0,0,$B89) -> 150000
A90: Канцелярские расходы | B90: 1000 | C90: =SUM(D90:DU90) -> 113000 | D90: =IF(D$40=0,0,$B90) -> 0 | E90: =IF(E$40=0,0,$B90) -> 0 | F90: =IF(F$40=0,0,$B90) -> 0 | G90: =IF(G$40=0,0,$B90) -> 0 | H90: =IF(H$40=0,0,$B90) -> 0 | I90: =IF(I$40=0,0,$B90) -> 0 | J90: =IF(J$40=0,0,$B90) -> 0 | K90: =IF(K$40=0,0,$B90) -> 0 | ... DU90: =IF(DU$40=0,0,$B90) -> 1000
A91: Содержание автотранспорта | B91: 10000 | C91: =SUM(D91:DU91) -> 1130000 | D91: =IF(D$40=0,0,$B91) -> 0 | E91: =IF(E$40=0,0,$B91) -> 0 | F91: =IF(F$40=0,0,$B91) -> 0 | G91: =IF(G$40=0,0,$B91) -> 0 | H91: =IF(H$40=0,0,$B91) -> 0 | I91: =IF(I$40=0,0,$B91) -> 0 | J91: =IF(J$40=0,0,$B91) -> 0 | K91: =IF(K$40=0,0,$B91) -> 0 | ... DU91: =IF(DU$40=0,0,$B91) -> 10000
A92: Аудит (квартал) | B92: 25000 | C92: =SUM(D92:DU92) -> 950000 | D92: =IF(D$40=0,0,$B92) -> 0 | E92: =IF(E$40=0,0,$B92) -> 0 | F92: =IF(F$40=0,0,$B92) -> 0 | G92: =IF(G$40=0,0,$B92) -> 0 | H92: =IF(H$40=0,0,$B92) -> 0 | I92: =IF(I$40=0,0,$B92) -> 0 | J92: =IF(J$40=0,0,$B92) -> 0 | K92: =IF(K$40=0,0,$B92) -> 0 | ... M92: =IF(M$40=0,0,$B92) -> 25000 | N92: 0 | O92: 0 | P92: =IF(P$40=0,0,$B92) -> 25000 | Q92: 0 | R92: 0 | S92: =IF(S$40=0,0,$B92) -> 25000 | T92: 0 | U92: 0 | V92: =IF(V$40=0,0,$B92) -> 25000 | W92: 0 | X92: 0 | Y92: =IF(Y$40=0,0,$B92) -> 25000 | Z92: 0 | AA92: 0 | AB92: =IF(AB$40=0,0,$B92) -> 25000 | AC92: 0 | AD92: 0 | AE92: =IF(AE$40=0,0,$B92) -> 25000 | AF92: 0 | AG92: 0 | AH92: =IF(AH$40=0,0,$B92) -> 25000 | AI92: 0 | AJ92: 0 | AK92: =IF(AK$40=0,0,$B92) -> 25000 | AL92: 0 | AM92: 0 | AN92: =IF(AN$40=0,0,$B92) -> 25000 | AO92: 0 | AP92: 0 | AQ92: =IF(AQ$40=0,0,$B92) -> 25000 | AR92: 0 | AS92: 0 | AT92: =IF(AT$40=0,0,$B92) -> 25000 | AU92: 0 | AV92: 0 | AW92: =IF(AW$40=0,0,$B92) -> 25000 | AX92: 0 | AY92: 0 | AZ92: =IF(AZ$40=0,0,$B92) -> 25000 | BA92: 0 | BB92: 0 | BC92: =IF(BC$40=0,0,$B92) -> 25000 | BD92: 0 | BE92: 0 | BF92: =IF(BF$40=0,0,$B92) -> 25000 | BG92: 0 | BH92: 0 | BI92: =IF(BI$40=0,0,$B92) -> 25000 | BJ92: 0 | BK92: 0 | BL92: =IF(BL$40=0,0,$B92) -> 25000 | BM92: 0 | BN92: 0 | BO92: =IF(BO$40=0,0,$B92) -> 25000 | BP92: 0 | BQ92: 0 | BR92: =IF(BR$40=0,0,$B92) -> 25000 | BS92: 0 | BT92: 0 | BU92: =IF(BU$40=0,0,$B92) -> 25000 | BV92: 0 | BW92: 0 | BX92: =IF(BX$40=0,0,$B92) -> 25000 | BY92: 0 | BZ92: 0 | CA92: =IF(CA$40=0,0,$B92) -> 25000 | CB92: 0 | CC92: 0 | CD92: =IF(CD$40=0,0,$B92) -> 25000 | CE92: 0 | CF92: 0 | CG92: =IF(CG$40=0,0,$B92) -> 25000 | CH92: 0 | CI92: 0 | CJ92: =IF(CJ$40=0,0,$B92) -> 25000 | CK92: 0 | CL92: 0 | CM92: =IF(CM$40=0,0,$B92) -> 25000 | CN92: 0 | CO92: 0 | CP92: =IF(CP$40=0,0,$B92) -> 25000 | CQ92: 0 | CR92: 0 | CS92: =IF(CS$40=0,0,$B92) -> 25000 | CT92: 0 | CU92: 0 | CV92: =IF(CV$40=0,0,$B92) -> 25000 | CW92: 0 | CX92: 0 | CY92: =IF(CY$40=0,0,$B92) -> 25000 | CZ92: 0 | DA92: 0 | DB92: =IF(DB$40=0,0,$B92) -> 25000 | DC92: 0 | DD92: 0 | DE92: =IF(DE$40=0,0,$B92) -> 25000 | DF92: 0 | DG92: 0 | DH92: =IF(DH$40=0,0,$B92) -> 25000 | DI92: 0 | DJ92: 0 | DK92: =IF(DK$40=0,0,$B92) -> 25000 | DL92: 0 | DM92: 0 | DN92: =IF(DN$40=0,0,$B92) -> 25000 | DO92: 0 | DP92: 0 | DQ92: =IF(DQ$40=0,0,$B92) -> 25000 | DR92: 0 | DS92: 0 | DT92: =IF(DT$40=0,0,$B92) -> 25000 | DU92: 0
A93: Охрана | B93: 25000 | C93: =SUM(D93:DU93) -> 2825000 | D93: =IF(D$40=0,0,$B93) -> 0 | E93: =IF(E$40=0,0,$B93) -> 0 | F93: =IF(F$40=0,0,$B93) -> 0 | G93: =IF(G$40=0,0,$B93) -> 0 | H93: =IF(H$40=0,0,$B93) -> 0 | I93: =IF(I$40=0,0,$B93) -> 0 | J93: =IF(J$40=0,0,$B93) -> 0 | K93: =IF(K$40=0,0,$B93) -> 0 | ... DU93: =IF(DU$40=0,0,$B93) -> 25000
A94: Представительские | B94: 10000 | C94: =SUM(D94:DU94) -> 1130000 | D94: =IF(D$40=0,0,$B94) -> 0 | E94: =IF(E$40=0,0,$B94) -> 0 | F94: =IF(F$40=0,0,$B94) -> 0 | G94: =IF(G$40=0,0,$B94) -> 0 | H94: =IF(H$40=0,0,$B94) -> 0 | I94: =IF(I$40=0,0,$B94) -> 0 | J94: =IF(J$40=0,0,$B94) -> 0 | K94: =IF(K$40=0,0,$B94) -> 0 | ... DU94: =IF(DU$40=0,0,$B94) -> 10000
C95: =SUM(D95:DU95) -> 0 | D95: =IF(D$40=0,0,$B95) -> 0 | E95: =IF(E$40=0,0,$B95) -> 0 | F95: =IF(F$40=0,0,$B95) -> 0 | G95: =IF(G$40=0,0,$B95) -> 0 | H95: =IF(H$40=0,0,$B95) -> 0 | I95: =IF(I$40=0,0,$B95) -> 0 | J95: =IF(J$40=0,0,$B95) -> 0 | K95: =IF(K$40=0,0,$B95) -> 0 | ... DU95: =IF(DU$40=0,0,$B95) -> 0
A96: Итого расходы | C96: =SUM(D96:BK96) -> 20762500 | D96: =SUM(D82:D95) -> 0 | E96: =SUM(E82:E95) -> 0 | F96: =SUM(F82:F95) -> 0 | G96: =SUM(G82:G95) -> 0 | H96: =SUM(H82:H95) -> 0 | I96: =SUM(I82:I95) -> 0 | J96: =SUM(J82:J95) -> 0 | K96: =SUM(K82:K95) -> 0 | ... DU96: =SUM(DU82:DU95) -> 326166.67
A97: НДС | C97: =SUM(D97:BK97) -> 3167161 | D97: =D96/(1+vat)*vat -> 0 | E97: =E96/(1+vat)*vat -> 0 | F97: =F96/(1+vat)*vat -> 0 | G97: =G96/(1+vat)*vat -> 0 | H97: =H96/(1+vat)*vat -> 0 | I97: =I96/(1+vat)*vat -> 0 | J97: =J96/(1+vat)*vat -> 0 | K97: =K96/(1+vat)*vat -> 0 | ... DU97: =DU96/(1+vat)*vat -> 49754.237
A98: Расходы без НДС | C98: =SUM(D98:BK98) -> 17595339 | D98: =D96/(1+vat) -> 0 | E98: =E96/(1+vat) -> 0 | F98: =F96/(1+vat) -> 0 | G98: =G96/(1+vat) -> 0 | H98: =H96/(1+vat) -> 0 | I98: =I96/(1+vat) -> 0 | J98: =J96/(1+vat) -> 0 | K98: =K96/(1+vat) -> 0 | ... DU98: =DU96/(1+vat) -> 276412.43
A101: ФОТ | B101: долл./мес. | C101: Сумма | D101: =D3 -> 41944 | E101: =E3 -> 41974 | F101: =F3 -> 42005 | G101: =G3 -> 42036 | H101: =H3 -> 42064 | I101: =I3 -> 42095 | J101: =J3 -> 42125 | K101: =K3 -> 42156 | ... DU101: =DU3 -> 45627
A102: управляющий | B102: 25000 | M102: 1 | N102: =M102 -> 1 | O102: =N102 -> 1 | P102: =O102 -> 1 | Q102: =P102 -> 1 | R102: =Q102 -> 1 | S102: =R102 -> 1 | T102: =S102 -> 1 | U102: =T102 -> 1 | ... DU102: =DT102 -> 1
A103: менеджер по производству | B103: 10000 | M103: 1 | N103: =M103 -> 1 | O103: =N103 -> 1 | P103: =O103 -> 1 | Q103: =P103 -> 1 | R103: =Q103 -> 1 | S103: =R103 -> 1 | T103: =S103 -> 1 | U103: =T103 -> 1 | ... DU103: =DT103 -> 1
A104: менеджер по снабжению | B104: 5000 | M104: 3 | N104: =M104 -> 3 | O104: =N104 -> 3 | P104: =O104 -> 3 | Q104: =P104 -> 3 | R104: =Q104 -> 3 | S104: =R104 -> 3 | T104: =S104 -> 3 | U104: =T104 -> 3 | ... DU104: =DT104 -> 3
A105: менеджер по сбыту | B105: 5000 | M105: 1 | N105: =M105 -> 1 | O105: =N105 -> 1 | P105: =O105 -> 1 | Q105: =P105 -> 1 | R105: =Q105 -> 1 | S105: =R105 -> 1 | T105: =S105 -> 1 | U105: =T105 -> 1 | ... DU105: =DT105 -> 1
A106: главный бухгалтер | B106: 4000 | M106: 1 | N106: =M106 -> 1 | O106: =N106 -> 1 | P106: =O106 -> 1 | Q106: =P106 -> 1 | R106: =Q106 -> 1 | S106: =R106 -> 1 | T106: =S106 -> 1 | U106: =T106 -> 1 | ... DU106: =DT106 -> 1
A107: бухгалтер | B107: 3000 | M107: 1 | N107: =M107 -> 1 | O107: =N107 -> 1 | P107: =O107 -> 1 | Q107: =P107 -> 1 | R107: =Q107 -> 1 | S107: =R107 -> 1 | T107: =S107 -> 1 | U107: =T107 -> 1 | ... DU107: =DT107 -> 1
A108: водитель | B108: 2000 | M108: 3 | N108: =M108 -> 3 | O108: =N108 -> 3 | P108: =O108 -> 3 | Q108: =P108 -> 3 | R108: =Q108 -> 3 | S108: =R108 -> 3 | T108: =S108 -> 3 | U108: =T108 -> 3 | ... DU108: =DT108 -> 3
A109: юрисконсульт | B109: 3000 | M109: 1 | N109: =M109 -> 1 | O109: =N109 -> 1 | P109: =O109 -> 1 | Q109: =P109 -> 1 | R109: =Q109 -> 1 | S109: =R109 -> 1 | T109: =S109 -> 1 | U109: =T109 -> 1 | ... DU109: =DT109 -> 1
A110: референт-переводчик | B110: 2000 | M110: 1 | N110: =M110 -> 1 | O110: =N110 -> 1 | P110: =O110 -> 1 | Q110: =P110 -> 1 | R110: =Q110 -> 1 | S110: =R110 -> 1 | T110: =S110 -> 1 | U110: =T110 -> 1 | ... DU110: =DT110 -> 1
A111: повар | B111: 2500 | M111: 6 | N111: =M111 -> 6 | O111: =N111 -> 6 | P111: =O111 -> 6 | Q111: =P111 -> 6 | R111: =Q111 -> 6 | S111: =R111 -> 6 | T111: =S111 -> 6 | U111: =T111 -> 6 | ... DU111: =DT111 -> 6
A112: старший смены-технолог | B112: 3000 | M112: 8 | N112: =M112 -> 8 | O112: =N112 -> 8 | P112: =O112 -> 8 | Q112: =P112 -> 8 | R112: =Q112 -> 8 | S112: =R112 -> 8 | T112: =S112 -> 8 | U112: =T112 -> 8 | ... DU112: =DT112 -> 8
...

Sheet кредит
A1: =title -> Вариант 1 | B1: http://exceltable.com/ | D1: 1 | E1: 2 | F1: 3 | G1: 4 | H1: 5 | I1: 6 | J1: 7 | K1: 8 | L1: 9 | M1: 10 | N1: 11 | O1: 12 | P1: 13 | Q1: 14 | R1: 15 | S1: 16 | T1: 17 | U1: 18 | V1: 19 | W1: 20 | X1: 21 | Y1: 22 | Z1: 23 | AA1: 24 | AB1: 25 | AC1: 26 | AD1: 27 | AE1: 28 | AF1: 29 | AG1: 30 | AH1: 31 | AI1: 32 | AJ1: 33 | AK1: 34 | AL1: 35 | AM1: 36 | AN1: 37 | AO1: 38 | AP1: 39 | AQ1: 40 | AR1: 41 | AS1: 42 | AT1: 43 | AU1: 44 | AV1: 45 | AW1: 46 | AX1: 47 | AY1: 48 | AZ1: 49 | BA1: 50 | BB1: 51 | BC1: 52 | BD1: 53 | BE1: 54 | BF1: 55 | BG1: 56 | BH1: 57 | BI1: 58 | BJ1: 59 | BK1: 60 | BL1: 61 | BM1: 62 | BN1: 63 | BO1: 64 | BP1: 65 | BQ1: 66 | BR1: 67 | BS1: 68 | BT1: 69 | BU1: 70 | BV1: 71 | BW1: 72 | BX1: 73 | BY1: 74 | BZ1: 75 | CA1: 76 | CB1: 77 | CC1: 78 | CD1: 79 | CE1: 80 | CF1: 81 | CG1: 82 | CH1: 83 | CI1: 84 | CJ1: 85 | CK1: 86 | CL1: 87 | CM1: 88 | CN1: 89 | CO1: 90 | CP1: 91 | CQ1: 92 | CR1: 93 | CS1: 94 | CT1: 95 | CU1: 96 | CV1: 97 | CW1: 98 | CX1: 99 | CY1: 100 | CZ1: 101 | DA1: 102 | DB1: 103 | DC1: 104 | DD1: 105 | DE1: 106 | DF1: 107 | DG1: 108 | DH1: 109 | DI1: 110 | DJ1: 111 | DK1: 112 | DL1: 113 | DM1: 114 | DN1: 115 | DO1: 116 | DP1: 117 | DQ1: 118 | DR1: 119 | DS1: 120 | DT1: 121 | DU1: 122
A2: =cur -> USD | D2: =YEAR(D3) -> 2014 | E2: =YEAR(E3) -> 2014 | F2: =YEAR(F3) -> 2015 | G2: =YEAR(G3) -> 2015 | H2: =YEAR(H3) -> 2015 | I2: =YEAR(I3) -> 2015 | J2: =YEAR(J3) -> 2015 | K2: =YEAR(K3) -> 2015 | ... DU2: =YEAR(DU3) -> 2024
A3: Кредит | C3: Сумма | D3: =данные!D3 -> 41944 | E3: =данные!E3 -> 41974 | F3: =данные!F3 -> 42005 | G3: =данные!G3 -> 42036 | H3: =данные!H3 -> 42064 | I3: =данные!I3 -> 42095 | J3: =данные!J3 -> 42125 | K3: =данные!K3 -> 42156 | ... DU3: =данные!DU3 -> 45627
A4: Получение | C4: =SUM(D4:DU4) -> 87100000 | D4: =-ROUNDUP((MIN(0,'Cash Flow'!D17+'Cash Flow'!D23-'Cash Flow'!D31))/100000,0)*100000+D16 -> 52300000 | E4: =-ROUNDUP((MIN(0,'Cash Flow'!D36+'Cash Flow'!E17+'Cash Flow'!E23-'Cash Flow'!E31))/100000,0)*100000+E16 -> 900000 | F4: =-ROUNDUP((MIN(0,'Cash Flow'!E36+'Cash Flow'!F17+'Cash Flow'!F23-'Cash Flow'!F31))/100000,0)*100000+F16 -> 1100000 | G4: =-ROUNDUP((MIN(0,'Cash Flow'!F36+'Cash Flow'!G17+'Cash Flow'!G23-'Cash Flow'!G31))/100000,0)*100000+G16 -> 900000 | H4: =-ROUNDUP((MIN(0,'Cash Flow'!G36+'Cash Flow'!H17+'Cash Flow'!H23-'Cash Flow'!H31))/100000,0)*100000+H16 -> 2200000 | I4: =-ROUNDUP((MIN(0,'Cash Flow'!H36+'Cash Flow'!I17+'Cash Flow'!I23-'Cash Flow'!I31))/100000,0)*100000+I16 -> 1600000 | J4: =-ROUNDUP((MIN(0,'Cash Flow'!I36+'Cash Flow'!J17+'Cash Flow'!J23-'Cash Flow'!J31))/100000,0)*100000+J16 -> 1100000 | K4: =-ROUNDUP((MIN(0,'Cash Flow'!J36+'Cash Flow'!K17+'Cash Flow'!K23-'Cash Flow'!K31))/100000,0)*100000+K16 -> 1500000 | L4: =-ROUNDUP((MIN(0,'Cash Flow'!K36+'Cash Flow'!L17+'Cash Flow'!L23-'Cash Flow'!L31))/100000,0)*100000+L16 -> 17400000 | M4: =-ROUNDUP((MIN(0,'Cash Flow'!L36+'Cash Flow'!M17+'Cash Flow'!M23-'Cash Flow'!M31))/100000,0)*100000+M16 -> 8100000
A5: Льготный период, мес. | B5: 12
A6: Срок, мес. | B6: =IF(var=1,СВОД!B19,СВОД!C19) -> 18
A7: Погашение | C7: =SUM(D7:BK7) -> 87100000 | E7: =IF(AND(E1>$B$5,E1<=$B$6+1),$C$4/($B$6-$B$5+1),0) -> 0 | F7: =IF(AND(F1>$B$5,F1<=$B$6+1),$C$4/($B$6-$B$5+1),0) -> 0 | G7: =IF(AND(G1>$B$5,G1<=$B$6+1),$C$4/($B$6-$B$5+1),0) -> 0 | H7: =IF(AND(H1>$B$5,H1<=$B$6+1),$C$4/($B$6-$B$5+1),0) -> 0 | I7: =IF(AND(I1>$B$5,I1<=$B$6+1),$C$4/($B$6-$B$5+1),0) -> 0 | J7: =IF(AND(J1>$B$5,J1<=$B$6+1),$C$4/($B$6-$B$5+1),0) -> 0 | K7: =IF(AND(K1>$B$5,K1<=$B$6+1),$C$4/($B$6-$B$5+1),0) -> 0 | L7: =IF(AND(L1>$B$5,L1<=$B$6+1),$C$4/($B$6-$B$5+1),0) -> 0 | ... DU7: =IF(AND(DU1>$B$5,DU1<=$B$6+1),$C$4/($B$6-$B$5+1),0) -> 0
A8: Проценты
A9: начисленные | C9: =SUM(D9:BK9) -> 5885833.3 | E9: =IF(E1<=$B$5,D11*$B$10/12,0) -> 435833.33 | F9: =IF(F1<=$B$5,E11*$B$10/12,0) -> 443333.33 | G9: =IF(G1<=$B$5,F11*$B$10/12,0) -> 452500 | H9: =IF(H1<=$B$5,G11*$B$10/12,0) -> 460000 | I9: =IF(I1<=$B$5,H11*$B$10/12,0) -> 478333.33 | J9: =IF(J1<=$B$5,I11*$B$10/12,0) -> 491666.67 | K9: =IF(K1<=$B$5,J11*$B$10/12,0) -> 500833.33 | L9: =IF(L1<=$B$5,K11*$B$10/12,0) -> 513333.33 | ... DU9: =IF(DU1<=$B$5,DT11*$B$10/12,0) -> 0
A10: выплаченные | B10: 0.1 | C10: =SUM(D10:BK10) -> 8789166.7 | E10: =IF(E1>$B$5,D11*$B$10/12,0)+IF(E1=$B$5+1,SUM($D$9:E9),0) -> 0 | F10: =IF(F1>$B$5,E11*$B$10/12,0)+IF(F1=$B$5+1,SUM($D$9:F9),0) -> 0 | G10: =IF(G1>$B$5,F11*$B$10/12,0)+IF(G1=$B$5+1,SUM($D$9:G9),0) -> 0 | H10: =IF(H1>$B$5,G11*$B$10/12,0)+IF(H1=$B$5+1,SUM($D$9:H9),0) -> 0 | I10: =IF(I1>$B$5,H11*$B$10/12,0)+IF(I1=$B$5+1,SUM($D$9:I9),0) -> 0 | J10: =IF(J1>$B$5,I11*$B$10/12,0)+IF(J1=$B$5+1,SUM($D$9:J9),0) -> 0 | K10: =IF(K1>$B$5,J11*$B$10/12,0)+IF(K1=$B$5+1,SUM($D$9:K9),0) -> 0 | L10: =IF(L1>$B$5,K11*$B$10/12,0)+IF(L1=$B$5+1,SUM($D$9:L9),0) -> 0 | ... DU10: =IF(DU1>$B$5,DT11*$B$10/12,0)+IF(DU1=$B$5+1,SUM($D$9:DU9),0) -> 0
A11: Остаток долга | C11: =BK11 -> 0 | D11: =D4-D7 -> 52300000 | E11: =D11+E4-E7 -> 53200000 | F11: =E11+F4-F7 -> 54300000 | G11: =F11+G4-G7 -> 55200000 | H11: =G11+H4-H7 -> 57400000 | I11: =H11+I4-I7 -> 59000000 | J11: =I11+J4-J7 -> 60100000 | K11: =J11+K4-K7 -> 61600000 | L11: =K11+L4-L7 -> 79000000 | ... DU11: =DT11+DU4-DU7 -> 0
A14: Резерв, вариант 1 | D14: 1000000 | E14: 800000 | F14: 800000 | G14: 700000 | H14: 1200000 | I14: 1300000 | J14: 900000 | K14: 900000 | L14: 1400000
A15: Резерв, вариант 2 | D15: 1000000 | E15: 800000 | F15: 800000 | G15: 700000 | H15: 1200000 | I15: 1300000 | J15: 900000 | K15: 900000 | L15: 6500000
D16: =IF(var=1,D14,D15) -> 1000000 | E16: =IF(var=1,E14,E15) -> 800000 | F16: =IF(var=1,F14,F15) -> 800000 | G16: =IF(var=1,G14,G15) -> 700000 | H16: =IF(var=1,H14,H15) -> 1200000 | I16: =IF(var=1,I14,I15) -> 1300000 | J16: =IF(var=1,J14,J15) -> 900000 | K16: =IF(var=1,K14,K15) -> 900000 | ... DM16: =IF(var=1,DM14,DM15) -> 0

Sheet Cash Flow
A1: =title -> Вариант 1 | C1: http://exceltable.com/ | D1: 1 | E1: 2 | F1: 3 | G1: 4 | H1: 5 | I1: 6 | J1: 7 | K1: 8 | L1: 9 | M1: 10 | N1: 11 | O1: 12 | P1: 13 | Q1: 14 | R1: 15 | S1: 16 | T1: 17 | U1: 18 | V1: 19 | W1: 20 | X1: 21 | Y1: 22 | Z1: 23 | AA1: 24 | AB1: 25 | AC1: 26 | AD1: 27 | AE1: 28 | AF1: 29 | AG1: 30 | AH1: 31 | AI1: 32 | AJ1: 33 | AK1: 34 | AL1: 35 | AM1: 36 | AN1: 37 | AO1: 38 | AP1: 39 | AQ1: 40 | AR1: 41 | AS1: 42 | AT1: 43 | AU1: 44 | AV1: 45 | AW1: 46 | AX1: 47 | AY1: 48 | AZ1: 49 | BA1: 50 | BB1: 51 | BC1: 52 | BD1: 53 | BE1: 54 | BF1: 55 | BG1: 56 | BH1: 57 | BI1: 58 | BJ1: 59 | BK1: 60 | BL1: 61 | BM1: 62 | BN1: 63 | BO1: 64 | BP1: 65 | BQ1: 66 | BR1: 67 | BS1: 68 | BT1: 69 | BU1: 70 | BV1: 71 | BW1: 72 | BX1: 73 | BY1: 74 | BZ1: 75 | CA1: 76 | CB1: 77 | CC1: 78 | CD1: 79 | CE1: 80 | CF1: 81 | CG1: 82 | CH1: 83 | CI1: 84 | CJ1: 85 | CK1: 86 | CL1: 87 | CM1: 88 | CN1: 89 | CO1: 90 | CP1: 91 | CQ1: 92 | CR1: 93 | CS1: 94 | CT1: 95 | CU1: 96 | CV1: 97 | CW1: 98 | CX1: 99 | CY1: 100 | CZ1: 101 | DA1: 102 | DB1: 103 | DC1: 104 | DD1: 105 | DE1: 106 | DF1: 107 | DG1: 108 | DH1: 109 | DI1: 110 | DJ1: 111 | DK1: 112 | DL1: 113 | DM1: 114 | DN1: 115 | DO1: 116 | DP1: 117 | DQ1: 118 | DR1: 119 | DS1: 120 | DT1: 121 | DU1: 122
A2: =cur -> USD | D2: =YEAR(D3) -> 2014 | E2: =YEAR(E3) -> 2014 | F2: =YEAR(F3) -> 2015 | G2: =YEAR(G3) -> 2015 | H2: =YEAR(H3) -> 2015 | I2: =YEAR(I3) -> 2015 | J2: =YEAR(J3) -> 2015 | K2: =YEAR(K3) -> 2015 | ... DU2: =YEAR(DU3) -> 2024
A3: Движение денежных средств | C3: Сумма | D3: =данные!D3 -> 41944 | E3: =данные!E3 -> 41974 | F3: =данные!F3 -> 42005 | G3: =данные!G3 -> 42036 | H3: =данные!H3 -> 42064 | I3: =данные!I3 -> 42095 | J3: =данные!J3 -> 42125 | K3: =данные!K3 -> 42156 | ... DU3: =данные!DU3 -> 45627
A4: 1. Основная деятельность
A5: Выручка от реализации | C5: =SUM(D5:DU5) -> 6.5009942e+09 | D5: =данные!D51-данные!D156 -> 0 | E5: =данные!E51-данные!E156 -> 0 | F5: =данные!F51-данные!F156 -> 0 | G5: =данные!G51-данные!G156 -> 0 | H5: =данные!H51-данные!H156 -> 0 | I5: =данные!I51-данные!I156 -> 0 | J5: =данные!J51-данные!J156 -> 0 | K5: =данные!K51-данные!K156 -> 0 | ... DU5: =данные!DU51-данные!DU156 -> 72933757
A6: Прямые расходы | C6: =SUM(D6:DU6) -> 4.4710084e+09 | D6: =D7+D8 -> 0 | E6: =E7+E8 -> 0 | F6: =F7+F8 -> 0 | G6: =G7+G8 -> 0 | H6: =H7+H8 -> 0 | I6: =I7+I8 -> 0 | J6: =J7+J8 -> 0 | K6: =K7+K8 -> 0 | ... DU6: =DU7+DU8 -> 49666839
A7: сырье | C7: =SUM(D7:DU7) -> 4.3802084e+09 | D7: =данные!D67 -> 0 | E7: =данные!E67 -> 0 | F7: =данные!F67 -> 0 | G7: =данные!G67 -> 0 | H7: =данные!H67 -> 0 | I7: =данные!I67 -> 0 | J7: =данные!J67 -> 0 | K7: =данные!K67 -> 0 | ... DU7: =данные!DU67 -> 48866839
A8: энергия | C8: =SUM(D8:DU8) -> 90800000 | D8: =данные!D77 -> 0 | E8: =данные!E77 -> 0 | F8: =данные!F77 -> 0 | G8: =данные!G77 -> 0 | H8: =данные!H77 -> 0 | I8: =данные!I77 -> 0 | J8: =данные!J77 -> 0 | K8: =данные!K77 -> 0 | ... DU8: =данные!DU77 -> 800000
A9: Постоянные расходы | C9: =SUM(D9:DU9) -> 85590747 | D9: =SUM(D10:D11) -> 0 | E9: =SUM(E10:E11) -> 0 | F9: =SUM(F10:F11) -> 0 | G9: =SUM(G10:G11) -> 0 | H9: =SUM(H10:H11) -> 0 | I9: =SUM(I10:I11) -> 0 | J9: =SUM(J10:J11) -> 0 | K9: =SUM(K10:K11) -> 0 | ... DU9: =SUM(DU10:DU11) -> 713584
A10: ФОТ | C10: =SUM(D10:DU10) -> 40377913 | D10: =данные!D118-данные!D165 -> 0 | E10: =данные!E118-(данные!E165-данные!D165) -> 0 | F10: =данные!F118-(данные!F165-данные!E165) -> 0 | G10: =данные!G118-(данные!G165-данные!F165) -> 0 | H10: =данные!H118-(данные!H165-данные!G165) -> 0 | I10: =данные!I118-(данные!I165-данные!H165) -> 0 | J10: =данные!J118-(данные!J165-данные!I165) -> 0 | K10: =данные!K118-(данные!K165-данные!J165) -> 0 | L10: =данные!L118-(данные!L165-данные!K165) -> 0 | ... DU10: =данные!DU118-(данные!DU165-данные!DT165) -> 387417.33
A11: общие издержки | C11: =SUM(D11:DU11) -> 45212833 | D11: =данные!D96-данные!D164 -> 0 | E11: =данные!E96-(данные!E164-данные!E164) -> 0 | F11: =данные!F96-(данные!F164-данные!F164) -> 0 | G11: =данные!G96-(данные!G164-данные!G164) -> 0 | H11: =данные!H96-(данные!H164-данные!H164) -> 0 | I11: =данные!I96-(данные!I164-данные!I164) -> 0 | J11: =данные!J96-(данные!J164-данные!J164) -> 0 | K11: =данные!K96-(данные!K164-данные!K164) -> 0 | L11: =данные!L96-(данные!L164-данные!L164) -> 0 | ... DU11: =данные!DU96-(данные!DU164-данные!DU164) -> 326166.67
A12: Суммарные издержки производства | C12: =SUM(D12:DU12) -> 4.5565992e+09 | D12: =SUM(D6,D9) -> 0 | E12: =SUM(E6,E9) -> 0 | F12: =SUM(F6,F9) -> 0 | G12: =SUM(G6,G9) -> 0 | H12: =SUM(H6,H9) -> 0 | I12: =SUM(I6,I9) -> 0 | J12: =SUM(J6,J9) -> 0 | K12: =SUM(K6,K9) -> 0 | ... DU12: =SUM(DU6,DU9) -> 50380423
A13: Налоги | C13: =SUM(D13:DU13) -> 6.1672746e+08 | D13: =SUM(D14:D16) -> 0 | E13: =SUM(E14:E16) -> 0 | F13: =SUM(F14:F16) -> 0 | G13: =SUM(G14:G16) -> 0 | H13: =SUM(H14:H16) -> 0 | I13: =SUM(I14:I16) -> 0 | J13: =SUM(J14:J16) -> 0 | K13: =SUM(K14:K16) -> 0 | ... DU13: =SUM(DU14:DU16) -> 7212198.2
A14: НДС | C14: =SUM(D14:DU14) -> 2.9022479e+08 | D14: =данные!D144-данные!D166 -> 0 | E14: =данные!E144-(данные!E166-данные!D166) -> 0 | F14: =данные!F144-(данные!F166-данные!E166) -> 0 | G14: =данные!G144-(данные!G166-данные!F166) -> 0 | H14: =данные!H144-(данные!H166-данные!G166) -> 0 | I14: =данные!I144-(данные!I166-данные!H166) -> 0 | J14: =данные!J144-(данные!J166-данные!I166) -> 0 | K14: =данные!K144-(данные!K166-данные!J166) -> 0 | L14: =данные!L144-(данные!L166-данные!K166) -> 0 | ... DU14: =данные!DU144-(данные!DU166-данные!DT166) -> 3499436.7
A15: Налог на имущество | C15: =SUM(D15:DU15) -> 8550389.4 | D15: =данные!D150 -> 0 | E15: =данные!E150 -> 0 | F15: =данные!F150 -> 0 | G15: =данные!G150 -> 0 | H15: =данные!H150 -> 0 | I15: =данные!I150 -> 0 | J15: =данные!J150 -> 0 | K15: =данные!K150 -> 0 | ... DU15: =данные!DU150 -> 0
A16: Налог на прибыль | C16: =SUM(D16:DU16) -> 3.1795227e+08 | D16: =PL!D18-данные!D167 -> 0 | E16: =PL!E18-(данные!E167-данные!D167) -> 0 | F16: =PL!F18-(данные!F167-данные!E167) -> 0 | G16: =PL!G18-(данные!G167-данные!F167) -> 0 | H16: =PL!H18-(данные!H167-данные!G167) -> 0 | I16: =PL!I18-(данные!I167-данные!H167) -> 0 | J16: =PL!J18-(данные!J167-данные!I167) -> 0 | K16: =PL!K18-(данные!K167-данные!J167) -> 0 | L16: =PL!L18-(данные!L167-данные!K167) -> 0 | ... DU16: =PL!DU18-(данные!DU167-данные!DT167) -> 3712761.5
A17: Итого кэш-фло по основной деятельности | C17: =SUM(D17:DU17) -> 1.3276676e+09 | D17: =D5-D12-D13 -> 0 | E17: =E5-E12-E13 -> 0 | F17: =F5-F12-F13 -> 0 | G17: =G5-G12-G13 -> 0 | H17: =H5-H12-H13 -> 0 | I17: =I5-I12-I13 -> 0 | J17: =J5-J12-J13 -> 0 | K17: =K5-K12-K13 -> 0 | ... DU17: =DU5-DU12-DU13 -> 15341136
A19: 2. Инвестиционная деятельность
A20: Реализация основных средств | C20: =SUM(D20:DU20) -> 0 | G20: 0 | H20: 0 | I20: 0 | J20: 0 | K20: 0 | L20: 0 | M20: 0 | N20: 0 | O20: 0 | P20: 0 | Q20: 0 | R20: 0 | S20: 0 | T20: 0 | U20: 0 | V20: 0 | W20: 0 | X20: 0 | Y20: 0 | Z20: 0 | AA20: 0 | AB20: 0 | AC20: 0 | AD20: 0 | AE20: 0 | AF20: 0 | AG20: 0 | AH20: 0 | AI20: 0 | AJ20: 0 | AK20: 0 | AL20: 0 | AM20: 0 | AN20: 0 | AO20: 0 | AP20: 0 | AQ20: 0 | AR20: 0 | AS20: 0 | AT20: 0 | AU20: 0 | AV20: 0 | AW20: 0 | AX20: 0 | AY20: 0 | AZ20: 0 | BA20: 0 | BB20: 0 | BC20: 0 | BD20: 0 | BE20: 0 | BF20: 0 | BG20: 0 | BH20: 0 | BI20: 0 | BJ20: 0 | BK20: 0 | BL20: 0 | BM20: 0 | BN20: 0 | BO20: 0 | BP20: 0 | BQ20: 0 | BR20: 0 | BS20: 0 | BT20: 0 | BU20: 0 | BV20: 0 | BW20: 0 | BX20: 0 | BY20: 0 | BZ20: 0 | CA20: 0 | CB20: 0 | CC20: 0 | CD20: 0 | CE20: 0 | CF20: 0 | CG20: 0 | CH20: 0 | CI20: 0 | CJ20: 0 | CK20: 0 | CL20: 0 | CM20: 0 | CN20: 0 | CO20: 0 | CP20: 0 | CQ20: 0 | CR20: 0 | CS20: 0 | CT20: 0 | CU20: 0 | CV20: 0 | CW20: 0 | CX20: 0 | CY20: 0 | CZ20: 0 | DA20: 0 | DB20: 0 | DC20: 0 | DD20: 0 | DE20: 0 | DF20: 0 | DG20: 0 | DH20: 0 | DI20: 0 | DJ20: 0 | DK20: 0 | DL20: 0 | DM20: 0 | DN20: 0 | DO20: 0 | DP20: 0 | DQ20: 0 | DR20: 0 | DS20: 0 | DT20: 0 | DU20: 0
A21: Затраты на приобретение активов | C21: =SUM(D21:DU21) -> 82088400 | D21: =SUM(данные!D4:D5,данные!D7,данные!D9:D12)*capex -> 51197900 | E21: =SUM(данные!E4:E5,данные!E7,данные!E9:E12)*capex -> 1065000 | F21: =SUM(данные!F4:F5,данные!F7,данные!F9:F12)*capex -> 1065000 | G21: =SUM(данные!G4:G5,данные!G7,данные!G9:G12)*capex -> 1065000 | H21: =SUM(данные!H4:H5,данные!H7,данные!H9:H12)*capex -> 1670500 | I21: =SUM(данные!I4:I5,данные!I7,данные!I9:I12)*capex -> 1495000 | J21: =SUM(данные!J4:J5,данные!J7,данные!J9:J12)*capex -> 1495000 | K21: =SUM(данные!K4:K5,данные!K7,данные!K9:K12)*capex -> 1495000 | ... DU21: =SUM(данные!DU4:DU5,данные!DU7,данные!DU9:DU12)*capex -> 0
A22: Прочие расходы подготовительного периода | C22: =SUM(D22:DU22) -> 99780 | D22: =SUM(данные!D6,данные!D8) -> 99780 | E22: =SUM(данные!E6,данные!E8) -> 0 | F22: =SUM(данные!F6,данные!F8) -> 0 | G22: =SUM(данные!G6,данные!G8) -> 0 | H22: =SUM(данные!H6,данные!H8) -> 0 | I22: =SUM(данные!I6,данные!I8) -> 0 | J22: =SUM(данные!J6,данные!J8) -> 0 | K22: =SUM(данные!K6,данные!K8) -> 0 | ... DU22: =SUM(данные!DU6,данные!DU8) -> 0
A23: Итого кэш-фло по инвест. деятельности | C23: =SUM(D23:DU23) -> -82188180 | D23: =D20-D21-D22 -> -51297680 | E23: =E20-E21-E22 -> -1065000 | F23: =F20-F21-F22 -> -1065000 | G23: =G20-G21-G22 -> -1065000 | H23: =H20-H21-H22 -> -1670500 | I23: =I20-I21-I22 -> -1495000 | J23: =J20-J21-J22 -> -1495000 | K23: =K20-K21-K22 -> -1495000 | ... DU23: =DU20-DU21-DU22 -> 0
A25: 3. Финансовая деятельность
A26: Собственный капитал | C26: =SUM(D26:DU26) -> 0 | D26: 0 | E26: 0 | F26: 0 | G26: 0 | H26: 0 | I26: 0 | J26: 0 | K26: 0 | L26: 0 | M26: 0 | N26: 0 | O26: 0 | P26: 0 | Q26: 0 | R26: 0 | S26: 0 | T26: 0 | U26: 0 | V26: 0 | W26: 0 | X26: 0 | Y26: 0 | Z26: 0 | AA26: 0 | AB26: 0 | AC26: 0 | AD26: 0 | AE26: 0 | AF26: 0 | AG26: 0 | AH26: 0 | AI26: 0 | AJ26: 0 | AK26: 0 | AL26: 0 | AM26: 0 | AN26: 0 | AO26: 0 | AP26: 0 | AQ26: 0 | AR26: 0 | AS26: 0 | AT26: 0 | AU26: 0 | AV26: 0 | AW26: 0 | AX26: 0 | AY26: 0 | AZ26: 0 | BA26: 0 | BB26: 0 | BC26: 0 | BD26: 0 | BE26: 0 | BF26: 0 | BG26: 0 | BH26: 0 | BI26: 0 | BJ26: 0 | BK26: 0 | BL26: 0 | BM26: 0 | BN26: 0 | BO26: 0 | BP26: 0 | BQ26: 0 | BR26: 0 | BS26: 0 | BT26: 0 | BU26: 0 | BV26: 0 | BW26: 0 | BX26: 0 | BY26: 0 | BZ26: 0 | CA26: 0 | CB26: 0 | CC26: 0 | CD26: 0 | CE26: 0 | CF26: 0 | CG26: 0 | CH26: 0 | CI26: 0 | CJ26: 0 | CK26: 0 | CL26: 0 | CM26: 0 | CN26: 0 | CO26: 0 | CP26: 0 | CQ26: 0 | CR26: 0 | CS26: 0 | CT26: 0 | CU26: 0 | CV26: 0 | CW26: 0 | CX26: 0 | CY26: 0 | CZ26: 0 | DA26: 0 | DB26: 0 | DC26: 0 | DD26: 0 | DE26: 0 | DF26: 0 | DG26: 0 | DH26: 0 | DI26: 0 | DJ26: 0 | DK26: 0 | DL26: 0 | DM26: 0 | DN26: 0 | DO26: 0 | DP26: 0 | DQ26: 0 | DR26: 0 | DS26: 0 | DT26: 0 | DU26: 0
C27: =SUM(D27:DU27) -> 0
A28: Получение кредита | C28: =SUM(D28:DU28) -> 87100000 | D28: =кредит!D4 -> 52300000 | E28: =кредит!E4 -> 900000 | F28: =кредит!F4 -> 1100000 | G28: =кредит!G4 -> 900000 | H28: =кредит!H4 -> 2200000 | I28: =кредит!I4 -> 1600000 | J28: =кредит!J4 -> 1100000 | K28: =кредит!K4 -> 1500000 | ... DU28: =кредит!DU4 -> 0
A29: Платежи по кредиту | C29: =SUM(D29:DU29) -> 95889167 | D29: =D30+D31 -> 0 | E29: =E30+E31 -> 0 | F29: =F30+F31 -> 0 | G29: =G30+G31 -> 0 | H29: =H30+H31 -> 0 | I29: =I30+I31 -> 0 | J29: =J30+J31 -> 0 | K29: =K30+K31 -> 0 | ... DU29: =DU30+DU31 -> 0
A30: Погашение долга | C30: =SUM(D30:DU30) -> 87100000 | D30: =кредит!D7 -> 0 | E30: =кредит!E7 -> 0 | F30: =кредит!F7 -> 0 | G30: =кредит!G7 -> 0 | H30: =кредит!H7 -> 0 | I30: =кредит!I7 -> 0 | J30: =кредит!J7 -> 0 | K30: =кредит!K7 -> 0 | ... DU30: =кредит!DU7 -> 0
A31: Проценты | C31: =SUM(D31:DU31) -> 8789166.7 | D31: =кредит!D10 -> 0 | E31: =кредит!E10 -> 0 | F31: =кредит!F10 -> 0 | G31: =кредит!G10 -> 0 | H31: =кредит!H10 -> 0 | I31: =кредит!I10 -> 0 | J31: =кредит!J10 -> 0 | K31: =кредит!K10 -> 0 | ... DU31: =кредит!DU10 -> 0
C32: =SUM(D32:DU32) -> 0
A33: Итого кэш-фло по финансовой деятельности | C33: =SUM(D33:DU33) -> -8789166.7 | D33: =D26+D28-D29 -> 52300000 | E33: =E26+E28-E29 -> 900000 | F33: =F26+F28-F29 -> 1100000 | G33: =G26+G28-G29 -> 900000 | H33: =H26+H28-H29 -> 2200000 | I33: =I26+I28-I29 -> 1600000 | J33: =J26+J28-J29 -> 1100000 | K33: =K26+K28-K29 -> 1500000 | ... DU33: =DU26+DU28-DU29 -> 0
A35: Итого поток денежных средств | C35: =SUM(D35:DU35) -> 1.2366902e+09 | D35: =D17+D23+D33 -> 1002320 | E35: =E17+E23+E33 -> -165000 | F35: =F17+F23+F33 -> 35000 | G35: =G17+G23+G33 -> -165000 | H35: =H17+H23+H33 -> 529500 | I35: =I17+I23+I33 -> 105000 | J35: =J17+J23+J33 -> -395000 | K35: =K17+K23+K33 -> 5000 | ... DU35: =DU17+DU23+DU33 -> 15341136
A36: Баланс денежных средств на конец периода | C36: =DU36 -> 1.2366902e+09 | D36: =D35 -> 1002320 | E36: =D36+E35 -> 837320 | F36: =E36+F35 -> 872320 | G36: =F36+G35 -> 707320 | H36: =G36+H35 -> 1236820 | I36: =H36+I35 -> 1341820 | J36: =I36+J35 -> 946820 | K36: =J36+K35 -> 951820 | L36: =K36+L35 -> 1438495.5 | ... DU36: =DT36+DU35 -> 1.2366902e+09
A39: Движение денежных средств | C39: Сумма | D39: =D3 -> 41944 | E39: =E3 -> 41974 | F39: =F3 -> 42005 | G39: =G3 -> 42036 | H39: =H3 -> 42064 | I39: =I3 -> 42095 | J39: =J3 -> 42125 | K39: =K3 -> 42156 | ... DU39: =DU3 -> 45627
A40: Чистая прибыль | C40: =SUM(D40:DU40) -> 1.2718091e+09 | D40: =PL!D19 -> -84559.322 | E40: =PL!E19 -> 0 | F40: =PL!F19 -> 0 | G40: =PL!G19 -> 0 | H40: =PL!H19 -> 0 | I40: =PL!I19 -> -28166.667 | J40: =PL!J19 -> -28166.667 | K40: =PL!K19 -> -28166.667 | ... DU40: =PL!DU19 -> 14851046
A41: Амортизация | C41: =SUM(D41:DU41) -> 55492828 | D41: =PL!D14 -> 0 | E41: =PL!E14 -> 0 | F41: =PL!F14 -> 0 | G41: =PL!G14 -> 0 | H41: =PL!H14 -> 0 | I41: =PL!I14 -> 28166.667 | J41: =PL!J14 -> 28166.667 | K41: =PL!K14 -> 28166.667 | ... DU41: =PL!DU14 -> 490089.92
A42: Изменение оборотного капитала | C42: =SUM(D42:DU42) -> -21045271 | D42: =BS!D10 -> 0 | E42: =-(BS!E10-BS!D10) -> 0 | F42: =-(BS!F10-BS!E10) -> 0 | G42: =-(BS!G10-BS!F10) -> 0 | H42: =-(BS!H10-BS!G10) -> 0 | I42: =-(BS!I10-BS!H10) -> 0 | J42: =-(BS!J10-BS!I10) -> 0 | K42: =-(BS!K10-BS!J10) -> 0 | L42: =-(BS!L10-BS!K10) -> -13050847 | ... DU42: =-(BS!DU10-BS!DT10) -> -4.7683716e-07
A43: НДС по приобретенным ценностям | C43: =SUM(D43:DU43) -> 0 | D43: =-(BS!D12-BS!C12) -> -7825069.8 | E43: =-(BS!E12-BS!D12) -> -162457.63 | F43: =-(BS!F12-BS!E12) -> -162457.63 | G43: =-(BS!G12-BS!F12) -> -162457.63 | H43: =-(BS!H12-BS!G12) -> -254822.03 | I43: =-(BS!I12-BS!H12) -> -228050.85 | J43: =-(BS!J12-BS!I12) -> -228050.85 | K43: =-(BS!K12-BS!J12) -> -228050.85 | ... DU43: =-(BS!DU12-BS!DT12) -> 0
A44: Поток д/с от операций | C44: =SUM(D44:DU44) -> 1.3062567e+09 | D44: =D40+D41+D42+D43 -> -7909629.2 | E44: =E40+E41+E42+E43 -> -162457.63 | F44: =F40+F41+F42+F43 -> -162457.63 | G44: =G40+G41+G42+G43 -> -162457.63 | H44: =H40+H41+H42+H43 -> -254822.03 | I44: =I40+I41+I42+I43 -> -228050.85 | J44: =J40+J41+J42+J43 -> -228050.85 | K44: =K40+K41+K42+K43 -> -228050.85 | ... DU44: =DU40+DU41+DU42+DU43 -> 15341136
A45: Поток д/с от инвестиц. деятельности | C45: =SUM(D45:DU45) -> -69566441 | D45: =-(SUM(данные!D4:D5,данные!D7,данные!D9:D12)/(1+vat)) -> -43388051 | E45: =-(SUM(данные!E4:E5,данные!E7,данные!E9:E12)/(1+vat)) -> -902542.37 | F45: =-(SUM(данные!F4:F5,данные!F7,данные!F9:F12)/(1+vat)) -> -902542.37 | G45: =-(SUM(данные!G4:G5,данные!G7,данные!G9:G12)/(1+vat)) -> -902542.37 | H45: =-(SUM(данные!H4:H5,данные!H7,данные!H9:H12)/(1+vat)) -> -1415678 | I45: =-(SUM(данные!I4:I5,данные!I7,данные!I9:I12)/(1+vat)) -> -1266949.2 | J45: =-(SUM(данные!J4:J5,данные!J7,данные!J9:J12)/(1+vat)) -> -1266949.2 | K45: =-(SUM(данные!K4:K5,данные!K7,данные!K9:K12)/(1+vat)) -> -1266949.2 | ... DU45: =-(SUM(данные!DU4:DU5,данные!DU7,данные!DU9:DU12)/(1+vat)) -> 0
A46: Свободный поток д/с | C46: =SUM(D46:DU46) -> 1.2366902e+09 | D46: =D44+D45 -> -51297680 | E46: =E44+E45 -> -1065000 | F46: =F44+F45 -> -1065000 | G46: =G44+G45 -> -1065000 | H46: =H44+H45 -> -1670500 | I46: =I44+I45 -> -1495000 | J46: =J44+J45 -> -1495000 | K46: =K44+K45 -> -1495000 | ... DU46: =DU44+DU45 -> 15341136
A47: Расчеты с учредителями | C47: =SUM(D47:DU47) -> 0 | D47: =D26 -> 0 | E47: =E26 -> 0 | F47: =F26 -> 0 | G47: =G26 -> 0 | H47: =H26 -> 0 | I47: =I26 -> 0 | J47: =J26 -> 0 | K47: =K26 -> 0 | ... DU47: =DU26 -> 0
A48: Изменение долга | C48: =SUM(D48:DU48) -> -3.7252903e-09 | D48: =D28-D30 -> 52300000 | E48: =E28-E30 -> 900000 | F48: =F28-F30 -> 1100000 | G48: =G28-G30 -> 900000 | H48: =H28-H30 -> 2200000 | I48: =I28-I30 -> 1600000 | J48: =J28-J30 -> 1100000 | K48: =K28-K30 -> 1500000 | ... DU48: =DU28-DU30 -> 0
A49: Чистый поток д/с | C49: =SUM(D49:DU49) -> 1.2366902e+09 | D49: =D46+D47+D48 -> 1002320 | E49: =E46+E47+E48 -> -165000 | F49: =F46+F47+F48 -> 35000 | G49: =G46+G47+G48 -> -165000 | H49: =H46+H47+H48 -> 529500 | I49: =I46+I47+I48 -> 105000 | J49: =J46+J47+J48 -> -395000 | K49: =K46+K47+K48 -> 5000 | ... DU49: =DU46+DU47+DU48 -> 15341136
C50: =SUM(D50:DU50) -> 2.3043249e-06 | D50: =D35-D49 -> 7.4505806e-09 | E50: =E35-E49 -> 2.3283064e-10 | F50: =F35-F49 -> 2.3283064e-10 | G50: =G35-G49 -> 2.3283064e-10 | H50: =H35-H49 -> 0 | I50: =I35-I49 -> -2.3283064e-10 | J50: =J35-J49 -> 0 | K50: =K35-K49 -> -2.3283064e-10 | ... DU50: =DU35-DU49 -> 4.7124922e-07
A52: млн. USD
A53: Движение денежных средств | C53: Сумма | D53: 2014 | E53: 2015 | F53: 2016 | G53: 2017 | H53: 2018 | I53: 2019 | J53: 2020 | K53: 2021 | L53: 2022 | M53: 2023 | N53: 2024
A54: 1. Основная деятельность
A55: Выручка от реализации | C55: =SUM(D55:DU55) -> 6500.9942 | D55: =SUMIF($D$2:$DU$2,"="&D$53,$D5:$DU5)/1000000 -> 0 | E55: =SUMIF($D$2:$DU$2,"="&E$53,$D5:$DU5)/1000000 -> 228.3525 | F55: =SUMIF($D$2:$DU$2,"="&F$53,$D5:$DU5)/1000000 -> 568.86637 | G55: =SUMIF($D$2:$DU$2,"="&G$53,$D5:$DU5)/1000000 -> 597.30969 | H55: =SUMIF($D$2:$DU$2,"="&H$53,$D5:$DU5)/1000000 -> 627.17518 | I55: =SUMIF($D$2:$DU$2,"="&I$53,$D5:$DU5)/1000000 -> 658.53394 | J55: =SUMIF($D$2:$DU$2,"="&J$53,$D5:$DU5)/1000000 -> 691.46063 | K55: =SUMIF($D$2:$DU$2,"="&K$53,$D5:$DU5)/1000000 -> 726.03367 | ... N55: =SUMIF($D$2:$DU$2,"="&N$53,$D5:$DU5)/1000000 -> 840.47472
A56: Прямые расходы | C56: =SUM(D56:DU56) -> 4471.0084 | D56: =SUMIF($D$2:$DU$2,"="&D$53,$D6:$DU6)/1000000 -> 0 | E56: =SUMIF($D$2:$DU$2,"="&E$53,$D6:$DU6)/1000000 -> 173.15 | F56: =SUMIF($D$2:$DU$2,"="&F$53,$D6:$DU6)/1000000 -> 391.5375 | G56: =SUMIF($D$2:$DU$2,"="&G$53,$D6:$DU6)/1000000 -> 410.63437 | H56: =SUMIF($D$2:$DU$2,"="&H$53,$D6:$DU6)/1000000 -> 430.68609 | I56: =SUMIF($D$2:$DU$2,"="&I$53,$D6:$DU6)/1000000 -> 451.7404 | J56: =SUMIF($D$2:$DU$2,"="&J$53,$D6:$DU6)/1000000 -> 473.84742 | K56: =SUMIF($D$2:$DU$2,"="&K$53,$D6:$DU6)/1000000 -> 497.05979 | ... N56: =SUMIF($D$2:$DU$2,"="&N$53,$D6:$DU6)/1000000 -> 573.89564
A57: сырье | C57: =SUM(D57:DU57) -> 4380.2084 | D57: =SUMIF($D$2:$DU$2,"="&D$53,$D7:$DU7)/1000000 -> 0 | E57: =SUMIF($D$2:$DU$2,"="&E$53,$D7:$DU7)/1000000 -> 168.75 | F57: =SUMIF($D$2:$DU$2,"="&F$53,$D7:$DU7)/1000000 -> 381.9375 | G57: =SUMIF($D$2:$DU$2,"="&G$53,$D7:$DU7)/1000000 -> 401.03438 | H57: =SUMIF($D$2:$DU$2,"="&H$53,$D7:$DU7)/1000000 -> 421.08609 | I57: =SUMIF($D$2:$DU$2,"="&I$53,$D7:$DU7)/1000000 -> 442.1404 | J57: =SUMIF($D$2:$DU$2,"="&J$53,$D7:$DU7)/1000000 -> 464.24742 | K57: =SUMIF($D$2:$DU$2,"="&K$53,$D7:$DU7)/1000000 -> 487.45979 | ... N57: =SUMIF($D$2:$DU$2,"="&N$53,$D7:$DU7)/1000000 -> 564.29564
A58: энергия | C58: =SUM(D58:DU58) -> 90.8 | D58: =SUMIF($D$2:$DU$2,"="&D$53,$D8:$DU8)/1000000 -> 0 | E58: =SUMIF($D$2:$DU$2,"="&E$53,$D8:$DU8)/1000000 -> 4.4 | F58: =SUMIF($D$2:$DU$2,"="&F$53,$D8:$DU8)/1000000 -> 9.6 | G58: =SUMIF($D$2:$DU$2,"="&G$53,$D8:$DU8)/1000000 -> 9.6 | H58: =SUMIF($D$2:$DU$2,"="&H$53,$D8:$DU8)/1000000 -> 9.6 | I58: =SUMIF($D$2:$DU$2,"="&I$53,$D8:$DU8)/1000000 -> 9.6 | J58: =SUMIF($D$2:$DU$2,"="&J$53,$D8:$DU8)/1000000 -> 9.6 | K58: =SUMIF($D$2:$DU$2,"="&K$53,$D8:$DU8)/1000000 -> 9.6 | ... N58: =SUMIF($D$2:$DU$2,"="&N$53,$D8:$DU8)/1000000 -> 9.6
A59: Постоянные расходы | C59: =SUM(D59:DU59) -> 85.590747 | D59: =SUMIF($D$2:$DU$2,"="&D$53,$D9:$DU9)/1000000 -> 0 | E59: =SUMIF($D$2:$DU$2,"="&E$53,$D9:$DU9)/1000000 -> 4.0629867 | F59: =SUMIF($D$2:$DU$2,"="&F$53,$D9:$DU9)/1000000 -> 8.749136 | G59: =SUMIF($D$2:$DU$2,"="&G$53,$D9:$DU9)/1000000 -> 8.826512 | H59: =SUMIF($D$2:$DU$2,"="&H$53,$D9:$DU9)/1000000 -> 8.903888 | I59: =SUMIF($D$2:$DU$2,"="&I$53,$D9:$DU9)/1000000 -> 8.981264 | J59: =SUMIF($D$2:$DU$2,"="&J$53,$D9:$DU9)/1000000 -> 9.05864 | K59: =SUMIF($D$2:$DU$2,"="&K$53,$D9:$DU9)/1000000 -> 9.136016 | ... N59: =SUMIF($D$2:$DU$2,"="&N$53,$D9:$DU9)/1000000 -> 9.368144
A60: ФОТ | C60: =SUM(D60:DU60) -> 40.377913 | D60: =SUMIF($D$2:$DU$2,"="&D$53,$D10:$DU10)/1000000 -> 0 | E60: =SUMIF($D$2:$DU$2,"="&E$53,$D10:$DU10)/1000000 -> 1.6415533 | F60: =SUMIF($D$2:$DU$2,"="&F$53,$D10:$DU10)/1000000 -> 3.994536 | G60: =SUMIF($D$2:$DU$2,"="&G$53,$D10:$DU10)/1000000 -> 4.071912 | H60: =SUMIF($D$2:$DU$2,"="&H$53,$D10:$DU10)/1000000 -> 4.149288 | I60: =SUMIF($D$2:$DU$2,"="&I$53,$D10:$DU10)/1000000 -> 4.226664 | J60: =SUMIF($D$2:$DU$2,"="&J$53,$D10:$DU10)/1000000 -> 4.30404 | K60: =SUMIF($D$2:$DU$2,"="&K$53,$D10:$DU10)/1000000 -> 4.381416 | ... N60: =SUMIF($D$2:$DU$2,"="&N$53,$D10:$DU10)/1000000 -> 4.613544
A61: общие издержки | C61: =SUM(D61:DU61) -> 45.212833 | D61: =SUMIF($D$2:$DU$2,"="&D$53,$D11:$DU11)/1000000 -> 0 | E61: =SUMIF($D$2:$DU$2,"="&E$53,$D11:$DU11)/1000000 -> 2.4214333 | F61: =SUMIF($D$2:$DU$2,"="&F$53,$D11:$DU11)/1000000 -> 4.7546 | G61: =SUMIF($D$2:$DU$2,"="&G$53,$D11:$DU11)/1000000 -> 4.7546 | H61: =SUMIF($D$2:$DU$2,"="&H$53,$D11:$DU11)/1000000 -> 4.7546 | I61: =SUMIF($D$2:$DU$2,"="&I$53,$D11:$DU11)/1000000 -> 4.7546 | J61: =SUMIF($D$2:$DU$2,"="&J$53,$D11:$DU11)/1000000 -> 4.7546 | K61: =SUMIF($D$2:$DU$2,"="&K$53,$D11:$DU11)/1000000 -> 4.7546 | ... N61: =SUMIF($D$2:$DU$2,"="&N$53,$D11:$DU11)/1000000 -> 4.7546
A62: Суммарные издержки производства | C62: =SUM(D62:DU62) -> 4556.5992 | D62: =SUMIF($D$2:$DU$2,"="&D$53,$D12:$DU12)/1000000 -> 0 | E62: =SUMIF($D$2:$DU$2,"="&E$53,$D12:$DU12)/1000000 -> 177.21299 | F62: =SUMIF($D$2:$DU$2,"="&F$53,$D12:$DU12)/1000000 -> 400.28664 | G62: =SUMIF($D$2:$DU$2,"="&G$53,$D12:$DU12)/1000000 -> 419.46089 | H62: =SUMIF($D$2:$DU$2,"="&H$53,$D12:$DU12)/1000000 -> 439.58998 | I62: =SUMIF($D$2:$DU$2,"="&I$53,$D12:$DU12)/1000000 -> 460.72166 | J62: =SUMIF($D$2:$DU$2,"="&J$53,$D12:$DU12)/1000000 -> 482.90606 | K62: =SUMIF($D$2:$DU$2,"="&K$53,$D12:$DU12)/1000000 -> 506.19581 | ... N62: =SUMIF($D$2:$DU$2,"="&N$53,$D12:$DU12)/1000000 -> 583.26378
A63: Налоги | C63: =SUM(D63:DU63) -> 616.72746 | D63: =SUMIF($D$2:$DU$2,"="&D$53,$D13:$DU13)/1000000 -> 0 | E63: =SUMIF($D$2:$DU$2,"="&E$53,$D13:$DU13)/1000000 -> 9.5541447 | F63: =SUMIF($D$2:$DU$2,"="&F$53,$D13:$DU13)/1000000 -> 50.100204 | G63: =SUMIF($D$2:$DU$2,"="&G$53,$D13:$DU13)/1000000 -> 57.784063 | H63: =SUMIF($D$2:$DU$2,"="&H$53,$D13:$DU13)/1000000 -> 60.832454 | I63: =SUMIF($D$2:$DU$2,"="&I$53,$D13:$DU13)/1000000 -> 64.039213 | J63: =SUMIF($D$2:$DU$2,"="&J$53,$D13:$DU13)/1000000 -> 67.412259 | K63: =SUMIF($D$2:$DU$2,"="&K$53,$D13:$DU13)/1000000 -> 70.959907 | ... N63: =SUMIF($D$2:$DU$2,"="&N$53,$D13:$DU13)/1000000 -> 82.739963
A64: НДС | C64: =SUM(D64:DU64) -> 290.22479 | D64: =SUMIF($D$2:$DU$2,"="&D$53,$D14:$DU14)/1000000 -> 0 | E64: =SUMIF($D$2:$DU$2,"="&E$53,$D14:$DU14)/1000000 -> 0 | F64: =SUMIF($D$2:$DU$2,"="&F$53,$D14:$DU14)/1000000 -> 21.839059 | G64: =SUMIF($D$2:$DU$2,"="&G$53,$D14:$DU14)/1000000 -> 27.750618 | H64: =SUMIF($D$2:$DU$2,"="&H$53,$D14:$DU14)/1000000 -> 29.247633 | I64: =SUMIF($D$2:$DU$2,"="&I$53,$D14:$DU14)/1000000 -> 30.819499 | J64: =SUMIF($D$2:$DU$2,"="&J$53,$D14:$DU14)/1000000 -> 32.469958 | K64: =SUMIF($D$2:$DU$2,"="&K$53,$D14:$DU14)/1000000 -> 34.202941 | ... N64: =SUMIF($D$2:$DU$2,"="&N$53,$D14:$DU14)/1000000 -> 39.939328
A65: Налог на имущество | C65: =SUM(D65:DU65) -> 8.5503894 | D65: =SUMIF($D$2:$DU$2,"="&D$53,$D15:$DU15)/1000000 -> 0 | E65: =SUMIF($D$2:$DU$2,"="&E$53,$D15:$DU15)/1000000 -> 0.21940096 | F65: =SUMIF($D$2:$DU$2,"="&F$53,$D15:$DU15)/1000000 -> 1.4549854 | G65: =SUMIF($D$2:$DU$2,"="&G$53,$D15:$DU15)/1000000 -> 1.3123435 | H65: =SUMIF($D$2:$DU$2,"="&H$53,$D15:$DU15)/1000000 -> 1.1829597 | I65: =SUMIF($D$2:$DU$2,"="&I$53,$D15:$DU15)/1000000 -> 1.053576 | J65: =SUMIF($D$2:$DU$2,"="&J$53,$D15:$DU15)/1000000 -> 0.92419224 | K65: =SUMIF($D$2:$DU$2,"="&K$53,$D15:$DU15)/1000000 -> 0.7948085 | ... N65: =SUMIF($D$2:$DU$2,"="&N$53,$D15:$DU15)/1000000 -> 0.40665728
A66: Налог на прибыль | C66: =SUM(D66:DU66) -> 317.95227 | D66: =SUMIF($D$2:$DU$2,"="&D$53,$D16:$DU16)/1000000 -> 0 | E66: =SUMIF($D$2:$DU$2,"="&E$53,$D16:$DU16)/1000000 -> 9.3347438 | F66: =SUMIF($D$2:$DU$2,"="&F$53,$D16:$DU16)/1000000 -> 26.80616 | G66: =SUMIF($D$2:$DU$2,"="&G$53,$D16:$DU16)/1000000 -> 28.721102 | H66: =SUMIF($D$2:$DU$2,"="&H$53,$D16:$DU16)/1000000 -> 30.401861 | I66: =SUMIF($D$2:$DU$2,"="&I$53,$D16:$DU16)/1000000 -> 32.166138 | J66: =SUMIF($D$2:$DU$2,"="&J$53,$D16:$DU16)/1000000 -> 34.018108 | K66: =SUMIF($D$2:$DU$2,"="&K$53,$D16:$DU16)/1000000 -> 35.962158 | ... N66: =SUMIF($D$2:$DU$2,"="&N$53,$D16:$DU16)/1000000 -> 42.393978
A67: Итого кэш-фло по основной деятельности | C67: =SUM(D67:DU67) -> 1327.6676 | D67: =D55-D62-D63 -> 0 | E67: =E55-E62-E63 -> 41.585369 | F67: =F55-F62-F63 -> 118.47953 | G67: =G55-G62-G63 -> 120.06474 | H67: =H55-H62-H63 -> 126.75274 | I67: =I55-I62-I63 -> 133.77306 | J67: =J55-J62-J63 -> 141.14232 | K67: =K55-K62-K63 -> 148.87795 | ... N67: =N55-N62-N63 -> 174.47098
A69: 2. Инвестиционная деятельность
A70: Реализация основных средств | C70: =SUM(D70:DU70) -> 0 | D70: =SUMIF($D$2:$DU$2,"="&D$53,$D20:$DU20)/1000000 -> 0 | E70: =SUMIF($D$2:$DU$2,"="&E$53,$D20:$DU20)/1000000 -> 0 | F70: =SUMIF($D$2:$DU$2,"="&F$53,$D20:$DU20)/1000000 -> 0 | G70: =SUMIF($D$2:$DU$2,"="&G$53,$D20:$DU20)/1000000 -> 0 | H70: =SUMIF($D$2:$DU$2,"="&H$53,$D20:$DU20)/1000000 -> 0 | I70: =SUMIF($D$2:$DU$2,"="&I$53,$D20:$DU20)/1000000 -> 0 | J70: =SUMIF($D$2:$DU$2,"="&J$53,$D20:$DU20)/1000000 -> 0 | K70: =SUMIF($D$2:$DU$2,"="&K$53,$D20:$DU20)/1000000 -> 0 | ... N70: =SUMIF($D$2:$DU$2,"="&N$53,$D20:$DU20)/1000000 -> 0
A71: Затраты на приобретение активов | C71: =SUM(D71:DU71) -> 82.0884 | D71: =SUMIF($D$2:$DU$2,"="&D$53,$D21:$DU21)/1000000 -> 52.2629 | E71: =SUMIF($D$2:$DU$2,"="&E$53,$D21:$DU21)/1000000 -> 29.8255 | F71: =SUMIF($D$2:$DU$2,"="&F$53,$D21:$DU21)/1000000 -> 0 | G71: =SUMIF($D$2:$DU$2,"="&G$53,$D21:$DU21)/1000000 -> 0 | H71: =SUMIF($D$2:$DU$2,"="&H$53,$D21:$DU21)/1000000 -> 0 | I71: =SUMIF($D$2:$DU$2,"="&I$53,$D21:$DU21)/1000000 -> 0 | J71: =SUMIF($D$2:$DU$2,"="&J$53,$D21:$DU21)/1000000 -> 0 | K71: =SUMIF($D$2:$DU$2,"="&K$53,$D21:$DU21)/1000000 -> 0 | ... N71: =SUMIF($D$2:$DU$2,"="&N$53,$D21:$DU21)/1000000 -> 0
A72: Прочие расходы подготовительного периода | C72: =SUM(D72:DU72) -> 0.09978 | D72: =SUMIF($D$2:$DU$2,"="&D$53,$D22:$DU22)/1000000 -> 0.09978 | E72: =SUMIF($D$2:$DU$2,"="&E$53,$D22:$DU22)/1000000 -> 0 | F72: =SUMIF($D$2:$DU$2,"="&F$53,$D22:$DU22)/1000000 -> 0 | G72: =SUMIF($D$2:$DU$2,"="&G$53,$D22:$DU22)/1000000 -> 0 | H72: =SUMIF($D$2:$DU$2,"="&H$53,$D22:$DU22)/1000000 -> 0 | I72: =SUMIF($D$2:$DU$2,"="&I$53,$D22:$DU22)/1000000 -> 0 | J72: =SUMIF($D$2:$DU$2,"="&J$53,$D22:$DU22)/1000000 -> 0 | K72: =SUMIF($D$2:$DU$2,"="&K$53,$D22:$DU22)/1000000 -> 0 | ... N72: =SUMIF($D$2:$DU$2,"="&N$53,$D22:$DU22)/1000000 -> 0
A73: Итого кэш-фло по инвест. деятельности | C73: =SUM(D73:DU73) -> -82.18818 | D73: =D70-D71-D72 -> -52.36268 | E73: =E70-E71-E72 -> -29.8255 | F73: =F70-F71-F72 -> 0 | G73: =G70-G71-G72 -> 0 | H73: =H70-H71-H72 -> 0 | I73: =I70-I71-I72 -> 0 | J73: =J70-J71-J72 -> 0 | K73: =K70-K71-K72 -> 0 | ... N73: =N70-N71-N72 -> 0
A75: 3. Финансовая деятельность
A76: Собственный капитал | C76: =SUM(D76:DU76) -> 0 | D76: =SUMIF($D$2:$DU$2,"="&D$53,$D26:$DU26)/1000000 -> 0 | E76: =SUMIF($D$2:$DU$2,"="&E$53,$D26:$DU26)/1000000 -> 0 | F76: =SUMIF($D$2:$DU$2,"="&F$53,$D26:$DU26)/1000000 -> 0 | G76: =SUMIF($D$2:$DU$2,"="&G$53,$D26:$DU26)/1000000 -> 0 | H76: =SUMIF($D$2:$DU$2,"="&H$53,$D26:$DU26)/1000000 -> 0 | I76: =SUMIF($D$2:$DU$2,"="&I$53,$D26:$DU26)/1000000 -> 0 | J76: =SUMIF($D$2:$DU$2,"="&J$53,$D26:$DU26)/1000000 -> 0 | K76: =SUMIF($D$2:$DU$2,"="&K$53,$D26:$DU26)/1000000 -> 0 | ... N76: =SUMIF($D$2:$DU$2,"="&N$53,$D26:$DU26)/1000000 -> 0
C77: =SUM(D77:DU77) -> 0 | D77: =SUMIF($D$2:$DU$2,"="&D$53,$D27:$DU27)/1000000 -> 0 | E77: =SUMIF($D$2:$DU$2,"="&E$53,$D27:$DU27)/1000000 -> 0 | F77: =SUMIF($D$2:$DU$2,"="&F$53,$D27:$DU27)/1000000 -> 0 | G77: =SUMIF($D$2:$DU$2,"="&G$53,$D27:$DU27)/1000000 -> 0 | H77: =SUMIF($D$2:$DU$2,"="&H$53,$D27:$DU27)/1000000 -> 0 | I77: =SUMIF($D$2:$DU$2,"="&I$53,$D27:$DU27)/1000000 -> 0 | J77: =SUMIF($D$2:$DU$2,"="&J$53,$D27:$DU27)/1000000 -> 0 | K77: =SUMIF($D$2:$DU$2,"="&K$53,$D27:$DU27)/1000000 -> 0 | ... N77: =SUMIF($D$2:$DU$2,"="&N$53,$D27:$DU27)/1000000 -> 0
A78: Получение кредита | C78: =SUM(D78:DU78) -> 87.1 | D78: =SUMIF($D$2:$DU$2,"="&D$53,$D28:$DU28)/1000000 -> 53.2 | E78: =SUMIF($D$2:$DU$2,"="&E$53,$D28:$DU28)/1000000 -> 33.9 | F78: =SUMIF($D$2:$DU$2,"="&F$53,$D28:$DU28)/1000000 -> 0 | G78: =SUMIF($D$2:$DU$2,"="&G$53,$D28:$DU28)/1000000 -> 0 | H78: =SUMIF($D$2:$DU$2,"="&H$53,$D28:$DU28)/1000000 -> 0 | I78: =SUMIF($D$2:$DU$2,"="&I$53,$D28:$DU28)/1000000 -> 0 | J78: =SUMIF($D$2:$DU$2,"="&J$53,$D28:$DU28)/1000000 -> 0 | K78: =SUMIF($D$2:$DU$2,"="&K$53,$D28:$DU28)/1000000 -> 0 | ... N78: =SUMIF($D$2:$DU$2,"="&N$53,$D28:$DU28)/1000000 -> 0
A79: Платежи по кредиту | C79: =SUM(D79:DU79) -> 95.889167 | D79: =SUMIF($D$2:$DU$2,"="&D$53,$D29:$DU29)/1000000 -> 0 | E79: =SUMIF($D$2:$DU$2,"="&E$53,$D29:$DU29)/1000000 -> 32.119524 | F79: =SUMIF($D$2:$DU$2,"="&F$53,$D29:$DU29)/1000000 -> 63.769643 | G79: =SUMIF($D$2:$DU$2,"="&G$53,$D29:$DU29)/1000000 -> 0 | H79: =SUMIF($D$2:$DU$2,"="&H$53,$D29:$DU29)/1000000 -> 0 | I79: =SUMIF($D$2:$DU$2,"="&I$53,$D29:$DU29)/1000000 -> 0 | J79: =SUMIF($D$2:$DU$2,"="&J$53,$D29:$DU29)/1000000 -> 0 | K79: =SUMIF($D$2:$DU$2,"="&K$53,$D29:$DU29)/1000000 -> 0 | ... N79: =SUMIF($D$2:$DU$2,"="&N$53,$D29:$DU29)/1000000 -> 0
A80: Погашение долга | C80: =SUM(D80:DU80) -> 87.1 | D80: =SUMIF($D$2:$DU$2,"="&D$53,$D30:$DU30)/1000000 -> 0 | E80: =SUMIF($D$2:$DU$2,"="&E$53,$D30:$DU30)/1000000 -> 24.885714 | F80: =SUMIF($D$2:$DU$2,"="&F$53,$D30:$DU30)/1000000 -> 62.214286 | G80: =SUMIF($D$2:$DU$2,"="&G$53,$D30:$DU30)/1000000 -> 0 | H80: =SUMIF($D$2:$DU$2,"="&H$53,$D30:$DU30)/1000000 -> 0 | I80: =SUMIF($D$2:$DU$2,"="&I$53,$D30:$DU30)/1000000 -> 0 | J80: =SUMIF($D$2:$DU$2,"="&J$53,$D30:$DU30)/1000000 -> 0 | K80: =SUMIF($D$2:$DU$2,"="&K$53,$D30:$DU30)/1000000 -> 0 | ... N80: =SUMIF($D$2:$DU$2,"="&N$53,$D30:$DU30)/1000000 -> 0
A81: Проценты | C81: =SUM(D81:DU81) -> 8.7891667 | D81: =SUMIF($D$2:$DU$2,"="&D$53,$D31:$DU31)/1000000 -> 0 | E81: =SUMIF($D$2:$DU$2,"="&E$53,$D31:$DU31)/1000000 -> 7.2338095 | F81: =SUMIF($D$2:$DU$2,"="&F$53,$D31:$DU31)/1000000 -> 1.5553571 | G81: =SUMIF($D$2:$DU$2,"="&G$53,$D31:$DU31)/1000000 -> 0 | H81: =SUMIF($D$2:$DU$2,"="&H$53,$D31:$DU31)/1000000 -> 0 | I81: =SUMIF($D$2:$DU$2,"="&I$53,$D31:$DU31)/1000000 -> 0 | J81: =SUMIF($D$2:$DU$2,"="&J$53,$D31:$DU31)/1000000 -> 0 | K81: =SUMIF($D$2:$DU$2,"="&K$53,$D31:$DU31)/1000000 -> 0 | ... N81: =SUMIF($D$2:$DU$2,"="&N$53,$D31:$DU31)/1000000 -> 0
C82: =SUM(D82:DU82) -> 0
A83: Итого кэш-фло по финансовой деятельности | C83: =SUM(D83:DU83) -> -8.7891667 | D83: =D76+D78-D79 -> 53.2 | E83: =E76+E78-E79 -> 1.7804762 | F83: =F76+F78-F79 -> -63.769643 | G83: =G76+G78-G79 -> 0 | H83: =H76+H78-H79 -> 0 | I83: =I76+I78-I79 -> 0 | J83: =J76+J78-J79 -> 0 | K83: =K76+K78-K79 -> 0 | ... N83: =N76+N78-N79 -> 0
A85: Итого поток денежных средств | C85: =SUM(D85:DU85) -> 1236.6902 | D85: =D67+D73+D83 -> 0.83732 | E85: =E67+E73+E83 -> 13.540345 | F85: =F67+F73+F83 -> 54.709892 | G85: =G67+G73+G83 -> 120.06474 | H85: =H67+H73+H83 -> 126.75274 | I85: =I67+I73+I83 -> 133.77306 | J85: =J67+J73+J83 -> 141.14232 | K85: =K67+K73+K83 -> 148.87795 | ... N85: =N67+N73+N83 -> 174.47098
A86: Баланс денежных средств на конец периода | C86: =N86 -> 1236.6902 | D86: =D85 -> 0.83732 | E86: =D86+E85 -> 14.377665 | F86: =E86+F85 -> 69.087557 | G86: =F86+G85 -> 189.1523 | H86: =G86+H85 -> 315.90504 | I86: =H86+I85 -> 449.67811 | J86: =I86+J85 -> 590.82042 | K86: =J86+K85 -> 739.69838 | L86: =K86+L85 -> 896.69667 | ... N86: =M86+N85 -> 1236.6902

Sheet PL
A1: =title -> Вариант 1 | C1: http://exceltable.com/ | D1: 1 | E1: 2 | F1: 3 | G1: 4 | H1: 5 | I1: 6 | J1: 7 | K1: 8 | L1: 9 | M1: 10 | N1: 11 | O1: 12 | P1: 13 | Q1: 14 | R1: 15 | S1: 16 | T1: 17 | U1: 18 | V1: 19 | W1: 20 | X1: 21 | Y1: 22 | Z1: 23 | AA1: 24 | AB1: 25 | AC1: 26 | AD1: 27 | AE1: 28 | AF1: 29 | AG1: 30 | AH1: 31 | AI1: 32 | AJ1: 33 | AK1: 34 | AL1: 35 | AM1: 36 | AN1: 37 | AO1: 38 | AP1: 39 | AQ1: 40 | AR1: 41 | AS1: 42 | AT1: 43 | AU1: 44 | AV1: 45 | AW1: 46 | AX1: 47 | AY1: 48
A2: =cur -> USD | D2: =YEAR(D3) -> 2014 | E2: =YEAR(E3) -> 2014 | F2: =YEAR(F3) -> 2015 | G2: =YEAR(G3) -> 2015 | H2: =YEAR(H3) -> 2015 | I2: =YEAR(I3) -> 2015 | J2: =YEAR(J3) -> 2015 | K2: =YEAR(K3) -> 2015 | ... DU2: =YEAR(DU3) -> 2024
A3: Прибыли/убытки | C3: Сумма | D3: =данные!D147 -> 41944 | E3: =данные!E147 -> 41974 | F3: =данные!F147 -> 42005 | G3: =данные!G147 -> 42036 | H3: =данные!H147 -> 42064 | I3: =данные!I147 -> 42095 | J3: =данные!J147 -> 42125 | K3: =данные!K147 -> 42156 | ... DU3: =данные!DU147 -> 45627
A4: Выручка от реализации (без НДС) | C4: =SUM(D4:DU4) -> 5.5093171e+09 | D4: =данные!D56 -> 0 | E4: =данные!E56 -> 0 | F4: =данные!F56 -> 0 | G4: =данные!G56 -> 0 | H4: =данные!H56 -> 0 | I4: =данные!I56 -> 0 | J4: =данные!J56 -> 0 | K4: =данные!K56 -> 0 | ... DU4: =данные!DU56 -> 61808269
A5: Прямые расходы (без НДС) | C5: =SUM(D5:DU5) -> 3.7679449e+09 | D5: =данные!D63/(1+vat)+данные!D75 -> 0 | E5: =данные!E63/(1+vat)+данные!E75 -> 0 | F5: =данные!F63/(1+vat)+данные!F75 -> 0 | G5: =данные!G63/(1+vat)+данные!G75 -> 0 | H5: =данные!H63/(1+vat)+данные!H75 -> 0 | I5: =данные!I63/(1+vat)+данные!I75 -> 0 | J5: =данные!J63/(1+vat)+данные!J75 -> 0 | K5: =данные!K63/(1+vat)+данные!K75 -> 0 | ... DU5: =данные!DU63/(1+vat)+данные!DU75 -> 42090541
A6: Валовая прибыль | C6: =SUM(D6:DU6) -> 1.7413722e+09 | D6: =D4-D5 -> 0 | E6: =E4-E5 -> 0 | F6: =F4-F5 -> 0 | G6: =G4-G5 -> 0 | H6: =H4-H5 -> 0 | I6: =I4-I5 -> 0 | J6: =J4-J5 -> 0 | K6: =K4-K5 -> 0 | ... DU6: =DU4-DU5 -> 19717727
A7: ФОТ | C7: =SUM(D7:DU7) -> 40377913 | D7: =данные!D118 -> 0 | E7: =данные!E118 -> 0 | F7: =данные!F118 -> 0 | G7: =данные!G118 -> 0 | H7: =данные!H118 -> 0 | I7: =данные!I118 -> 0 | J7: =данные!J118 -> 0 | K7: =данные!K118 -> 0 | ... DU7: =данные!DU118 -> 387417.33
A8: Постоянные расходы | C8: =SUM(D8:DU8) -> 38315960 | D8: =данные!D98 -> 0 | E8: =данные!E98 -> 0 | F8: =данные!F98 -> 0 | G8: =данные!G98 -> 0 | H8: =данные!H98 -> 0 | I8: =данные!I98 -> 0 | J8: =данные!J98 -> 0 | K8: =данные!K98 -> 0 | ... DU8: =данные!DU98 -> 276412.43
A9: Налог на имущество | C9: =SUM(D9:DU9) -> 8550389.4 | D9: =данные!D150 -> 0 | E9: =данные!E150 -> 0 | F9: =данные!F150 -> 0 | G9: =данные!G150 -> 0 | H9: =данные!H150 -> 0 | I9: =данные!I150 -> 0 | J9: =данные!J150 -> 0 | K9: =данные!K150 -> 0 | ... DU9: =данные!DU150 -> 0
A10: Прибыль от реализации | C10: =SUM(D10:DU10) -> 1.6541279e+09 | D10: =D6-SUM(D7:D9) -> 0 | E10: =E6-SUM(E7:E9) -> 0 | F10: =F6-SUM(F7:F9) -> 0 | G10: =G6-SUM(G7:G9) -> 0 | H10: =H6-SUM(H7:H9) -> 0 | I10: =I6-SUM(I7:I9) -> 0 | J10: =J6-SUM(J7:J9) -> 0 | K10: =K6-SUM(K7:K9) -> 0 | ... DU10: =DU6-SUM(DU7:DU9) -> 19053897
A11: Прочие доходы | C11: =SUM(D11:DU11) -> 0 | D11: 0 | E11: 0 | F11: 0 | G11: 0 | H11: 0 | I11: 0 | J11: 0 | K11: 0 | L11: 0 | M11: 0 | N11: 0 | O11: 0 | P11: 0 | Q11: 0 | R11: 0 | S11: 0 | T11: 0 | U11: 0 | V11: 0 | W11: 0 | X11: 0 | Y11: 0 | Z11: 0 | AA11: 0 | AB11: 0 | AC11: 0 | AD11: 0 | AE11: 0 | AF11: 0 | AG11: 0 | AH11: 0 | AI11: 0 | AJ11: 0 | AK11: 0 | AL11: 0 | AM11: 0 | AN11: 0 | AO11: 0 | AP11: 0 | AQ11: 0 | AR11: 0 | AS11: 0 | AT11: 0 | AU11: 0 | AV11: 0 | AW11: 0 | AX11: 0 | AY11: 0 | AZ11: 0 | BA11: 0 | BB11: 0 | BC11: 0 | BD11: 0 | BE11: 0 | BF11: 0 | BG11: 0 | BH11: 0 | BI11: 0 | BJ11: 0 | BK11: 0 | BL11: 0 | BM11: 0 | BN11: 0 | BO11: 0 | BP11: 0 | BQ11: 0 | BR11: 0 | BS11: 0 | BT11: 0 | BU11: 0 | BV11: 0 | BW11: 0 | BX11: 0 | BY11: 0 | BZ11: 0 | CA11: 0 | CB11: 0 | CC11: 0 | CD11: 0 | CE11: 0 | CF11: 0 | CG11: 0 | CH11: 0 | CI11: 0 | CJ11: 0 | CK11: 0 | CL11: 0 | CM11: 0 | CN11: 0 | CO11: 0 | CP11: 0 | CQ11: 0 | CR11: 0 | CS11: 0 | CT11: 0 | CU11: 0 | CV11: 0 | CW11: 0 | CX11: 0 | CY11: 0 | CZ11: 0 | DA11: 0 | DB11: 0 | DC11: 0 | DD11: 0 | DE11: 0 | DF11: 0 | DG11: 0 | DH11: 0 | DI11: 0 | DJ11: 0 | DK11: 0 | DL11: 0 | DM11: 0 | DN11: 0 | DO11: 0 | DP11: 0 | DQ11: 0 | DR11: 0 | DS11: 0 | DT11: 0 | DU11: 0
A12: Прочие расходы | C12: =SUM(D12:DU12) -> 84559.322 | D12: =(данные!D6+данные!D8)/(1+vat) -> 84559.322 | E12: =(данные!E6+данные!E8)/(1+vat) -> 0 | F12: =(данные!F6+данные!F8)/(1+vat) -> 0 | G12: =(данные!G6+данные!G8)/(1+vat) -> 0 | H12: =(данные!H6+данные!H8)/(1+vat) -> 0 | I12: =(данные!I6+данные!I8)/(1+vat) -> 0 | J12: =(данные!J6+данные!J8)/(1+vat) -> 0 | K12: =(данные!K6+данные!K8)/(1+vat) -> 0 | ... DU12: =(данные!DU6+данные!DU8)/(1+vat) -> 0
A13: EBITDA | C13: =SUM(D13:DU13) -> 1.6540434e+09 | D13: =D10+D11-D12 -> -84559.322 | E13: =E10+E11-E12 -> 0 | F13: =F10+F11-F12 -> 0 | G13: =G10+G11-G12 -> 0 | H13: =H10+H11-H12 -> 0 | I13: =I10+I11-I12 -> 0 | J13: =J10+J11-J12 -> 0 | K13: =K10+K11-K12 -> 0 | ... DU13: =DU10+DU11-DU12 -> 19053897
A14: Амортизация | C14: =SUM(D14:DU14) -> 55492828 | D14: =данные!D28 -> 0 | E14: =данные!E28 -> 0 | F14: =данные!F28 -> 0 | G14: =данные!G28 -> 0 | H14: =данные!H28 -> 0 | I14: =данные!I28 -> 28166.667 | J14: =данные!J28 -> 28166.667 | K14: =данные!K28 -> 28166.667 | ... DU14: =данные!DU28 -> 490089.92
A15: EBIT | C15: =SUM(D15:DU15) -> 1.5985505e+09 | D15: =D13-D14 -> -84559.322 | E15: =E13-E14 -> 0 | F15: =F13-F14 -> 0 | G15: =G13-G14 -> 0 | H15: =H13-H14 -> 0 | I15: =I13-I14 -> -28166.667 | J15: =J13-J14 -> -28166.667 | K15: =K13-K14 -> -28166.667 | ... DU15: =DU13-DU14 -> 18563808
A16: Проценты уплаченные | C16: =SUM(D16:DU16) -> 8789166.7 | D16: =кредит!D10 -> 0 | E16: =кредит!E10 -> 0 | F16: =кредит!F10 -> 0 | G16: =кредит!G10 -> 0 | H16: =кредит!H10 -> 0 | I16: =кредит!I10 -> 0 | J16: =кредит!J10 -> 0 | K16: =кредит!K10 -> 0 | ... DU16: =кредит!DU10 -> 0
A17: Налогооблагаемая прибыль | C17: =SUM(D17:DU17) -> 1.5897614e+09 | D17: =D15-D16 -> -84559.322 | E17: =E15-E16 -> 0 | F17: =F15-F16 -> 0 | G17: =G15-G16 -> 0 | H17: =H15-H16 -> 0 | I17: =I15-I16 -> -28166.667 | J17: =J15-J16 -> -28166.667 | K17: =K15-K16 -> -28166.667 | ... DU17: =DU15-DU16 -> 18563808
A18: Налог на прибыль | B18: =profittax -> 0.2 | C18: =SUM(D18:DU18) -> 3.1795227e+08 | D18: =MAX(0,D17*$B$18) -> 0 | E18: =MAX(0,$B$18*SUM($D$17:E17)-SUM($D$18:D18)) -> 0 | F18: =MAX(0,$B$18*SUM($D$17:F17)-SUM($D$18:E18)) -> 0 | G18: =MAX(0,$B$18*SUM($D$17:G17)-SUM($D$18:F18)) -> 0 | H18: =MAX(0,$B$18*SUM($D$17:H17)-SUM($D$18:G18)) -> 0 | I18: =MAX(0,$B$18*SUM($D$17:I17)-SUM($D$18:H18)) -> 0 | J18: =MAX(0,$B$18*SUM($D$17:J17)-SUM($D$18:I18)) -> 0 | K18: =MAX(0,$B$18*SUM($D$17:K17)-SUM($D$18:J18)) -> 0 | L18: =MAX(0,$B$18*SUM($D$17:L17)-SUM($D$18:K18)) -> 0 | ... DU18: =MAX(0,$B$18*SUM($D$17:DU17)-SUM($D$18:DT18)) -> 3712761.5
A19: Чистая прибыль | C19: =SUM(D19:DU19) -> 1.2718091e+09 | D19: =D15-D16-D18 -> -84559.322 | E19: =E15-E16-E18 -> 0 | F19: =F15-F16-F18 -> 0 | G19: =G15-G16-G18 -> 0 | H19: =H15-H16-H18 -> 0 | I19: =I15-I16-I18 -> -28166.667 | J19: =J15-J16-J18 -> -28166.667 | K19: =K15-K16-K18 -> -28166.667 | ... DU19: =DU15-DU16-DU18 -> 14851046
A22: млн. USD
A23: Прибыли/убытки | C23: Сумма | D23: 2014 | E23: 2015 | F23: 2016 | G23: 2017 | H23: 2018 | I23: 2019 | J23: 2020 | K23: 2021 | L23: 2022 | M23: 2023 | N23: 2024
A24: Выручка от реализации (без НДС) | C24: =SUM(D24:DU24) -> 5509.3171 | D24: =SUMIF($D$2:$DU$2,"="&D$23,$D4:$DU4)/1000000 -> 0 | E24: =SUMIF($D$2:$DU$2,"="&E$23,$D4:$DU4)/1000000 -> 193.51907 | F24: =SUMIF($D$2:$DU$2,"="&F$23,$D4:$DU4)/1000000 -> 482.09015 | G24: =SUMIF($D$2:$DU$2,"="&G$23,$D4:$DU4)/1000000 -> 506.19466 | H24: =SUMIF($D$2:$DU$2,"="&H$23,$D4:$DU4)/1000000 -> 531.50439 | I24: =SUMIF($D$2:$DU$2,"="&I$23,$D4:$DU4)/1000000 -> 558.07961 | J24: =SUMIF($D$2:$DU$2,"="&J$23,$D4:$DU4)/1000000 -> 585.98359 | K24: =SUMIF($D$2:$DU$2,"="&K$23,$D4:$DU4)/1000000 -> 615.28277 | ... N24: =SUMIF($D$2:$DU$2,"="&N$23,$D4:$DU4)/1000000 -> 712.26671
A25: Прямые расходы (без НДС) | C25: =SUM(D25:DU25) -> 3767.9449 | D25: =SUMIF($D$2:$DU$2,"="&D$23,$D5:$DU5)/1000000 -> 0 | E25: =SUMIF($D$2:$DU$2,"="&E$23,$D5:$DU5)/1000000 -> 133.05085 | F25: =SUMIF($D$2:$DU$2,"="&F$23,$D5:$DU5)/1000000 -> 331.14407 | G25: =SUMIF($D$2:$DU$2,"="&G$23,$D5:$DU5)/1000000 -> 347.29449 | H25: =SUMIF($D$2:$DU$2,"="&H$23,$D5:$DU5)/1000000 -> 364.25244 | I25: =SUMIF($D$2:$DU$2,"="&I$23,$D5:$DU5)/1000000 -> 382.05828 | J25: =SUMIF($D$2:$DU$2,"="&J$23,$D5:$DU5)/1000000 -> 400.75441 | K25: =SUMIF($D$2:$DU$2,"="&K$23,$D5:$DU5)/1000000 -> 420.38535 | ... N25: =SUMIF($D$2:$DU$2,"="&N$23,$D5:$DU5)/1000000 -> 485.36622
A26: Валовая прибыль | C26: =SUM(D26:DU26) -> 1741.3722 | D26: =D24-D25 -> 0 | E26: =E24-E25 -> 60.46822 | F26: =F24-F25 -> 150.94608 | G26: =G24-G25 -> 158.90016 | H26: =H24-H25 -> 167.25195 | I26: =I24-I25 -> 176.02133 | J26: =J24-J25 -> 185.22918 | K26: =K24-K25 -> 194.89741 | ... N26: =N24-N25 -> 226.90049
A27: ФОТ | C27: =SUM(D27:DU27) -> 40.377913 | D27: =SUMIF($D$2:$DU$2,"="&D$23,$D7:$DU7)/1000000 -> 0 | E27: =SUMIF($D$2:$DU$2,"="&E$23,$D7:$DU7)/1000000 -> 1.6415533 | F27: =SUMIF($D$2:$DU$2,"="&F$23,$D7:$DU7)/1000000 -> 3.994536 | G27: =SUMIF($D$2:$DU$2,"="&G$23,$D7:$DU7)/1000000 -> 4.071912 | H27: =SUMIF($D$2:$DU$2,"="&H$23,$D7:$DU7)/1000000 -> 4.149288 | I27: =SUMIF($D$2:$DU$2,"="&I$23,$D7:$DU7)/1000000 -> 4.226664 | J27: =SUMIF($D$2:$DU$2,"="&J$23,$D7:$DU7)/1000000 -> 4.30404 | K27: =SUMIF($D$2:$DU$2,"="&K$23,$D7:$DU7)/1000000 -> 4.381416 | ... N27: =SUMIF($D$2:$DU$2,"="&N$23,$D7:$DU7)/1000000 -> 4.613544
A28: Постоянные расходы | C28: =SUM(D28:DU28) -> 38.31596 | D28: =SUMIF($D$2:$DU$2,"="&D$23,$D8:$DU8)/1000000 -> 0 | E28: =SUMIF($D$2:$DU$2,"="&E$23,$D8:$DU8)/1000000 -> 2.0520621 | F28: =SUMIF($D$2:$DU$2,"="&F$23,$D8:$DU8)/1000000 -> 4.029322 | G28: =SUMIF($D$2:$DU$2,"="&G$23,$D8:$DU8)/1000000 -> 4.029322 | H28: =SUMIF($D$2:$DU$2,"="&H$23,$D8:$DU8)/1000000 -> 4.029322 | I28: =SUMIF($D$2:$DU$2,"="&I$23,$D8:$DU8)/1000000 -> 4.029322 | J28: =SUMIF($D$2:$DU$2,"="&J$23,$D8:$DU8)/1000000 -> 4.029322 | K28: =SUMIF($D$2:$DU$2,"="&K$23,$D8:$DU8)/1000000 -> 4.029322 | ... N28: =SUMIF($D$2:$DU$2,"="&N$23,$D8:$DU8)/1000000 -> 4.029322
A29: Налог на имущество | C29: =SUM(D29:DU29) -> 8.5503894 | D29: =SUMIF($D$2:$DU$2,"="&D$23,$D9:$DU9)/1000000 -> 0 | E29: =SUMIF($D$2:$DU$2,"="&E$23,$D9:$DU9)/1000000 -> 0.21940096 | F29: =SUMIF($D$2:$DU$2,"="&F$23,$D9:$DU9)/1000000 -> 1.4549854 | G29: =SUMIF($D$2:$DU$2,"="&G$23,$D9:$DU9)/1000000 -> 1.3123435 | H29: =SUMIF($D$2:$DU$2,"="&H$23,$D9:$DU9)/1000000 -> 1.1829597 | I29: =SUMIF($D$2:$DU$2,"="&I$23,$D9:$DU9)/1000000 -> 1.053576 | J29: =SUMIF($D$2:$DU$2,"="&J$23,$D9:$DU9)/1000000 -> 0.92419224 | K29: =SUMIF($D$2:$DU$2,"="&K$23,$D9:$DU9)/1000000 -> 0.7948085 | ... N29: =SUMIF($D$2:$DU$2,"="&N$23,$D9:$DU9)/1000000 -> 0.40665728
A30: Прибыль от реализации | C30: =SUM(D30:DU30) -> 1654.1279 | D30: =D26-SUM(D27:D29) -> 0 | E30: =E26-SUM(E27:E29) -> 56.555204 | F30: =F26-SUM(F27:F29) -> 141.46724 | G30: =G26-SUM(G27:G29) -> 149.48659 | H30: =H26-SUM(H27:H29) -> 157.89038 | I30: =I26-SUM(I27:I29) -> 166.71177 | J30: =J26-SUM(J27:J29) -> 175.97162 | K30: =K26-SUM(K27:K29) -> 185.69187 | ... N30: =N26-SUM(N27:N29) -> 217.85097
A31: Прочие доходы | C31: =SUM(D31:DU31) -> 0 | D31: =SUMIF($D$2:$DU$2,"="&D$23,$D11:$DU11)/1000000 -> 0 | E31: =SUMIF($D$2:$DU$2,"="&E$23,$D11:$DU11)/1000000 -> 0 | F31: =SUMIF($D$2:$DU$2,"="&F$23,$D11:$DU11)/1000000 -> 0 | G31: =SUMIF($D$2:$DU$2,"="&G$23,$D11:$DU11)/1000000 -> 0 | H31: =SUMIF($D$2:$DU$2,"="&H$23,$D11:$DU11)/1000000 -> 0 | I31: =SUMIF($D$2:$DU$2,"="&I$23,$D11:$DU11)/1000000 -> 0 | J31: =SUMIF($D$2:$DU$2,"="&J$23,$D11:$DU11)/1000000 -> 0 | K31: =SUMIF($D$2:$DU$2,"="&K$23,$D11:$DU11)/1000000 -> 0 | ... N31: =SUMIF($D$2:$DU$2,"="&N$23,$D11:$DU11)/1000000 -> 0
A32: Прочие расходы | C32: =SUM(D32:DU32) -> 0.084559322 | D32: =SUMIF($D$2:$DU$2,"="&D$23,$D12:$DU12)/1000000 -> 0.084559322 | E32: =SUMIF($D$2:$DU$2,"="&E$23,$D12:$DU12)/1000000 -> 0 | F32: =SUMIF($D$2:$DU$2,"="&F$23,$D12:$DU12)/1000000 -> 0 | G32: =SUMIF($D$2:$DU$2,"="&G$23,$D12:$DU12)/1000000 -> 0 | H32: =SUMIF($D$2:$DU$2,"="&H$23,$D12:$DU12)/1000000 -> 0 | I32: =SUMIF($D$2:$DU$2,"="&I$23,$D12:$DU12)/1000000 -> 0 | J32: =SUMIF($D$2:$DU$2,"="&J$23,$D12:$DU12)/1000000 -> 0 | K32: =SUMIF($D$2:$DU$2,"="&K$23,$D12:$DU12)/1000000 -> 0 | ... N32: =SUMIF($D$2:$DU$2,"="&N$23,$D12:$DU12)/1000000 -> 0
A33: EBITDA | C33: =SUM(D33:DU33) -> 1654.0434 | D33: =D30+D31-D32 -> -0.084559322 | E33: =E30+E31-E32 -> 56.555204 | F33: =F30+F31-F32 -> 141.46724 | G33: =G30+G31-G32 -> 149.48659 | H33: =H30+H31-H32 -> 157.89038 | I33: =I30+I31-I32 -> 166.71177 | J33: =J30+J31-J32 -> 175.97162 | K33: =K30+K31-K32 -> 185.69187 | ... N33: =N30+N31-N32 -> 217.85097
A34: Амортизация | C34: =SUM(D34:DU34) -> 55.492828 | D34: =SUMIF($D$2:$DU$2,"="&D$23,$D14:$DU14)/1000000 -> 0 | E34: =SUMIF($D$2:$DU$2,"="&E$23,$D14:$DU14)/1000000 -> 2.5631163 | F34: =SUMIF($D$2:$DU$2,"="&F$23,$D14:$DU14)/1000000 -> 5.8810791 | G34: =SUMIF($D$2:$DU$2,"="&G$23,$D14:$DU14)/1000000 -> 5.8810791 | H34: =SUMIF($D$2:$DU$2,"="&H$23,$D14:$DU14)/1000000 -> 5.8810791 | I34: =SUMIF($D$2:$DU$2,"="&I$23,$D14:$DU14)/1000000 -> 5.8810791 | J34: =SUMIF($D$2:$DU$2,"="&J$23,$D14:$DU14)/1000000 -> 5.8810791 | K34: =SUMIF($D$2:$DU$2,"="&K$23,$D14:$DU14)/1000000 -> 5.8810791 | ... N34: =SUMIF($D$2:$DU$2,"="&N$23,$D14:$DU14)/1000000 -> 5.8810791
A35: EBIT | C35: =SUM(D35:DU35) -> 1598.5505 | D35: =D33-D34 -> -0.084559322 | E35: =E33-E34 -> 53.992088 | F35: =F33-F34 -> 135.58616 | G35: =G33-G34 -> 143.60551 | H35: =H33-H34 -> 152.0093 | I35: =I33-I34 -> 160.83069 | J35: =J33-J34 -> 170.09054 | K35: =K33-K34 -> 179.81079 | ... N35: =N33-N34 -> 211.96989
A36: Проценты уплаченные | C36: =SUM(D36:DU36) -> 8.7891667 | D36: =SUMIF($D$2:$DU$2,"="&D$23,$D16:$DU16)/1000000 -> 0 | E36: =SUMIF($D$2:$DU$2,"="&E$23,$D16:$DU16)/1000000 -> 7.2338095 | F36: =SUMIF($D$2:$DU$2,"="&F$23,$D16:$DU16)/1000000 -> 1.5553571 | G36: =SUMIF($D$2:$DU$2,"="&G$23,$D16:$DU16)/1000000 -> 0 | H36: =SUMIF($D$2:$DU$2,"="&H$23,$D16:$DU16)/1000000 -> 0 | I36: =SUMIF($D$2:$DU$2,"="&I$23,$D16:$DU16)/1000000 -> 0 | J36: =SUMIF($D$2:$DU$2,"="&J$23,$D16:$DU16)/1000000 -> 0 | K36: =SUMIF($D$2:$DU$2,"="&K$23,$D16:$DU16)/1000000 -> 0 | ... N36: =SUMIF($D$2:$DU$2,"="&N$23,$D16:$DU16)/1000000 -> 0
A37: Налогооблагаемая прибыль | C37: =SUM(D37:DU37) -> 1589.7614 | D37: =SUMIF($D$2:$DU$2,"="&D$23,$D17:$DU17)/1000000 -> -0.084559322 | E37: =SUMIF($D$2:$DU$2,"="&E$23,$D17:$DU17)/1000000 -> 46.758278 | F37: =SUMIF($D$2:$DU$2,"="&F$23,$D17:$DU17)/1000000 -> 134.0308 | G37: =SUMIF($D$2:$DU$2,"="&G$23,$D17:$DU17)/1000000 -> 143.60551 | H37: =SUMIF($D$2:$DU$2,"="&H$23,$D17:$DU17)/1000000 -> 152.0093 | I37: =SUMIF($D$2:$DU$2,"="&I$23,$D17:$DU17)/1000000 -> 160.83069 | J37: =SUMIF($D$2:$DU$2,"="&J$23,$D17:$DU17)/1000000 -> 170.09054 | K37: =SUMIF($D$2:$DU$2,"="&K$23,$D17:$DU17)/1000000 -> 179.81079 | ... N37: =SUMIF($D$2:$DU$2,"="&N$23,$D17:$DU17)/1000000 -> 211.96989
A38: Налог на прибыль | B38: =profittax -> 0.2 | C38: =SUM(D38:DU38) -> 317.95227 | D38: =SUMIF($D$2:$DU$2,"="&D$23,$D18:$DU18)/1000000 -> 0 | E38: =SUMIF($D$2:$DU$2,"="&E$23,$D18:$DU18)/1000000 -> 9.3347438 | F38: =SUMIF($D$2:$DU$2,"="&F$23,$D18:$DU18)/1000000 -> 26.80616 | G38: =SUMIF($D$2:$DU$2,"="&G$23,$D18:$DU18)/1000000 -> 28.721102 | H38: =SUMIF($D$2:$DU$2,"="&H$23,$D18:$DU18)/1000000 -> 30.401861 | I38: =SUMIF($D$2:$DU$2,"="&I$23,$D18:$DU18)/1000000 -> 32.166138 | J38: =SUMIF($D$2:$DU$2,"="&J$23,$D18:$DU18)/1000000 -> 34.018108 | K38: =SUMIF($D$2:$DU$2,"="&K$23,$D18:$DU18)/1000000 -> 35.962158 | ... N38: =SUMIF($D$2:$DU$2,"="&N$23,$D18:$DU18)/1000000 -> 42.393978
A39: Чистая прибыль | C39: =SUM(D39:DU39) -> 1271.8091 | D39: =D35-D36-D38 -> -0.084559322 | E39: =E35-E36-E38 -> 37.423534 | F39: =F35-F36-F38 -> 107.22464 | G39: =G35-G36-G38 -> 114.88441 | H39: =H35-H36-H38 -> 121.60744 | I39: =I35-I36-I38 -> 128.66455 | J39: =J35-J36-J38 -> 136.07243 | K39: =K35-K36-K38 -> 143.84863 | ... N39: =N35-N36-N38 -> 169.57591

Sheet BS
A1: =title -> Вариант 1 | B1: http://exceltable.com/ | D1: 1 | E1: 2 | F1: 3 | G1: 4 | H1: 5 | I1: 6 | J1: 7 | K1: 8 | L1: 9 | M1: 10 | N1: 11 | O1: 12 | P1: 13 | Q1: 14 | R1: 15 | S1: 16 | T1: 17 | U1: 18 | V1: 19 | W1: 20 | X1: 21 | Y1: 22 | Z1: 23 | AA1: 24 | AB1: 25 | AC1: 26 | AD1: 27 | AE1: 28 | AF1: 29 | AG1: 30 | AH1: 31 | AI1: 32 | AJ1: 33 | AK1: 34 | AL1: 35 | AM1: 36 | AN1: 37 | AO1: 38 | AP1: 39 | AQ1: 40 | AR1: 41 | AS1: 42 | AT1: 43 | AU1: 44 | AV1: 45 | AW1: 46 | AX1: 47 | AY1: 48 | AZ1: 49 | BA1: 50 | BB1: 51 | BC1: 52 | BD1: 53 | BE1: 54 | BF1: 55 | BG1: 56 | BH1: 57 | BI1: 58 | BJ1: 59 | BK1: 60 | BL1: 61 | BM1: 62 | BN1: 63 | BO1: 64 | BP1: 65 | BQ1: 66 | BR1: 67 | BS1: 68 | BT1: 69 | BU1: 70 | BV1: 71 | BW1: 72 | BX1: 73 | BY1: 74 | BZ1: 75 | CA1: 76 | CB1: 77 | CC1: 78 | CD1: 79 | CE1: 80 | CF1: 81 | CG1: 82 | CH1: 83 | CI1: 84 | CJ1: 85 | CK1: 86 | CL1: 87 | CM1: 88 | CN1: 89 | CO1: 90 | CP1: 91 | CQ1: 92 | CR1: 93 | CS1: 94 | CT1: 95 | CU1: 96 | CV1: 97 | CW1: 98 | CX1: 99 | CY1: 100 | CZ1: 101 | DA1: 102 | DB1: 103 | DC1: 104 | DD1: 105 | DE1: 106 | DF1: 107 | DG1: 108 | DH1: 109 | DI1: 110 | DJ1: 111 | DK1: 112 | DL1: 113 | DM1: 114 | DN1: 115 | DO1: 116 | DP1: 117 | DQ1: 118 | DR1: 119 | DS1: 120 | DT1: 121 | DU1: 122
A2: =cur -> USD | D2: =YEAR(D3) -> 2014 | E2: =YEAR(E3) -> 2014 | F2: =YEAR(F3) -> 2015 | G2: =YEAR(G3) -> 2015 | H2: =YEAR(H3) -> 2015 | I2: =YEAR(I3) -> 2015 | J2: =YEAR(J3) -> 2015 | K2: =YEAR(K3) -> 2015 | ... DU2: =YEAR(DU3) -> 2024
A3: Баланс | D3: =данные!D3 -> 41944 | E3: =данные!E3 -> 41974 | F3: =данные!F3 -> 42005 | G3: =данные!G3 -> 42036 | H3: =данные!H3 -> 42064 | I3: =данные!I3 -> 42095 | J3: =данные!J3 -> 42125 | K3: =данные!K3 -> 42156 | ... DU3: =данные!DU3 -> 45627
A4: Активы
A5: Внеоборотные активы | D5: =D6+D7 -> 43388051 | E5: =E6+E7 -> 44290593 | F5: =F6+F7 -> 45193136 | G5: =G6+G7 -> 46095678 | H5: =H6+H7 -> 47511356 | I5: =I6+I7 -> 48750138 | J5: =J6+J7 -> 49988921 | K5: =K6+K7 -> 51227703 | ... DU5: =DU6+DU7 -> 14073613
A6: Основные средства | D6: =данные!D36 -> 0 | E6: =данные!E36 -> 0 | F6: =данные!F36 -> 0 | G6: =данные!G36 -> 0 | H6: =данные!H36 -> 0 | I6: =данные!I36 -> 4470477.4 | J6: =данные!J36 -> 4442310.7 | K6: =данные!K36 -> 4414144.1 | ... DU6: =данные!DU36 -> 14073613
A7: Незавершенное строительство | D7: =данные!D27 -> 43388051 | E7: =данные!E27 -> 44290593 | F7: =данные!F27 -> 45193136 | G7: =данные!G27 -> 46095678 | H7: =данные!H27 -> 47511356 | I7: =данные!I27 -> 44279661 | J7: =данные!J27 -> 45546610 | K7: =данные!K27 -> 46813559 | ... DU7: =данные!DU27 -> 0
A8: Оборотные активы | D8: =SUM(D9:D13) -> 8827389.8 | E8: =SUM(E9:E13) -> 8824847.5 | F8: =SUM(F9:F13) -> 9022305.1 | G8: =SUM(G9:G13) -> 9019762.7 | H8: =SUM(H9:H13) -> 9804084.7 | I8: =SUM(I9:I13) -> 10137136 | J8: =SUM(J9:J13) -> 9970186.4 | K8: =SUM(K9:K13) -> 10203237 | ... DU8: =SUM(DU9:DU13) -> 1.2577355e+09
A9: Запасы и незавершенное пр-во | D9: 0 | E9: 0 | F9: 0 | G9: 0 | H9: 0 | I9: 0 | J9: 0 | K9: 0 | L9: 0 | M9: 0 | N9: 0 | O9: 0 | P9: 0 | Q9: 0 | R9: 0 | S9: 0 | T9: 0 | U9: 0 | V9: 0 | W9: 0 | X9: 0 | Y9: 0 | Z9: 0 | AA9: 0 | AB9: 0 | AC9: 0 | AD9: 0 | AE9: 0 | AF9: 0 | AG9: 0 | AH9: 0 | AI9: 0 | AJ9: 0 | AK9: 0 | AL9: 0 | AM9: 0 | AN9: 0 | AO9: 0 | AP9: 0 | AQ9: 0 | AR9: 0 | AS9: 0 | AT9: 0 | AU9: 0 | AV9: 0 | AW9: 0 | AX9: 0 | AY9: 0 | AZ9: 0 | BA9: 0 | BB9: 0 | BC9: 0 | BD9: 0 | BE9: 0 | BF9: 0 | BG9: 0 | BH9: 0 | BI9: 0 | BJ9: 0 | BK9: 0 | BL9: 0 | BM9: 0 | BN9: 0 | BO9: 0 | BP9: 0 | BQ9: 0 | BR9: 0 | BS9: 0 | BT9: 0 | BU9: 0 | BV9: 0 | BW9: 0 | BX9: 0 | BY9: 0 | BZ9: 0 | CA9: 0 | CB9: 0 | CC9: 0 | CD9: 0 | CE9: 0 | CF9: 0 | CG9: 0 | CH9: 0 | CI9: 0 | CJ9: 0 | CK9: 0 | CL9: 0 | CM9: 0 | CN9: 0 | CO9: 0 | CP9: 0 | CQ9: 0 | CR9: 0 | CS9: 0 | CT9: 0 | CU9: 0 | CV9: 0 | CW9: 0 | CX9: 0 | CY9: 0 | CZ9: 0 | DA9: 0 | DB9: 0 | DC9: 0 | DD9: 0 | DE9: 0 | DF9: 0 | DG9: 0 | DH9: 0 | DI9: 0 | DJ9: 0 | DK9: 0 | DL9: 0 | DM9: 0 | DN9: 0 | DO9: 0 | DP9: 0 | DQ9: 0 | DR9: 0 | DS9: 0 | DT9: 0 | DU9: 0
A10: Авансы выданные | D10: =данные!D69-данные!D63 -> 0 | E10: =(SUM(данные!$D$69:E69)-SUM(данные!$D$63:E63)/(1+vat))+(SUM(данные!$D$79:E79)-SUM(данные!$D$75:E75)) -> 0 | F10: =(SUM(данные!$D$69:F69)-SUM(данные!$D$63:F63)/(1+vat))+(SUM(данные!$D$79:F79)-SUM(данные!$D$75:F75)) -> 0 | G10: =(SUM(данные!$D$69:G69)-SUM(данные!$D$63:G63)/(1+vat))+(SUM(данные!$D$79:G79)-SUM(данные!$D$75:G75)) -> 0 | H10: =(SUM(данные!$D$69:H69)-SUM(данные!$D$63:H63)/(1+vat))+(SUM(данные!$D$79:H79)-SUM(данные!$D$75:H75)) -> 0 | I10: =(SUM(данные!$D$69:I69)-SUM(данные!$D$63:I63)/(1+vat))+(SUM(данные!$D$79:I79)-SUM(данные!$D$75:I75)) -> 0 | J10: =(SUM(данные!$D$69:J69)-SUM(данные!$D$63:J63)/(1+vat))+(SUM(данные!$D$79:J79)-SUM(данные!$D$75:J75)) -> 0 | K10: =(SUM(данные!$D$69:K69)-SUM(данные!$D$63:K63)/(1+vat))+(SUM(данные!$D$79:K79)-SUM(данные!$D$75:K75)) -> 0 | L10: =(SUM(данные!$D$69:L69)-SUM(данные!$D$63:L63)/(1+vat))+(SUM(данные!$D$79:L79)-SUM(данные!$D$75:L75)) -> 13050847 | ... DU10: =(SUM(данные!$D$69:DU69)-SUM(данные!$D$63:DU63)/(1+vat))+(SUM(данные!$D$79:DU79)-SUM(данные!$D$75:DU75)) -> 21045271
A11: Расчеты с покупателями | D11: =данные!D155 -> 0 | E11: =данные!E155 -> 0 | F11: =данные!F155 -> 0 | G11: =данные!G155 -> 0 | H11: =данные!H155 -> 0 | I11: =данные!I155 -> 0 | J11: =данные!J155 -> 0 | K11: =данные!K155 -> 0 | ... DU11: =данные!DU155 -> 0
A12: НДС по приобретенным ценностям | D12: =данные!D145 -> 7825069.8 | E12: =данные!E145 -> 7987527.5 | F12: =данные!F145 -> 8149985.1 | G12: =данные!G145 -> 8312442.7 | H12: =данные!H145 -> 8567264.7 | I12: =данные!I145 -> 8795315.6 | J12: =данные!J145 -> 9023366.4 | K12: =данные!K145 -> 9251417.3 | ... DU12: =данные!DU145 -> 0
A13: Денежные средства | D13: ='Cash Flow'!D36 -> 1002320 | E13: ='Cash Flow'!E36 -> 837320 | F13: ='Cash Flow'!F36 -> 872320 | G13: ='Cash Flow'!G36 -> 707320 | H13: ='Cash Flow'!H36 -> 1236820 | I13: ='Cash Flow'!I36 -> 1341820 | J13: ='Cash Flow'!J36 -> 946820 | K13: ='Cash Flow'!K36 -> 951820 | ... DU13: ='Cash Flow'!DU36 -> 1.2366902e+09
A14: ИТОГО АКТИВЫ | D14: =D5+D8 -> 52215441 | E14: =E5+E8 -> 53115441 | F14: =F5+F8 -> 54215441 | G14: =G5+G8 -> 55115441 | H14: =H5+H8 -> 57315441 | I14: =I5+I8 -> 58887274 | J14: =J5+J8 -> 59959107 | K14: =K5+K8 -> 61430941 | ... DU14: =DU5+DU8 -> 1.2718091e+09
A15: Пассивы
A16: Собственный капитал | D16: ='Cash Flow'!D26 -> 0 | E16: =D16+'Cash Flow'!E26 -> 0 | F16: =E16+'Cash Flow'!F26 -> 0 | G16: =F16+'Cash Flow'!G26 -> 0 | H16: =G16+'Cash Flow'!H26 -> 0 | I16: =H16+'Cash Flow'!I26 -> 0 | J16: =I16+'Cash Flow'!J26 -> 0 | K16: =J16+'Cash Flow'!K26 -> 0 | L16: =K16+'Cash Flow'!L26 -> 0 | ... DU16: =DT16+'Cash Flow'!DU26 -> 0
A17: Нераспределенная прибыль (убыток) | D17: =PL!D19 -> -84559.322 | E17: =D17+PL!E19 -> -84559.322 | F17: =E17+PL!F19 -> -84559.322 | G17: =F17+PL!G19 -> -84559.322 | H17: =G17+PL!H19 -> -84559.322 | I17: =H17+PL!I19 -> -112725.99 | J17: =I17+PL!J19 -> -140892.66 | K17: =J17+PL!K19 -> -169059.32 | L17: =K17+PL!L19 -> -215550.52 | ... DU17: =DT17+PL!DU19 -> 1.2718091e+09
A18: Всего капитал | D18: =D16+D17 -> -84559.322 | E18: =E16+E17 -> -84559.322 | F18: =F16+F17 -> -84559.322 | G18: =G16+G17 -> -84559.322 | H18: =H16+H17 -> -84559.322 | I18: =I16+I17 -> -112725.99 | J18: =J16+J17 -> -140892.66 | K18: =K16+K17 -> -169059.32 | ... DU18: =DU16+DU17 -> 1.2718091e+09
A19: Кредиты | D19: =кредит!D11 -> 52300000 | E19: =кредит!E11 -> 53200000 | F19: =кредит!F11 -> 54300000 | G19: =кредит!G11 -> 55200000 | H19: =кредит!H11 -> 57400000 | I19: =кредит!I11 -> 59000000 | J19: =кредит!J11 -> 60100000 | K19: =кредит!K11 -> 61600000 | ... DU19: =кредит!DU11 -> 0
A20: Кредиторская задолженность | D20: =данные!D162+данные!D37 -> 0 | E20: =данные!E162+данные!E37 -> 0 | F20: =данные!F162+данные!F37 -> 0 | G20: =данные!G162+данные!G37 -> 0 | H20: =данные!H162+данные!H37 -> 0 | I20: =данные!I162+данные!I37 -> 0 | J20: =данные!J162+данные!J37 -> 0 | K20: =данные!K162+данные!K37 -> 0 | ... DU20: =данные!DU162+данные!DU37 -> 1.4901161e-08
A21: Всего обязательства | D21: =D19+D20 -> 52300000 | E21: =E19+E20 -> 53200000 | F21: =F19+F20 -> 54300000 | G21: =G19+G20 -> 55200000 | H21: =H19+H20 -> 57400000 | I21: =I19+I20 -> 59000000 | J21: =J19+J20 -> 60100000 | K21: =K19+K20 -> 61600000 | ... DU21: =DU19+DU20 -> 1.4901161e-08
A22: ИТОГО ПАСИВЫ | D22: =D18+D21 -> 52215441 | E22: =E18+E21 -> 53115441 | F22: =F18+F21 -> 54215441 | G22: =G18+G21 -> 55115441 | H22: =H18+H21 -> 57315441 | I22: =I18+I21 -> 58887274 | J22: =J18+J21 -> 59959107 | K22: =K18+K21 -> 61430941 | ... DU22: =DU18+DU21 -> 1.2718091e+09
A24: БАЛАНС | C24: =SUM(D24:DU24) -> 2.4527311e-05 | D24: =D14-D22 -> 0 | E24: =E14-E22 -> 0 | F24: =F14-F22 -> 0 | G24: =G14-G22 -> 0 | H24: =H14-H22 -> 0 | I24: =I14-I22 -> 0 | J24: =J14-J22 -> 0 | K24: =K14-K22 -> 0 | ... DU24: =DU14-DU22 -> 2.8610229e-06

Sheet NPV
A1: =title -> Вариант 1 | B1: http://exceltable.com/ | D1: 1 | E1: 2 | F1: 3 | G1: 4 | H1: 5 | I1: 6 | J1: 7 | K1: 8 | L1: 9 | M1: 10 | N1: 11 | O1: 12 | P1: 13 | Q1: 14 | R1: 15 | S1: 16 | T1: 17 | U1: 18 | V1: 19 | W1: 20 | X1: 21 | Y1: 22 | Z1: 23 | AA1: 24 | AB1: 25 | AC1: 26 | AD1: 27 | AE1: 28 | AF1: 29 | AG1: 30 | AH1: 31 | AI1: 32 | AJ1: 33 | AK1: 34 | AL1: 35 | AM1: 36 | AN1: 37 | AO1: 38 | AP1: 39 | AQ1: 40 | AR1: 41 | AS1: 42 | AT1: 43 | AU1: 44 | AV1: 45 | AW1: 46 | AX1: 47 | AY1: 48 | AZ1: 49 | BA1: 50 | BB1: 51 | BC1: 52 | BD1: 53 | BE1: 54 | BF1: 55 | BG1: 56 | BH1: 57 | BI1: 58 | BJ1: 59 | BK1: 60 | BL1: 61 | BM1: 62 | BN1: 63 | BO1: 64 | BP1: 65 | BQ1: 66 | BR1: 67 | BS1: 68 | BT1: 69 | BU1: 70 | BV1: 71 | BW1: 72 | BX1: 73 | BY1: 74 | BZ1: 75 | CA1: 76 | CB1: 77 | CC1: 78 | CD1: 79 | CE1: 80 | CF1: 81 | CG1: 82 | CH1: 83 | CI1: 84 | CJ1: 85 | CK1: 86 | CL1: 87 | CM1: 88 | CN1: 89 | CO1: 90 | CP1: 91 | CQ1: 92 | CR1: 93 | CS1: 94 | CT1: 95 | CU1: 96 | CV1: 97 | CW1: 98 | CX1: 99 | CY1: 100 | CZ1: 101 | DA1: 102 | DB1: 103 | DC1: 104 | DD1: 105 | DE1: 106 | DF1: 107 | DG1: 108 | DH1: 109 | DI1: 110 | DJ1: 111 | DK1: 112 | DL1: 113 | DM1: 114 | DN1: 115 | DO1: 116 | DP1: 117 | DQ1: 118 | DR1: 119 | DS1: 120 | DT1: 121 | DU1: 122
A2: =cur -> USD | D2: =YEAR(D3) -> 2014 | E2: =YEAR(E3) -> 2014 | F2: =YEAR(F3) -> 2015 | G2: =YEAR(G3) -> 2015 | H2: =YEAR(H3) -> 2015 | I2: =YEAR(I3) -> 2015 | J2: =YEAR(J3) -> 2015 | K2: =YEAR(K3) -> 2015 | ... DU2: =YEAR(DU3) -> 2024
A3: Коммерческая эффективность | C3: Сумма | D3: =данные!D3 -> 41944 | E3: =данные!E3 -> 41974 | F3: =данные!F3 -> 42005 | G3: =данные!G3 -> 42036 | H3: =данные!H3 -> 42064 | I3: =данные!I3 -> 42095 | J3: =данные!J3 -> 42125 | K3: =данные!K3 -> 42156 | ... DU3: =данные!DU3 -> 45627
A4: Свободный поток д/с | C4: =SUM(D4:DU4) -> 1.2366902e+09 | D4: ='Cash Flow'!D46 -> -51297680 | E4: ='Cash Flow'!E46 -> -1065000 | F4: ='Cash Flow'!F46 -> -1065000 | G4: ='Cash Flow'!G46 -> -1065000 | H4: ='Cash Flow'!H46 -> -1670500 | I4: ='Cash Flow'!I46 -> -1495000 | J4: ='Cash Flow'!J46 -> -1495000 | K4: ='Cash Flow'!K46 -> -1495000 | ... DU4: ='Cash Flow'!DU46 -> 15341136
A5: Текущие расходы | C5: =SUM(D5:BK5) -> 0
A6: Налоги | C6: =SUM(D6:BK6) -> 0
A7: Инвестиции | C7: =SUM(D7:BK7) -> 0
A8: Финансовые издержки | C8: =SUM(I8:BK8) -> 0
A9: Терминальная стоимость | C9: =SUM(I9:DU9) -> 6.9788391e+08 | DU9: =SUM(DJ4:DU4)/discont -> 6.9788391e+08
A10: Поток денежных средств | C10: =SUM(D10:DU10) -> 1.9345524e+09 | D10: =SUM(D4:D9)-15000-6700 -> -51319380 | E10: =SUM(E4:E9) -> -1065000 | F10: =SUM(F4:F9) -> -1065000 | G10: =SUM(G4:G9) -> -1065000 | H10: =SUM(H4:H9) -> -1670500 | I10: =SUM(I4:I9) -> -1495000 | J10: =SUM(J4:J9) -> -1495000 | K10: =SUM(K4:K9) -> -1495000 | L10: =SUM(L4:L9) -> -16913325 | ... DU10: =SUM(DU4:DU9) -> 7.1322504e+08
A11: Дисконтированный поток денежных средств (NPV) | B11: =POWER(1+discont,1/12)-1 -> 0.018769265 | C11: =SUM(D11:DU11) -> 4.1540684e+08 | D11: =D10/POWER(1+$B$11,D1) -> -50373899 | E11: =E10/POWER(1+$B$11,E1) -> -1026119.5 | F11: =F10/POWER(1+$B$11,F1) -> -1007214.8 | G11: =G10/POWER(1+$B$11,G1) -> -988658.42 | H11: =H10/POWER(1+$B$11,H1) -> -1522184.5 | I11: =I10/POWER(1+$B$11,I1) -> -1337168.7 | J11: =J10/POWER(1+$B$11,J1) -> -1312533.4 | K11: =K10/POWER(1+$B$11,K1) -> -1288351.9 | ... DU11: =DU10/POWER(1+$B$11,DU1) -> 73786139
A12: Внутренняя ставка доходности (IRR) | C12: =POWER(IRR(D10:DU10,0.00001)+1,12)-1 -> 1.3290017
A13: Индекс доходности (PI) | C13: =C23/(-C22) -> 3.5754771
A14: Срок окупаемости (PBP), мес | C14: =MAX(D18:BK18) -> 18
A15: Дисконтированный срок окупаемости (DPBP), мес | C15: =MAX(D20:BK20) -> 21
D17: =D10 -> -51319380 | E17: =E10+D17 -> -52384380 | F17: =F10+E17 -> -53449380 | G17: =G10+F17 -> -54514380 | H17: =H10+G17 -> -56184880 | I17: =I10+H17 -> -57679880 | J17: =J10+I17 -> -59174880 | K17: =K10+J17 -> -60669880 | L17: =L10+K17 -> -77583205 | ... DU17: =DU10+DT17 -> 1.9345524e+09
D18: =IF(D17<0,D1,0) -> 1 | E18: =IF(E17<0,E1,0) -> 2 | F18: =IF(F17<0,F1,0) -> 3 | G18: =IF(G17<0,G1,0) -> 4 | H18: =IF(H17<0,H1,0) -> 5 | I18: =IF(I17<0,I1,0) -> 6 | J18: =IF(J17<0,J1,0) -> 7 | K18: =IF(K17<0,K1,0) -> 8 | ... DU18: =IF(DU17<0,DU1,0) -> 0
D19: =D11 -> -50373899 | E19: =E11+D19 -> -51400018 | F19: =F11+E19 -> -52407233 | G19: =G11+F19 -> -53395892 | H19: =H11+G19 -> -54918076 | I19: =I11+H19 -> -56255245 | J19: =J11+I19 -> -57567778 | K19: =K11+J19 -> -58856130 | L19: =L11+K19 -> -73163061 | ... DU19: =DU11+DT19 -> 4.1540684e+08
D20: =IF(D19<0,D1,0) -> 1 | E20: =IF(E19<0,E1,0) -> 2 | F20: =IF(F19<0,F1,0) -> 3 | G20: =IF(G19<0,G1,0) -> 4 | H20: =IF(H19<0,H1,0) -> 5 | I20: =IF(I19<0,I1,0) -> 6 | J20: =IF(J19<0,J1,0) -> 7 | K20: =IF(K19<0,K1,0) -> 8 | ... DU20: =IF(DU19<0,DU1,0) -> 0
C22: =SUM(D22:BK22) -> -76743063 | D22: ='Cash Flow'!D23/POWER(1+$B$11,D$1) -> -50352599 | E22: ='Cash Flow'!E23/POWER(1+$B$11,E$1) -> -1026119.5 | F22: ='Cash Flow'!F23/POWER(1+$B$11,F$1) -> -1007214.8 | G22: ='Cash Flow'!G23/POWER(1+$B$11,G$1) -> -988658.42 | H22: ='Cash Flow'!H23/POWER(1+$B$11,H$1) -> -1522184.5 | I22: ='Cash Flow'!I23/POWER(1+$B$11,I$1) -> -1337168.7 | J22: ='Cash Flow'!J23/POWER(1+$B$11,J$1) -> -1312533.4 | K22: ='Cash Flow'!K23/POWER(1+$B$11,K$1) -> -1288351.9 | ... DU22: ='Cash Flow'!DU23/POWER(1+$B$11,DU$1) -> 0
C23: =SUM(D23:BK23) -> 2.7439307e+08 | D23: =('Cash Flow'!D17)/POWER(1+$B$11,D$1) -> 0 | E23: =('Cash Flow'!E17)/POWER(1+$B$11,E$1) -> 0 | F23: =('Cash Flow'!F17)/POWER(1+$B$11,F$1) -> 0 | G23: =('Cash Flow'!G17)/POWER(1+$B$11,G$1) -> 0 | H23: =('Cash Flow'!H17)/POWER(1+$B$11,H$1) -> 0 | I23: =('Cash Flow'!I17)/POWER(1+$B$11,I$1) -> 0 | J23: =('Cash Flow'!J17)/POWER(1+$B$11,J$1) -> 0 | K23: =('Cash Flow'!K17)/POWER(1+$B$11,K$1) -> 0 | ... DU23: =('Cash Flow'!DU17)/POWER(1+$B$11,DU$1) -> 1587105.2

Sheet чувствительность
A1: Анализ чувствительности | E1: http://exceltable.com/
A2: =title -> Вариант 1
A4: Параметры | D4: 1. Двухфакторный анализ
A5: Кап. затраты | B5: 1 | G5: Объем продаж | T5: =G5 -> Объем продаж
A6: Объем переработки | B6: 1 | D6: IRR минимум | F6: 0.25 | Q6: NPV минимум | S6: 0
A7: Цена | B7: 1 | D7: IRR текущая | F7: =B12 -> 1.3290017 | G7: 0.8 | H7: 0.85 | I7: 0.9 | J7: 0.95 | K7: 1 | L7: 1.05 | M7: 1.1 | N7: 1.15 | O7: 1.2 | Q7: NPV текущая | S7: =B11 -> 415.40684 | T7: 0.8 | U7: 0.85 | V7: 0.9 | W7: 0.95 | X7: 1 | Y7: 1.05 | Z7: 1.1 | AA7: 1.15 | AB7: 1.2
A8: Стоимость сырья | B8: 1 | D8: Цена | F8: 0.8 | G8: 0.37396479 | H8: 0.39675796 | I8: 0.41903871 | J8: 0.44088031 | K8: 0.46234317 | L8: 0.48344339 | M8: 0.50424008 | N8: 0.52473926 | O8: 0.54496562 | Q8: =D8 -> Цена | S8: 0.8 | T8: 44.970478 | U8: 53.959345 | V8: 62.933732 | W8: 71.899139 | X8: 80.859546 | Y8: 89.810206 | Z8: 98.758236 | AA8: 107.69908 | AB8: 116.6341
F9: 0.85 | G9: 0.54970701 | H9: 0.58144436 | I9: 0.61277401 | J9: 0.64377312 | K9: 0.67446322 | L9: 0.70488619 | M9: 0.73503016 | N9: 0.76494349 | O9: 0.79462529 | S9: 0.85 | T9: 112.33494 | U9: 125.46283 | V9: 138.57855 | W9: 151.68895 | X9: 164.79315 | Y9: 177.89501 | Z9: 190.98925 | AA9: 204.08088 | AB9: 217.17021
A10: Критерии | F10: 0.9 | G10: 0.72349658 | H10: 0.765307 | I10: 0.80678026 | J10: 0.84797317 | K10: 0.88884841 | L10: 0.92951656 | M10: 0.96988374 | N10: 1.0100435 | O10: 1.049978 | S10: 0.9 | T10: 179.37768 | U10: 196.65257 | V10: 213.92106 | W10: 231.18393 | X10: 248.43922 | Y10: 265.69399 | Z10: 282.9442 | AA10: 300.19187 | AB10: 317.43709
A11: NPV, mln USD | B11: =NPV!C11/1000000 -> 415.40684 | F11: 0.95 | G11: 0.89909028 | H11: 0.95154289 | I11: 1.0037205 | J11: 1.0555904 | K11: 1.1071878 | L11: 1.1585571 | M11: 1.209556 | N11: 1.2603146 | O11: 1.3108634 | S11: 0.95 | T11: 246.26957 | U11: 267.69663 | V11: 289.12013 | W11: 310.53885 | X11: 331.95603 | Y11: 353.37016 | Z11: 374.77742 | AA11: 396.18378 | AB11: 417.58961
A12: IRR, % | B12: =NPV!C12 -> 1.3290017 | F12: 1 | G12: 1.0769928 | H12: 1.1404982 | I12: 1.2035974 | J12: 1.2664137 | K12: 1.3290017 | L12: 1.3911396 | M12: 1.4529995 | N12: 1.514662 | O12: 1.5760659 | S12: 1 | T12: 313.08095 | U12: 338.66933 | V12: 364.24992 | W12: 389.82864 | X12: 415.40684 | Y12: 440.97758 | Z12: 466.54695 | AA12: 492.1199 | AB12: 517.68927
F13: 1.05 | G13: 1.256991 | H13: 1.3316834 | I13: 1.4058371 | J13: 1.4797416 | K13: 1.5533933 | L13: 1.6265602 | M13: 1.6993628 | N13: 1.7719144 | O13: 1.8442117 | S13: 1.05 | T13: 379.84825 | U13: 409.59807 | V13: 439.33812 | W13: 469.07869 | X13: 498.81874 | Y13: 528.55255 | Z13: 558.28369 | AA13: 588.01537 | AB13: 617.74652
F14: 1.1 | G14: 1.4386253 | H14: 1.5245448 | I14: 1.6099504 | J14: 1.6949375 | K14: 1.7796404 | L14: 1.8640744 | M14: 1.9481143 | N14: 2.0315953 | O14: 2.1147953 | S14: 1.1 | T14: 446.58583 | U14: 480.49656 | V14: 514.39832 | W14: 548.29921 | X14: 582.19958 | Y14: 616.09994 | Z14: 649.99764 | AA14: 683.89007 | AB14: 717.78199
F15: 1.15 | G15: 1.6215898 | H15: 1.7186733 | I15: 1.8154666 | J15: 1.9119466 | K15: 2.0076832 | L15: 2.1031178 | M15: 2.1982631 | N15: 2.2931027 | O15: 2.3873863 | S15: 1.15 | T15: 513.30198 | U15: 551.37156 | V15: 589.44114 | W15: 627.51044 | X15: 665.57033 | Y15: 703.63022 | Z15: 741.69011 | AA15: 779.74746 | AB15: 817.77976
F16: 1.2 | G16: 1.8056243 | H16: 1.9142462 | I16: 2.0221295 | J16: 2.1296996 | K16: 2.2369593 | L16: 2.3437879 | M16: 2.4500984 | N16: 2.5555954 | O16: 2.6607461 | S16: 1.2 | T16: 580.00636 | U16: 622.24271 | V16: 664.47058 | W16: 706.69897 | X16: 748.92684 | Y16: 791.14245 | Z16: 833.33933 | AA16: 875.53167 | AB16: 917.72041
G21: Объем продаж | T21: =G21 -> Объем продаж
D22: IRR минимум | F22: =F6 -> 0.25 | Q22: NPV минимум | S22: 0
D23: IRR текущая | F23: =B12 -> 1.3290017 | G23: 0.8 | H23: 0.85 | I23: 0.9 | J23: 0.95 | K23: 1 | L23: 1.05 | M23: 1.1 | N23: 1.15 | O23: 1.2 | Q23: NPV текущая | S23: =B11 -> 415.40684 | T23: 0.8 | U23: 0.85 | V23: 0.9 | W23: 0.95 | X23: 1 | Y23: 1.05 | Z23: 1.1 | AA23: 1.15 | AB23: 1.2
D24: =A8 -> Стоимость сырья | F24: 0.8 | G24: 1.5903774 | H24: 1.6866547 | I24: 1.7827411 | J24: 1.8786382 | K24: 1.9738622 | L24: 2.0688543 | M24: 2.1636288 | N24: 2.2582078 | O24: 2.3525224 | Q24: =D24 -> Стоимость сырья | S24: 0.8 | T24: 494.28842 | U24: 531.16862 | V24: 568.04935 | W24: 604.93008 | X24: 641.8014 | Y24: 678.67249 | Z24: 715.54306 | AA24: 752.41416 | AB24: 789.27912
F25: 0.85 | G25: 1.4597853 | H25: 1.5478908 | I25: 1.6353947 | J25: 1.7226711 | K25: 1.8097327 | L25: 1.8965931 | M25: 1.9828023 | N25: 2.0687808 | O25: 2.1545322 | S25: 0.85 | T25: 449.00371 | U25: 483.06505 | V25: 517.11635 | W25: 551.16711 | X25: 585.21788 | Y25: 619.26917 | Z25: 653.31137 | AA25: 687.35394 | AB25: 721.39598
F26: 0.9 | G26: 1.3306792 | H26: 1.4102766 | I26: 1.4896596 | J26: 1.5687922 | K26: 1.6473765 | L26: 1.725727 | M26: 1.8038509 | N26: 1.8817556 | O26: 1.9592736 | S26: 0.9 | T26: 403.71255 | U26: 434.94344 | V26: 466.17434 | W26: 497.40415 | X26: 528.62548 | Y26: 559.84681 | Z26: 591.06814 | AA26: 622.28947 | AB26: 653.50979
F27: 0.95 | G27: 1.2029552 | H27: 1.2744715 | I27: 1.3457024 | J27: 1.4164874 | K27: 1.4870375 | L27: 1.557369 | M27: 1.6272339 | N27: 1.6967727 | O27: 1.7661149 | S27: 0.95 | T27: 358.40404 | U27: 386.81395 | V27: 415.22165 | W27: 443.62204 | X27: 472.02191 | Y27: 500.4223 | Z27: 528.81634 | AA27: 557.20771 | AB27: 585.60267
F28: 1 | G28: 1.0769928 | H28: 1.1404982 | I28: 1.2035974 | J28: 1.2664137 | K28: 1.3290017 | L28: 1.3911396 | M28: 1.4529995 | N28: 1.514662 | O28: 1.5760659 | S28: 1 | T28: 313.08095 | U28: 338.66933 | V28: 364.24992 | W28: 389.82864 | X28: 415.40684 | Y28: 440.97758 | Z28: 466.54695 | AA28: 492.1199 | AB28: 517.68927
F29: 1.05 | G29: 0.95292157 | H29: 1.0085184 | I29: 1.0637486 | J29: 1.1186807 | K29: 1.1733646 | L29: 1.2276329 | M29: 1.2816698 | N29: 1.3355083 | O29: 1.3889502 | S29: 1.05 | T29: 267.73583 | U29: 290.50113 | V29: 313.2595 | W29: 336.01429 | X29: 358.76844 | Y29: 381.51493 | Z29: 404.26142 | AA29: 427.01097 | AB29: 449.75252
F30: 1.1 | G30: 0.83091657 | H30: 0.87878359 | I30: 0.92638375 | J30: 0.97358609 | K30: 1.0205575 | L30: 1.0671817 | M30: 1.1135489 | N30: 1.1596695 | O30: 1.2054674 | S30: 1.1 | T30: 222.36067 | U30: 242.30126 | V30: 262.24104 | W30: 282.17127 | X30: 302.10204 | Y30: 322.0265 | Z30: 341.95182 | AA30: 361.87408 | AB30: 381.79169
F31: 1.15 | G31: 0.71094636 | H31: 0.75146103 | I31: 0.79161842 | J31: 0.83145157 | K31: 0.87093314 | L31: 0.91014035 | M31: 0.94908509 | N31: 0.9877002 | O31: 1.0260953 | S31: 1.15 | T31: 176.93451 | U31: 194.05781 | V31: 211.17525 | W31: 228.28822 | X31: 245.39429 | Y31: 262.49839 | Z31: 279.60202 | AA31: 296.69771 | AB31: 313.79341
F32: 1.2 | G32: 0.59285492 | H32: 0.62640595 | I32: 0.65953722 | J32: 0.6922877 | K32: 0.72472355 | L32: 0.75683722 | M32: 0.78864943 | N32: 0.82015933 | O32: 0.85143692 | S32: 1.2 | T32: 131.43259 | U32: 145.74119 | V32: 160.04138 | W32: 174.33432 | X32: 188.62424 | Y32: 202.91032 | Z32: 217.19005 | AA32: 231.46489 | AB32: 245.73928
G35: =A7 -> Цена | T35: =G35 -> Цена
D36: IRR минимум | F36: =F6 -> 0.25 | Q36: NPV минимум | S36: 0
D37: IRR текущая | F37: =B12 -> 1.3290017 | G37: 0.8 | H37: 0.85 | I37: 0.9 | J37: 0.95 | K37: 1 | L37: 1.05 | M37: 1.1 | N37: 1.15 | O37: 1.2 | Q37: NPV текущая | S37: =B11 -> 415.40684 | T37: 0.8 | U37: 0.85 | V37: 0.9 | W37: 0.95 | X37: 1 | Y37: 1.05 | Z37: 1.1 | AA37: 1.15 | AB37: 1.2
D38: =A8 -> Стоимость сырья | F38: 0.8 | G38: 1.0616359 | H38: 1.2864739 | I38: 1.5138741 | J38: 1.7430432 | K38: 1.9738622 | L38: 2.2057547 | M38: 2.4387464 | N38: 2.671514 | O38: 2.9054288 | Q38: =D38 -> Стоимость сырья | S38: 0.8 | T38: 308.17351 | U38: 391.62997 | V38: 475.04605 | W38: 558.42956 | X38: 641.8014 | Y38: 725.15791 | Z38: 808.48902 | AA38: 891.76728 | AB38: 975.04553
F39: 0.85 | G39: 0.90731443 | H39: 1.1288901 | I39: 1.3536776 | J39: 1.5808699 | K39: 1.8097327 | L39: 2.040045 | M39: 2.2716649 | N39: 2.50384 | O39: 2.7362977 | S39: 0.85 | T39: 251.48362 | U39: 334.98708 | V39: 418.43183 | W39: 501.8397 | X39: 585.21788 | Y39: 668.58326 | Z39: 751.93671 | AA39: 835.24456 | AB39: 918.52282
F40: 0.9 | G40: 0.75623861 | H40: 0.97415794 | I40: 1.1958589 | J40: 1.4204897 | K40: 1.6473765 | L40: 1.876165 | M40: 2.1059254 | N40: 2.337355 | O40: 2.5687094 | S40: 0.9 | T40: 194.73433 | U40: 278.31245 | V40: 361.79786 | W40: 445.22866 | X40: 528.62548 | Y40: 612.00672 | Z40: 695.36259 | AA40: 778.7191 | AB40: 862.00369
F41: 0.95 | G41: 0.60831312 | H41: 0.82267479 | I41: 1.0408277 | J41: 1.2625326 | K41: 1.4870375 | L41: 1.7136476 | M41: 1.9420981 | N41: 2.1715678 | O41: 2.4025327 | S41: 0.95 | T41: 137.88337 | U41: 221.59278 | V41: 305.13887 | W41: 388.60362 | X41: 472.02191 | Y41: 555.4138 | Z41: 638.78794 | AA41: 722.14445 | AB41: 805.47951
F42: 1 | G42: 0.46234317 | H42: 0.67446322 | I42: 0.88884841 | J42: 1.1071878 | K42: 1.3290017 | L42: 1.5533933 | M42: 1.7796404 | N42: 2.0076832 | O42: 2.2369593 | S42: 1 | T42: 80.859546 | U42: 164.79315 | V42: 248.43922 | W42: 331.95603 | X42: 415.40684 | Y42: 498.81874 | Z42: 582.19958 | AA42: 665.57033 | AB42: 748.92684
F43: 1.05 | G43: 0.31364297 | H43: 0.52900847 | I43: 0.74022752 | J43: 0.95481098 | K43: 1.1733646 | L43: 1.3950593 | M43: 1.6192858 | N43: 1.845413 | O43: 2.0730027 | S43: 1.05 | T43: 23.455327 | U43: 107.85875 | V43: 191.67903 | W43: 275.27571 | X43: 358.76844 | Y43: 442.20452 | Z43: 525.60665 | AA43: 608.9879 | AB43: 692.35219
F44: 1.1 | G44: 0.14671167 | H44: 0.38375032 | I44: 0.5947582 | J44: 0.8057122 | K44: 1.0205575 | L44: 1.2391906 | M44: 1.4608461 | N44: 1.6848735 | O44: 1.9109534 | S44: 1.1 | T44: -35.061972 | U44: 50.676526 | V44: 134.81359 | W44: 218.54614 | X44: 302.10204 | Y44: 385.57473 | Z44: 468.99828 | AA44: 552.3955 | AB44: 635.77674
F45: 1.15 | G45: -0.16058902 | H45: 0.23012216 | I45: 0.45108837 | J45: 0.65993887 | K45: 0.87093314 | L45: 1.0860542 | M45: 1.3048551 | N45: 1.5264518 | O45: 1.7502215 | S45: 1.15 | T45: -103.68231 | U45: -7.1437651 | V45: 77.764143 | W45: 161.73383 | X45: 245.39429 | Y45: 328.9214 | Z45: 412.38049 | AA45: 495.79459 | AB45: 579.18382
F46: 1.2 | G46: #NUM! | H46: 0.034972226 | I46: 0.30434449 | J46: 0.51684649 | K46: 0.72472355 | L46: 0.93600912 | M46: 1.1514018 | N46: 1.3702556 | O46: 1.5918627 | S46: 1.2 | T46: -186.8598 | U46: -67.974252 | V46: 20.316349 | W46: 104.78073 | X46: 188.62424 | Y46: 272.23643 | Z46: 355.73856 | AA46: 439.1809 | AB46: 522.59141
D49: 2. Однофакторный анализ
G50: CAPEX | T50: =G50 -> CAPEX
D51: IRR минимум | F51: =F6 -> 0.25 | Q51: NPV минимум | S51: 0
D52: IRR текущая | F52: =B12 -> 1.3290017 | G52: 0.8 | H52: 0.85 | I52: 0.9 | J52: 0.95 | K52: 1 | L52: 1.05 | M52: 1.1 | N52: 1.15 | O52: 1.2 | Q52: NPV текущая | S52: =B11 -> 415.40684 | T52: 0.8 | U52: 0.85 | V52: 0.9 | W52: 0.95 | X52: 1 | Y52: 1.05 | Z52: 1.1 | AA52: 1.15 | AB52: 1.2
F53: =F52 -> 1.3290017 | G53: 1.360834 | H53: 1.3527878 | I53: 1.344769 | J53: 1.3368447 | K53: 1.3290017 | L53: 1.3210485 | M53: 1.3132094 | N53: 1.3054865 | O53: 1.2977291 | S53: =S52 -> 415.40684 | T53: 416.91481 | U53: 416.54043 | V53: 416.16407 | W53: 415.78562 | X53: 415.40684 | Y53: 415.01981 | Z53: 414.63279 | AA53: 414.24628 | AB53: 413.85476
G56: =A6 -> Объем переработки | T56: =G56 -> Объем переработки
D57: IRR минимум | F57: =F6 -> 0.25 | Q57: NPV минимум | S57: 0
D58: IRR текущая | F58: =B12 -> 1.3290017 | G58: 0.8 | H58: 0.85 | I58: 0.9 | J58: 0.95 | K58: 1 | L58: 1.05 | M58: 1.1 | N58: 1.15 | O58: 1.2 | Q58: NPV текущая | S58: =S52 -> 415.40684 | T58: 0.8 | U58: 0.85 | V58: 0.9 | W58: 0.95 | X58: 1 | Y58: 1.05 | Z58: 1.1 | AA58: 1.15 | AB58: 1.2
D59: =B6 -> 1 | F59: =F58 -> 1.3290017 | G59: 1.0769928 | H59: 1.1404982 | I59: 1.2035974 | J59: 1.2664137 | K59: 1.3290017 | L59: 1.3911396 | M59: 1.4529995 | N59: 1.514662 | O59: 1.5760659 | Q59: =D59 -> 1 | S59: =S58 -> 415.40684 | T59: 313.08095 | U59: 338.66933 | V59: 364.24992 | W59: 389.82864 | X59: 415.40684 | Y59: 440.97758 | Z59: 466.54695 | AA59: 492.1199 | AB59: 517.68927
G62: Цена | T62: =G62 -> Цена
D63: IRR минимум | F63: =F6 -> 0.25 | Q63: NPV минимум | S63: 0
D64: IRR текущая | F64: =B12 -> 1.3290017 | G64: 0.8 | H64: 0.85 | I64: 0.9 | J64: 0.95 | K64: 1 | L64: 1.05 | M64: 1.1 | N64: 1.15 | O64: 1.2 | Q64: NPV текущая | S64: =S52 -> 415.40684 | T64: 0.8 | U64: 0.85 | V64: 0.9 | W64: 0.95 | X64: 1 | Y64: 1.05 | Z64: 1.1 | AA64: 1.15 | AB64: 1.2
D65: =B10 -> 0 | F65: =F64 -> 1.3290017 | G65: 0.46234317 | H65: 0.67446322 | I65: 0.88884841 | J65: 1.1071878 | K65: 1.3290017 | L65: 1.5533933 | M65: 1.7796404 | N65: 2.0076832 | O65: 2.2369593 | Q65: =D65 -> 0 | S65: =S64 -> 415.40684 | T65: 80.859546 | U65: 164.79315 | V65: 248.43922 | W65: 331.95603 | X65: 415.40684 | Y65: 498.81874 | Z65: 582.19958 | AA65: 665.57033 | AB65: 748.92684
G68: =A8 -> Стоимость сырья | T68: =G68 -> Стоимость сырья
D69: IRR минимум | F69: =F6 -> 0.25 | Q69: NPV минимум | S69: 0
D70: IRR текущая | F70: =B12 -> 1.3290017 | G70: 0.8 | H70: 0.85 | I70: 0.9 | J70: 0.95 | K70: 1 | L70: 1.05 | M70: 1.1 | N70: 1.15 | O70: 1.2 | Q70: NPV текущая | S70: =S52 -> 415.40684 | T70: 0.8 | U70: 0.85 | V70: 0.9 | W70: 0.95 | X70: 1 | Y70: 1.05 | Z70: 1.1 | AA70: 1.15 | AB70: 1.2
D71: =B15 -> 0 | F71: =F70 -> 1.3290017 | G71: 1.9738622 | H71: 1.8097327 | I71: 1.6473765 | J71: 1.4870375 | K71: 1.3290017 | L71: 1.1733646 | M71: 1.0205575 | N71: 0.87093314 | O71: 0.72472355 | Q71: =D71 -> 0 | S71: =S70 -> 415.40684 | T71: 641.8014 | U71: 585.21788 | V71: 528.62548 | W71: 472.02191 | X71: 415.40684 | Y71: 358.76844 | Z71: 302.10204 | AA71: 245.39429 | AB71: 188.62424
